Workbook

Sheet Guide
A1: SONCHOY 360°: Personal Finance Command Center
A2: Version 1.0 - all amounts in BDT (Bangladeshi Taka, with lakh/crore digit grouping) - works in Microsoft Excel and Google Sheets
A4: WHAT IS SONCHOY?
A5: Name | B5: Sonchoy (সঞ্চয়) means 'savings' in Bangla. This workbook is a complete personal finance system built around how money actually works in Bangladesh: bKash/Nagad payments, lakh/crore numbers, DPS/FDR/Sanchayapatra, Eid bonuses and Qurbani, Zakat, NBR income-tax slabs, and loan EMIs.
A7: QUICK START (about 5 minutes)
A8: Step 1 - Settings | B8: Open Settings. Enter your name, tracking year and targets (savings rate, emergency-fund months, max debt-to-income). Review the tax slabs and exchange rates.
A9: Step 2 - Clear sample data | B9: The file ships with SAMPLE data (a fictional Dhaka salaried household, Jan-Oct 2026). In Transactions select the blue cells in rows 6 onward and press Delete. Also overwrite the sample rows in Savings Goals, Debt & Loans, Investments, Net Worth, Bills and Festivals.
A10: Step 3 - Set your budget | B10: Open Budget and type a planned monthly amount (blue) next to every category. Set 'Planned Monthly Income' underneath.
A11: Step 4 - Log transactions | B11: In Transactions add one row per payment or receipt: Date, Type (Income/Expense), Category (dropdown), Description, Payment Method, Amount in BDT. Everything else is automatic.
A12: Step 5 - Read the Dashboard | B12: Pick a month at the top of the Dashboard. KPI cards, the health scorecard, the budget status and all charts refresh automatically.
A13: Step 6 - Monthly routine | B13: At month-end: pay down priority goals, update Net Worth values and record the closing Net Worth in the history table, update Bills due dates.
A14: Google Sheets | B14: Upload the .xlsx to Google Drive and open with Google Sheets (File > Save as Google Sheets). Dropdowns, formulas, conditional formats and charts carry over; the lakh/crore format may show Western commas in Sheets.
A16: SHEET DIRECTORY (click a name to jump)
A17: Guide | B17: This page.
A18: Dashboard | B18: Headline KPIs, financial-health scorecard, top outflows and four charts. Pick the month here.
A19: Transactions | B19: The only place you must type daily: every income and expense (2,000-row capacity).
A20: Budget | B20: Monthly budget vs actual per category, status flags, YTD view and the 50/30/20 rule check.
A21: Annual Matrix | B21: Automatic category x month table for the whole year with annual budget variance.
A22: Monthly Summary | B22: Income, spending, net savings, savings rate and cumulative savings for each month.
A23: Savings Goals | B23: Hajj, education, flat, emergency fund and more: required monthly saving, projected value, on-track status.
A24: Debt & Loans | B24: EMI, outstanding balance, interest cost, payoff date, avalanche priority and debt-to-income check.
A25: Investments | B25: DPS, FDR and Sanchayapatra maturity, source tax, net and real (inflation-adjusted) returns.
A26: Net Worth | B26: Assets (incl. gold by bhori) minus liabilities, emergency-fund coverage and net-worth history chart.
A27: Income Tax | B27: NBR slab-based individual tax estimator with exempt salary, investment rebate and minimum tax.
A28: Zakat | B28: Nisab-based Zakat calculator (silver or gold basis) pulling balances from Net Worth.
... A32: Settings | B32: All dropdown lists, categories, tax parameters, FX rates and fee tables. Rename a category once and it updates everywhere.
A34: COLOUR CODE
A35: 1,25,000 | B35: Blue text on pale yellow = INPUT cell. Type here (amounts, dates, rates, assumptions).
A36: =1+1 -> 2 | B36: Black text = FORMULA on the same sheet. Do not overwrite.
A37: =Settings!$B$5 -> 2026 | B37: Green text = value LINKED from another sheet. Do not overwrite.
A38: OVER | B38: Red = over budget / below target / warning. Amber = watch. Green fill = healthy / on track.
A39: TOTAL | B39: Pale green band = totals and key results. Dark bands = section headers.
A41: BANGLADESH-SPECIFIC FEATURES
A42: Feature 1 | B42: Lakh / crore digit grouping (12,34,567) on all BDT amounts; Quick Tools converts BDT to lakh / crore / million.
A43: Feature 2 | B43: Category set built for local life: DESCO / DPDC / REB electricity, Titas gas, WASA, broadband, Rickshaw / CNG / Pathao, bazar, maid, holding tax, Zakat & Fitra, Qurbani, Eid / Boishakh / Puja.
A44: Feature 3 | B44: bKash, Nagad, Rocket, Upay, BEFTN, cheque and auto-debit payment methods; MFS cash-out fee calculator.
A45: Feature 4 | B45: DPS, FDR and Sanchayapatra maturity with source tax (10% with TIN) and real yield after inflation.
A46: Feature 5 | B46: NBR individual income-tax slabs with category thresholds (general, women/senior, disabled, freedom fighter), minimum tax and investment rebate.
A47: Feature 6 | B47: Eid bonus income category, Eid-ul-Fitr / Eid-ul-Adha / Boishakh / Puja planner, Fitra and Qurbani-share calculators.
A48: Feature 7 | B48: Zakat on cash, gold (bhori / tola), silver, shares and savings with silver or gold nisab.
A49: Feature 8 | B49: Gold valued per bhori (11.664 g); remittance calculator with government cash incentive; USD, SAR, AED, GBP, EUR, MYR, KWD, INR.
A50: Feature 9 | B50: Home / car / motorcycle / personal / credit-card / microfinance loan types with EMI and debt-avalanche priority.
A52: ASSUMPTIONS, SOURCES & DISCLAIMER
A53: Sample data | B53: All names, balances, transactions, loans and investments are fictional illustrations created for this template. Delete or overwrite them.
A54: Tax figures | B54: Slabs and thresholds (general Tk 3,75,000; women/65+ Tk 4,25,000; disabled/third gender Tk 5,00,000; freedom fighter Tk 5,25,000; rates 10/15/20/25/30%; minimum tax Tk 5,000) follow Bangladesh budget FY2026-27 press coverage (Daily Star, Dhaka Tribune, UNB, June 2026). Sources differ on some details and rules can change by Finance Act or NBR order - confirm with the NBR or a tax professional. All are editable in Settings. Salary-exemption cap and rebate percentages are standard-rule assumptions to verify.
A55: Rates & fees | B55: Interest rates (DPS 8.5%, FDR 9%, Sanchayapatra 11.52%), exchange rates, MFS fees, gold/silver prices, Fitra and Qurbani prices are illustrative placeholders. Replace with figures from your bank, the National Savings Directorate, BAJUS, Bangladesh Bank and your provider.
A56: Calculations | B56: Savings = Income - Spending (spending excludes deposits to DPS/FDR/shares/gold/emergency fund, which count as savings). EMI uses reducing-balance maths. Projections assume constant rates.
A57: Disclaimer | B57: Sonchoy is a planning and record-keeping tool. It is not financial, tax, legal or religious advice. Consult qualified professionals (including a scholar for Zakat) before making decisions.

Sheet Dashboard
B1: SONCHOY 360°: Personal Finance Command Center
B2: ="Prepared for "&Settings!$B$4&" | Tracking year "&Settings!$B$5&" | All amounts in BDT (Bangladeshi Taka)" -> Prepared for Your Name | Tracking year 2026 | All amounts in BDT (Bangladeshi Taka)
B4: VIEW MONTH > | D4: February | G4: Pick any month - KPIs, budget status and the breakdown charts update instantly.
B6: MONTH INCOME (BDT) | D6: MONTH SPENDING (BDT) | F6: MONTH NET SAVINGS (BDT) | H6: MONTH SAVINGS RATE | J6: YEAR-TO-DATE SAVINGS (BDT) | L6: NET WORTH (BDT)
B7: =INDEX('Monthly Summary'!$B$5:$B$16,Settings!$B$11) -> 128330 | D7: =INDEX('Monthly Summary'!$E$5:$E$16,Settings!$B$11) -> 94240 | F7: =INDEX('Monthly Summary'!$F$5:$F$16,Settings!$B$11) -> 34090 | H7: =INDEX('Monthly Summary'!$G$5:$G$16,Settings!$B$11) -> 0.26564326 | J7: ='Monthly Summary'!$F$17 -> 468924 | L7: ='Net Worth'!$C$25 -> 2100008
B8: =$D$4&" "&Settings!$B$5 -> February 2026 | D8: Excludes savings & investments | F8: Income - Spending | H8: ="Target "&TEXT(Settings!$B$7,"0%") -> Target 20% | J8: Jan to latest month | L8: Assets - Liabilities
B10: BUDGET USED (MONTH) | D10: EMERGENCY FUND (MONTHS) | F10: DEBT-TO-INCOME | H10: AVG MONTHLY INCOME (BDT) | J10: AVG MONTHLY SPENDING (BDT) | L10: SAVINGS GOALS PROGRESS
B11: =Budget!$G$47 -> 0.96243999 | D11: ='Net Worth'!$C$27 -> 2.8618897 | F11: ='Debt & Loans'!$C$21 -> 0.12884348 | H11: ='Monthly Summary'!$B$19 -> 140187.4 | J11: ='Monthly Summary'!$E$19 -> 93295 | L11: ='Savings Goals'!$I$18 -> 0.14641211
B12: All outflows vs total budget | D12: ="Target "&Settings!$B$8&" months" -> Target 6 months | F12: ="Max "&TEXT(Settings!$B$9,"0%") -> Max 40% | H12: Months with income | J12: Months with income | L12: Across all goals
B14: FINANCIAL HEALTH SCORECARD | H14: TOP 5 OUTFLOWS THIS MONTH
B15: Check | D15: Your Value | E15: Target | F15: Status | H15: Category | K15: Amount (BDT) | M15: % of Total
B16: Savings rate (YTD) | D16: ='Monthly Summary'!$G$17 -> 0.33449796 | E16: =Settings!$B$7 -> 0.2 | F16: =IF(D16>=E16,"GOOD",IF(D16>=E16*0.6,"IMPROVE","WARNING")) -> GOOD | H16: =IFERROR(IF(LARGE(Budget!$M$6:$M$46,1)<1,"-",INDEX(Budget!$A$6:$A$46,MATCH(LARGE(Budget!$M$6:$M$46,1),Budget!$M$6:$M$46,0))),"-") -> House Rent | K16: =IFERROR(IF(LARGE(Budget!$M$6:$M$46,1)<1,0,INDEX(Budget!$E$6:$E$46,MATCH(LARGE(Budget!$M$6:$M$46,1),Budget!$M$6:$M$46,0))),0) -> 22000 | M16: =IF(Budget!$E$47=0,0,K16/Budget!$E$47) -> 0.21517997
B17: Emergency fund (months) | D17: ='Net Worth'!$C$27 -> 2.8618897 | E17: =Settings!$B$8 -> 6 | F17: =IF(D17>=E17,"GOOD",IF(D17>=E17/2,"IMPROVE","WARNING")) -> WARNING | H17: =IFERROR(IF(LARGE(Budget!$M$6:$M$46,2)<1,"-",INDEX(Budget!$A$6:$A$46,MATCH(LARGE(Budget!$M$6:$M$46,2),Budget!$M$6:$M$46,0))),"-") -> Loan EMI | K17: =IFERROR(IF(LARGE(Budget!$M$6:$M$46,2)<1,0,INDEX(Budget!$E$6:$E$46,MATCH(LARGE(Budget!$M$6:$M$46,2),Budget!$M$6:$M$46,0))),0) -> 15300 | M17: =IF(Budget!$E$47=0,0,K17/Budget!$E$47) -> 0.14964789
B18: Debt-to-income ratio | D18: ='Debt & Loans'!$C$21 -> 0.12884348 | E18: =Settings!$B$9 -> 0.4 | F18: =IF(D18<=E18,"GOOD",IF(D18<=E18*1.25,"IMPROVE","WARNING")) -> GOOD | H18: =IFERROR(IF(LARGE(Budget!$M$6:$M$46,3)<1,"-",INDEX(Budget!$A$6:$A$46,MATCH(LARGE(Budget!$M$6:$M$46,3),Budget!$M$6:$M$46,0))),"-") -> Travel & Holidays | K18: =IFERROR(IF(LARGE(Budget!$M$6:$M$46,3)<1,0,INDEX(Budget!$E$6:$E$46,MATCH(LARGE(Budget!$M$6:$M$46,3),Budget!$M$6:$M$46,0))),0) -> 12000 | M18: =IF(Budget!$E$47=0,0,K18/Budget!$E$47) -> 0.11737089
B19: Needs share of income (month) | D19: =Budget!$D$59 -> 0.6049248 | E19: =Settings!$B$12 -> 0.5 | F19: =IF(D19<=E19,"GOOD",IF(D19<=E19+0.1,"IMPROVE","WARNING")) -> WARNING | H19: =IFERROR(IF(LARGE(Budget!$M$6:$M$46,4)<1,"-",INDEX(Budget!$A$6:$A$46,MATCH(LARGE(Budget!$M$6:$M$46,4),Budget!$M$6:$M$46,0))),"-") -> Groceries & Bazar | K19: =IFERROR(IF(LARGE(Budget!$M$6:$M$46,4)<1,0,INDEX(Budget!$E$6:$E$46,MATCH(LARGE(Budget!$M$6:$M$46,4),Budget!$M$6:$M$46,0))),0) -> 11610 | M19: =IF(Budget!$E$47=0,0,K19/Budget!$E$47) -> 0.11355634
B20: Wants share of income (month) | D20: =Budget!$D$60 -> 0.12943193 | E20: =Settings!$B$13 -> 0.3 | F20: =IF(D20<=E20,"GOOD",IF(D20<=E20+0.1,"IMPROVE","WARNING")) -> GOOD | H20: =IFERROR(IF(LARGE(Budget!$M$6:$M$46,5)<1,"-",INDEX(Budget!$A$6:$A$46,MATCH(LARGE(Budget!$M$6:$M$46,5),Budget!$M$6:$M$46,0))),"-") -> DPS Deposit | K20: =IFERROR(IF(LARGE(Budget!$M$6:$M$46,5)<1,0,INDEX(Budget!$E$6:$E$46,MATCH(LARGE(Budget!$M$6:$M$46,5),Budget!$M$6:$M$46,0))),0) -> 5000 | M20: =IF(Budget!$E$47=0,0,K20/Budget!$E$47) -> 0.048904538
B21: Categories over budget (month) | D21: =COUNTIF(Budget!$H$6:$H$46,"OVER") -> 5 | E21: 0 | F21: =IF(D21=0,"GOOD",IF(D21<=3,"IMPROVE","WARNING")) -> WARNING | H21: Total outflow this month | K21: =Budget!$E$47 -> 102240 | M21: =IF(K21=0,0,1) -> 1
B22: ="Health score: "&COUNTIF(F16:F21,"GOOD")&" of 6 checks are GOOD" -> Health score: 3 of 6 checks are GOOD
B23: TRENDS & BREAKDOWN
M26: CHART DATA (automatic - do not edit)
M27: Expense Group | N27: Budget (BDT) | O27: Actual (BDT)
M28: =Settings!$O$4 -> Housing & Utilities | N28: =SUMIF(Budget!$B$6:$B$46,M28,Budget!$D$6:$D$46) -> 32180 | O28: =SUMIF(Budget!$B$6:$B$46,M28,Budget!$E$6:$E$46) -> 30610
M29: =Settings!$O$5 -> Food | N29: =SUMIF(Budget!$B$6:$B$46,M29,Budget!$D$6:$D$46) -> 13000 | O29: =SUMIF(Budget!$B$6:$B$46,M29,Budget!$E$6:$E$46) -> 12670
M30: =Settings!$O$6 -> Transport | N30: =SUMIF(Budget!$B$6:$B$46,M30,Budget!$D$6:$D$46) -> 5300 | O30: =SUMIF(Budget!$B$6:$B$46,M30,Budget!$E$6:$E$46) -> 3090
M31: =Settings!$O$7 -> Family & Education | N31: =SUMIF(Budget!$B$6:$B$46,M31,Budget!$D$6:$D$46) -> 9500 | O31: =SUMIF(Budget!$B$6:$B$46,M31,Budget!$E$6:$E$46) -> 8500
M32: =Settings!$O$8 -> Health | N32: =SUMIF(Budget!$B$6:$B$46,M32,Budget!$D$6:$D$46) -> 2000 | O32: =SUMIF(Budget!$B$6:$B$46,M32,Budget!$E$6:$E$46) -> 1770
M33: =Settings!$O$9 -> Lifestyle | N33: =SUMIF(Budget!$B$6:$B$46,M33,Budget!$D$6:$D$46) -> 6900 | O33: =SUMIF(Budget!$B$6:$B$46,M33,Budget!$E$6:$E$46) -> 15550
M34: =Settings!$O$10 -> Religious & Social | N34: =SUMIF(Budget!$B$6:$B$46,M34,Budget!$D$6:$D$46) -> 5500 | O34: =SUMIF(Budget!$B$6:$B$46,M34,Budget!$E$6:$E$46) -> 0
M35: =Settings!$O$11 -> Financial Obligations | N35: =SUMIF(Budget!$B$6:$B$46,M35,Budget!$D$6:$D$46) -> 21350 | O35: =SUMIF(Budget!$B$6:$B$46,M35,Budget!$E$6:$E$46) -> 22050
M36: =Settings!$O$12 -> Savings & Investments | N36: =SUMIF(Budget!$B$6:$B$46,M36,Budget!$D$6:$D$46) -> 9500 | O36: =SUMIF(Budget!$B$6:$B$46,M36,Budget!$E$6:$E$46) -> 8000
M37: =Settings!$O$13 -> Other | N37: =SUMIF(Budget!$B$6:$B$46,M37,Budget!$D$6:$D$46) -> 1000 | O37: =SUMIF(Budget!$B$6:$B$46,M37,Budget!$E$6:$E$46) -> 0
B56: Sonchoy is a planning aid, not financial, tax or religious advice. Verify tax, rate and fee assumptions in Settings. Go to the Guide tab for instructions.

Sheet Transactions
A1: TRANSACTION LOG | লেনদেন
A2: Log every taka in or out. Fill only the blue cells; Group, Month, Year and Check are automatic. ROWS BELOW CONTAIN SAMPLE DATA (Jan-Oct 2026): select the blue cells and press Delete to start fresh.
A4: Entries logged: | B4: =COUNT(G6:G2005) -> 300 | D4: Capacity: 2,000 rows. Insert rows inside the table (not below row 2005) to extend.
A5: Date | B5: Type | C5: Category | D5: Description | E5: Payment Method | F5: Paid To / Received From | G5: Amount (BDT) | H5: Group | I5: Month # | J5: Year | K5: Notes | L5: Check
A6: 46023 | B6: Income | C6: Salary | D6: Salary - January | E6: Bank Transfer / BEFTN | F6: Employer Ltd. | G6: 115000 | H6: =IF(C6="","",IFERROR(INDEX(Settings!$L$4:$L$56,MATCH(C6,Settings!$K$4:$K$56,0)),"Unknown")) -> Income | I6: =IF(A6="","",MONTH(A6)) -> 1 | J6: =IF(A6="","",YEAR(A6)) -> 2026 | L6: =IF(OR(B6="",C6=""),"",IF(AND(B6="Income",H6<>"Income"),"Category is not an Income category",IF(AND(B6="Expense",H6="Income"),"Category is an Income category","OK"))) -> OK
A7: 46024 | B7: Expense | C7: Entertainment & Subscriptions | D7: Netflix / Chorki subscription | E7: Credit Card | F7: Streaming | G7: 1100 | H7: =IF(C7="","",IFERROR(INDEX(Settings!$L$4:$L$56,MATCH(C7,Settings!$K$4:$K$56,0)),"Unknown")) -> Lifestyle | I7: =IF(A7="","",MONTH(A7)) -> 1 | J7: =IF(A7="","",YEAR(A7)) -> 2026 | L7: =IF(OR(B7="",C7=""),"",IF(AND(B7="Income",H7<>"Income"),"Category is not an Income category",IF(AND(B7="Expense",H7="Income"),"Category is an Income category","OK"))) -> OK
A8: 46025 | B8: Expense | C8: House Rent | D8: House rent - January | E8: Bank Transfer / BEFTN | F8: Landlord | G8: 22000 | H8: =IF(C8="","",IFERROR(INDEX(Settings!$L$4:$L$56,MATCH(C8,Settings!$K$4:$K$56,0)),"Unknown")) -> Housing & Utilities | I8: =IF(A8="","",MONTH(A8)) -> 1 | J8: =IF(A8="","",YEAR(A8)) -> 2026 | L8: =IF(OR(B8="",C8=""),"",IF(AND(B8="Income",H8<>"Income"),"Category is not an Income category",IF(AND(B8="Expense",H8="Income"),"Category is an Income category","OK"))) -> OK
A9: 46026 | B9: Expense | C9: Groceries & Bazar | D9: Kacha bazar & grocery | E9: Cash | F9: Local bazar | G9: 3520 | H9: =IF(C9="","",IFERROR(INDEX(Settings!$L$4:$L$56,MATCH(C9,Settings!$K$4:$K$56,0)),"Unknown")) -> Food | I9: =IF(A9="","",MONTH(A9)) -> 1 | J9: =IF(A9="","",YEAR(A9)) -> 2026 | L9: =IF(OR(B9="",C9=""),"",IF(AND(B9="Income",H9<>"Income"),"Category is not an Income category",IF(AND(B9="Expense",H9="Income"),"Category is an Income category","OK"))) -> OK
A10: 46027 | B10: Expense | C10: Maid / Domestic Help | D10: Maid salary | E10: Cash | F10: Domestic help | G10: 3000 | H10: =IF(C10="","",IFERROR(INDEX(Settings!$L$4:$L$56,MATCH(C10,Settings!$K$4:$K$56,0)),"Unknown")) -> Housing & Utilities | I10: =IF(A10="","",MONTH(A10)) -> 1 | J10: =IF(A10="","",YEAR(A10)) -> 2026 | L10: =IF(OR(B10="",C10=""),"",IF(AND(B10="Income",H10<>"Income"),"Category is not an Income category",IF(AND(B10="Expense",H10="Income"),"Category is an Income category","OK"))) -> OK
A11: 46027 | B11: Expense | C11: Loan EMI | D11: Loan EMI (personal + motorcycle) | E11: Auto-debit / Standing Order | F11: Bank | G11: 15300 | H11: =IF(C11="","",IFERROR(INDEX(Settings!$L$4:$L$56,MATCH(C11,Settings!$K$4:$K$56,0)),"Unknown")) -> Financial Obligations | I11: =IF(A11="","",MONTH(A11)) -> 1 | J11: =IF(A11="","",YEAR(A11)) -> 2026 | L11: =IF(OR(B11="",C11=""),"",IF(AND(B11="Income",H11<>"Income"),"Category is not an Income category",IF(AND(B11="Expense",H11="Income"),"Category is an Income category","OK"))) -> OK
A12: 46027 | B12: Expense | C12: DPS Deposit | D12: Monthly DPS instalment | E12: Auto-debit / Standing Order | F12: Dutch-Bangla Bank | G12: 5000 | H12: =IF(C12="","",IFERROR(INDEX(Settings!$L$4:$L$56,MATCH(C12,Settings!$K$4:$K$56,0)),"Unknown")) -> Savings & Investments | I12: =IF(A12="","",MONTH(A12)) -> 1 | J12: =IF(A12="","",YEAR(A12)) -> 2026 | L12: =IF(OR(B12="",C12=""),"",IF(AND(B12="Income",H12<>"Income"),"Category is not an Income category",IF(AND(B12="Expense",H12="Income"),"Category is an Income category","OK"))) -> OK
A13: 46027 | B13: Expense | C13: School / College / University Fees | D13: School tuition fee | E13: Bank Transfer / BEFTN | F13: Child's school | G13: 3500 | H13: =IF(C13="","",IFERROR(INDEX(Settings!$L$4:$L$56,MATCH(C13,Settings!$K$4:$K$56,0)),"Unknown")) -> Family & Education | I13: =IF(A13="","",MONTH(A13)) -> 1 | J13: =IF(A13="","",YEAR(A13)) -> 2026 | L13: =IF(OR(B13="",C13=""),"",IF(AND(B13="Income",H13<>"Income"),"Category is not an Income category",IF(AND(B13="Expense",H13="Income"),"Category is an Income category","OK"))) -> OK
A14: 46028 | B14: Expense | C14: Internet / Broadband | D14: Broadband bill | E14: bKash | F14: Link3 | G14: 1000 | H14: =IF(C14="","",IFERROR(INDEX(Settings!$L$4:$L$56,MATCH(C14,Settings!$K$4:$K$56,0)),"Unknown")) -> Housing & Utilities | I14: =IF(A14="","",MONTH(A14)) -> 1 | J14: =IF(A14="","",YEAR(A14)) -> 2026 | L14: =IF(OR(B14="",C14=""),"",IF(AND(B14="Income",H14<>"Income"),"Category is not an Income category",IF(AND(B14="Expense",H14="Income"),"Category is an Income category","OK"))) -> OK
A15: 46029 | B15: Expense | C15: Rickshaw / CNG / Ride-share | D15: Uber / Pathao rides | E15: bKash | F15: Pathao | G15: 940 | H15: =IF(C15="","",IFERROR(INDEX(Settings!$L$4:$L$56,MATCH(C15,Settings!$K$4:$K$56,0)),"Unknown")) -> Transport | I15: =IF(A15="","",MONTH(A15)) -> 1 | J15: =IF(A15="","",YEAR(A15)) -> 2026 | L15: =IF(OR(B15="",C15=""),"",IF(AND(B15="Income",H15<>"Income"),"Category is not an Income category",IF(AND(B15="Expense",H15="Income"),"Category is an Income category","OK"))) -> OK
A16: 46030 | B16: Expense | C16: Electricity (DESCO / DPDC / REB) | D16: Electricity bill (prepaid recharge) | E16: bKash | F16: DESCO | G16: 2150 | H16: =IF(C16="","",IFERROR(INDEX(Settings!$L$4:$L$56,MATCH(C16,Settings!$K$4:$K$56,0)),"Unknown")) -> Housing & Utilities | I16: =IF(A16="","",MONTH(A16)) -> 1 | J16: =IF(A16="","",YEAR(A16)) -> 2026 | L16: =IF(OR(B16="",C16=""),"",IF(AND(B16="Income",H16<>"Income"),"Category is not an Income category",IF(AND(B16="Expense",H16="Income"),"Category is an Income category","OK"))) -> OK
A17: 46031 | B17: Expense | C17: Mobile Recharge & Data | D17: Mobile recharge / data pack | E17: bKash | F17: Grameenphone | G17: 700 | H17: =IF(C17="","",IFERROR(INDEX(Settings!$L$4:$L$56,MATCH(C17,Settings!$K$4:$K$56,0)),"Unknown")) -> Housing & Utilities | I17: =IF(A17="","",MONTH(A17)) -> 1 | J17: =IF(A17="","",YEAR(A17)) -> 2026 | L17: =IF(OR(B17="",C17=""),"",IF(AND(B17="Income",H17<>"Income"),"Category is not an Income category",IF(AND(B17="Expense",H17="Income"),"Category is an Income category","OK"))) -> OK
... A305: 46315 | B305: Expense | C305: Personal Care & Salon | D305: Haircut & grooming | E305: Cash | F305: Salon | G305: 780 | H305: =IF(C305="","",IFERROR(INDEX(Settings!$L$4:$L$56,MATCH(C305,Settings!$K$4:$K$56,0)),"Unknown")) -> Lifestyle | I305: =IF(A305="","",MONTH(A305)) -> 10 | J305: =IF(A305="","",YEAR(A305)) -> 2026 | L305: =IF(OR(B305="",C305=""),"",IF(AND(B305="Income",H305<>"Income"),"Category is not an Income category",IF(AND(B305="Expense",H305="Income"),"Category is an Income category","OK"))) -> OK
H306: =IF(C306="","",IFERROR(INDEX(Settings!$L$4:$L$56,MATCH(C306,Settings!$K$4:$K$56,0)),"Unknown")) | I306: =IF(A306="","",MONTH(A306)) | J306: =IF(A306="","",YEAR(A306)) | L306: =IF(OR(B306="",C306=""),"",IF(AND(B306="Income",H306<>"Income"),"Category is not an Income category",IF(AND(B306="Expense",H306="Income"),"Category is an Income category","OK")))
H307: =IF(C307="","",IFERROR(INDEX(Settings!$L$4:$L$56,MATCH(C307,Settings!$K$4:$K$56,0)),"Unknown")) | I307: =IF(A307="","",MONTH(A307)) | J307: =IF(A307="","",YEAR(A307)) | L307: =IF(OR(B307="",C307=""),"",IF(AND(B307="Income",H307<>"Income"),"Category is not an Income category",IF(AND(B307="Expense",H307="Income"),"Category is an Income category","OK")))
H308: =IF(C308="","",IFERROR(INDEX(Settings!$L$4:$L$56,MATCH(C308,Settings!$K$4:$K$56,0)),"Unknown")) | I308: =IF(A308="","",MONTH(A308)) | J308: =IF(A308="","",YEAR(A308)) | L308: =IF(OR(B308="",C308=""),"",IF(AND(B308="Income",H308<>"Income"),"Category is not an Income category",IF(AND(B308="Expense",H308="Income"),"Category is an Income category","OK")))
H309: =IF(C309="","",IFERROR(INDEX(Settings!$L$4:$L$56,MATCH(C309,Settings!$K$4:$K$56,0)),"Unknown")) | I309: =IF(A309="","",MONTH(A309)) | J309: =IF(A309="","",YEAR(A309)) | L309: =IF(OR(B309="",C309=""),"",IF(AND(B309="Income",H309<>"Income"),"Category is not an Income category",IF(AND(B309="Expense",H309="Income"),"Category is an Income category","OK")))
H310: =IF(C310="","",IFERROR(INDEX(Settings!$L$4:$L$56,MATCH(C310,Settings!$K$4:$K$56,0)),"Unknown")) | I310: =IF(A310="","",MONTH(A310)) | J310: =IF(A310="","",YEAR(A310)) | L310: =IF(OR(B310="",C310=""),"",IF(AND(B310="Income",H310<>"Income"),"Category is not an Income category",IF(AND(B310="Expense",H310="Income"),"Category is an Income category","OK")))
H311: =IF(C311="","",IFERROR(INDEX(Settings!$L$4:$L$56,MATCH(C311,Settings!$K$4:$K$56,0)),"Unknown")) | I311: =IF(A311="","",MONTH(A311)) | J311: =IF(A311="","",YEAR(A311)) | L311: =IF(OR(B311="",C311=""),"",IF(AND(B311="Income",H311<>"Income"),"Category is not an Income category",IF(AND(B311="Expense",H311="Income"),"Category is an Income category","OK")))
H312: =IF(C312="","",IFERROR(INDEX(Settings!$L$4:$L$56,MATCH(C312,Settings!$K$4:$K$56,0)),"Unknown")) | I312: =IF(A312="","",MONTH(A312)) | J312: =IF(A312="","",YEAR(A312)) | L312: =IF(OR(B312="",C312=""),"",IF(AND(B312="Income",H312<>"Income"),"Category is not an Income category",IF(AND(B312="Expense",H312="Income"),"Category is an Income category","OK")))
H313: =IF(C313="","",IFERROR(INDEX(Settings!$L$4:$L$56,MATCH(C313,Settings!$K$4:$K$56,0)),"Unknown")) | I313: =IF(A313="","",MONTH(A313)) | J313: =IF(A313="","",YEAR(A313)) | L313: =IF(OR(B313="",C313=""),"",IF(AND(B313="Income",H313<>"Income"),"Category is not an Income category",IF(AND(B313="Expense",H313="Income"),"Category is an Income category","OK")))
H314: =IF(C314="","",IFERROR(INDEX(Settings!$L$4:$L$56,MATCH(C314,Settings!$K$4:$K$56,0)),"Unknown")) | I314: =IF(A314="","",MONTH(A314)) | J314: =IF(A314="","",YEAR(A314)) | L314: =IF(OR(B314="",C314=""),"",IF(AND(B314="Income",H314<>"Income"),"Category is not an Income category",IF(AND(B314="Expense",H314="Income"),"Category is an Income category","OK")))
H315: =IF(C315="","",IFERROR(INDEX(Settings!$L$4:$L$56,MATCH(C315,Settings!$K$4:$K$56,0)),"Unknown")) | I315: =IF(A315="","",MONTH(A315)) | J315: =IF(A315="","",YEAR(A315)) | L315: =IF(OR(B315="",C315=""),"",IF(AND(B315="Income",H315<>"Income"),"Category is not an Income category",IF(AND(B315="Expense",H315="Income"),"Category is an Income category","OK")))
H316: =IF(C316="","",IFERROR(INDEX(Settings!$L$4:$L$56,MATCH(C316,Settings!$K$4:$K$56,0)),"Unknown")) | I316: =IF(A316="","",MONTH(A316)) | J316: =IF(A316="","",YEAR(A316)) | L316: =IF(OR(B316="",C316=""),"",IF(AND(B316="Income",H316<>"Income"),"Category is not an Income category",IF(AND(B316="Expense",H316="Income"),"Category is an Income category","OK")))
H317: =IF(C317="","",IFERROR(INDEX(Settings!$L$4:$L$56,MATCH(C317,Settings!$K$4:$K$56,0)),"Unknown")) | I317: =IF(A317="","",MONTH(A317)) | J317: =IF(A317="","",YEAR(A317)) | L317: =IF(OR(B317="",C317=""),"",IF(AND(B317="Income",H317<>"Income"),"Category is not an Income category",IF(AND(B317="Expense",H317="Income"),"Category is an Income category","OK")))
... H2005: =IF(C2005="","",IFERROR(INDEX(Settings!$L$4:$L$56,MATCH(C2005,Settings!$K$4:$K$56,0)),"Unknown")) | I2005: =IF(A2005="","",MONTH(A2005)) | J2005: =IF(A2005="","",YEAR(A2005)) | L2005: =IF(OR(B2005="",C2005=""),"",IF(AND(B2005="Income",H2005<>"Income"),"Category is not an Income category",IF(AND(B2005="Expense",H2005="Income"),"Category is an Income category","OK")))

Sheet Budget
A1: BUDGET vs ACTUAL | বাজেট
A2: Enter your planned monthly amount per category (blue). Actuals come from the Transaction Log for the month picked on the Dashboard.
A3: Selected month (change on Dashboard) | B3: =Dashboard!$D$4 -> February
A5: Category | B5: Group | C5: Budget Type | D5: Monthly Budget (BDT) | E5: Actual - Selected Month | F5: Variance (Budget - Actual) | G5: % Used | H5: Status | I5: Annual Budget | J5: YTD Budget | K5: YTD Actual | L5: YTD Variance | M5: Rank key (helper)
A6: =Settings!$K$16 -> House Rent | B6: =Settings!$L$16 -> Housing & Utilities | C6: =Settings!$M$16 -> Needs | D6: 22000 | E6: =INDEX('Annual Matrix'!$C21:$N21,Settings!$B$11) -> 22000 | F6: =D6-E6 -> 0 | G6: =IF(D6=0,"",E6/D6) -> 1 | H6: =IF(D6=0,IF(E6>0,"Unbudgeted","-"),IF(E6>D6,"OVER",IF(E6>=0.9*D6,"WATCH","OK"))) -> WATCH | I6: =D6*12 -> 264000 | J6: =D6*Settings!$B$11 -> 44000 | K6: ='Annual Matrix'!$O21 -> 220000 | L6: =J6-K6 -> -176000 | M6: =E6+ROW()/1000000 -> 22000
A7: =Settings!$K$17 -> Electricity (DESCO / DPDC / REB) | B7: =Settings!$L$17 -> Housing & Utilities | C7: =Settings!$M$17 -> Needs | D7: 3000 | E7: =INDEX('Annual Matrix'!$C22:$N22,Settings!$B$11) -> 1930 | F7: =D7-E7 -> 1070 | G7: =IF(D7=0,"",E7/D7) -> 0.64333333 | H7: =IF(D7=0,IF(E7>0,"Unbudgeted","-"),IF(E7>D7,"OVER",IF(E7>=0.9*D7,"WATCH","OK"))) -> OK | I7: =D7*12 -> 36000 | J7: =D7*Settings!$B$11 -> 6000 | K7: ='Annual Matrix'!$O22 -> 29640 | L7: =J7-K7 -> -23640 | M7: =E7+ROW()/1000000 -> 1930
A8: =Settings!$K$18 -> Gas (Titas / Bakhrabad / Jalalabad) | B8: =Settings!$L$18 -> Housing & Utilities | C8: =Settings!$M$18 -> Needs | D8: 1080 | E8: =INDEX('Annual Matrix'!$C23:$N23,Settings!$B$11) -> 1080 | F8: =D8-E8 -> 0 | G8: =IF(D8=0,"",E8/D8) -> 1 | H8: =IF(D8=0,IF(E8>0,"Unbudgeted","-"),IF(E8>D8,"OVER",IF(E8>=0.9*D8,"WATCH","OK"))) -> WATCH | I8: =D8*12 -> 12960 | J8: =D8*Settings!$B$11 -> 2160 | K8: ='Annual Matrix'!$O23 -> 10800 | L8: =J8-K8 -> -8640 | M8: =E8+ROW()/1000000 -> 1080
A9: =Settings!$K$19 -> Water & Sewerage (WASA) | B9: =Settings!$L$19 -> Housing & Utilities | C9: =Settings!$M$19 -> Needs | D9: 900 | E9: =INDEX('Annual Matrix'!$C24:$N24,Settings!$B$11) -> 900 | F9: =D9-E9 -> 0 | G9: =IF(D9=0,"",E9/D9) -> 1 | H9: =IF(D9=0,IF(E9>0,"Unbudgeted","-"),IF(E9>D9,"OVER",IF(E9>=0.9*D9,"WATCH","OK"))) -> WATCH | I9: =D9*12 -> 10800 | J9: =D9*Settings!$B$11 -> 1800 | K9: ='Annual Matrix'!$O24 -> 9000 | L9: =J9-K9 -> -7200 | M9: =E9+ROW()/1000000 -> 900.00001
A10: =Settings!$K$20 -> Internet / Broadband | B10: =Settings!$L$20 -> Housing & Utilities | C10: =Settings!$M$20 -> Needs | D10: 1000 | E10: =INDEX('Annual Matrix'!$C25:$N25,Settings!$B$11) -> 1000 | F10: =D10-E10 -> 0 | G10: =IF(D10=0,"",E10/D10) -> 1 | H10: =IF(D10=0,IF(E10>0,"Unbudgeted","-"),IF(E10>D10,"OVER",IF(E10>=0.9*D10,"WATCH","OK"))) -> WATCH | I10: =D10*12 -> 12000 | J10: =D10*Settings!$B$11 -> 2000 | K10: ='Annual Matrix'!$O25 -> 10000 | L10: =J10-K10 -> -8000 | M10: =E10+ROW()/1000000 -> 1000
A11: =Settings!$K$21 -> Mobile Recharge & Data | B11: =Settings!$L$21 -> Housing & Utilities | C11: =Settings!$M$21 -> Needs | D11: 700 | E11: =INDEX('Annual Matrix'!$C26:$N26,Settings!$B$11) -> 700 | F11: =D11-E11 -> 0 | G11: =IF(D11=0,"",E11/D11) -> 1 | H11: =IF(D11=0,IF(E11>0,"Unbudgeted","-"),IF(E11>D11,"OVER",IF(E11>=0.9*D11,"WATCH","OK"))) -> WATCH | I11: =D11*12 -> 8400 | J11: =D11*Settings!$B$11 -> 1400 | K11: ='Annual Matrix'!$O26 -> 7000 | L11: =J11-K11 -> -5600 | M11: =E11+ROW()/1000000 -> 700.00001
A12: =Settings!$K$22 -> Maid / Domestic Help | B12: =Settings!$L$22 -> Housing & Utilities | C12: =Settings!$M$22 -> Needs | D12: 3000 | E12: =INDEX('Annual Matrix'!$C27:$N27,Settings!$B$11) -> 3000 | F12: =D12-E12 -> 0 | G12: =IF(D12=0,"",E12/D12) -> 1 | H12: =IF(D12=0,IF(E12>0,"Unbudgeted","-"),IF(E12>D12,"OVER",IF(E12>=0.9*D12,"WATCH","OK"))) -> WATCH | I12: =D12*12 -> 36000 | J12: =D12*Settings!$B$11 -> 6000 | K12: ='Annual Matrix'!$O27 -> 30000 | L12: =J12-K12 -> -24000 | M12: =E12+ROW()/1000000 -> 3000
A13: =Settings!$K$23 -> Home Repair & Maintenance | B13: =Settings!$L$23 -> Housing & Utilities | C13: =Settings!$M$23 -> Needs | D13: 500 | E13: =INDEX('Annual Matrix'!$C28:$N28,Settings!$B$11) -> 0 | F13: =D13-E13 -> 500 | G13: =IF(D13=0,"",E13/D13) -> 0 | H13: =IF(D13=0,IF(E13>0,"Unbudgeted","-"),IF(E13>D13,"OVER",IF(E13>=0.9*D13,"WATCH","OK"))) -> OK | I13: =D13*12 -> 6000 | J13: =D13*Settings!$B$11 -> 1000 | K13: ='Annual Matrix'!$O28 -> 0 | L13: =J13-K13 -> 1000 | M13: =E13+ROW()/1000000 -> 1.3e-05
A14: =Settings!$K$24 -> Service Charge & Holding Tax | B14: =Settings!$L$24 -> Housing & Utilities | C14: =Settings!$M$24 -> Needs | D14: 0 | E14: =INDEX('Annual Matrix'!$C29:$N29,Settings!$B$11) -> 0 | F14: =D14-E14 -> 0 | G14: =IF(D14=0,"",E14/D14) | H14: =IF(D14=0,IF(E14>0,"Unbudgeted","-"),IF(E14>D14,"OVER",IF(E14>=0.9*D14,"WATCH","OK"))) -> - | I14: =D14*12 -> 0 | J14: =D14*Settings!$B$11 -> 0 | K14: ='Annual Matrix'!$O29 -> 0 | L14: =J14-K14 -> 0 | M14: =E14+ROW()/1000000 -> 1.4e-05
A15: =Settings!$K$25 -> Groceries & Bazar | B15: =Settings!$L$25 -> Food | C15: =Settings!$M$25 -> Needs | D15: 11000 | E15: =INDEX('Annual Matrix'!$C30:$N30,Settings!$B$11) -> 11610 | F15: =D15-E15 -> -610 | G15: =IF(D15=0,"",E15/D15) -> 1.0554545 | H15: =IF(D15=0,IF(E15>0,"Unbudgeted","-"),IF(E15>D15,"OVER",IF(E15>=0.9*D15,"WATCH","OK"))) -> OVER | I15: =D15*12 -> 132000 | J15: =D15*Settings!$B$11 -> 22000 | K15: ='Annual Matrix'!$O30 -> 108460 | L15: =J15-K15 -> -86460 | M15: =E15+ROW()/1000000 -> 11610
A16: =Settings!$K$26 -> Dining Out & Food Delivery | B16: =Settings!$L$26 -> Food | C16: =Settings!$M$26 -> Wants | D16: 2000 | E16: =INDEX('Annual Matrix'!$C31:$N31,Settings!$B$11) -> 1060 | F16: =D16-E16 -> 940 | G16: =IF(D16=0,"",E16/D16) -> 0.53 | H16: =IF(D16=0,IF(E16>0,"Unbudgeted","-"),IF(E16>D16,"OVER",IF(E16>=0.9*D16,"WATCH","OK"))) -> OK | I16: =D16*12 -> 24000 | J16: =D16*Settings!$B$11 -> 4000 | K16: ='Annual Matrix'!$O31 -> 10040 | L16: =J16-K16 -> -6040 | M16: =E16+ROW()/1000000 -> 1060
A17: =Settings!$K$27 -> Rickshaw / CNG / Ride-share | B17: =Settings!$L$27 -> Transport | C17: =Settings!$M$27 -> Needs | D17: 2500 | E17: =INDEX('Annual Matrix'!$C32:$N32,Settings!$B$11) -> 1800 | F17: =D17-E17 -> 700 | G17: =IF(D17=0,"",E17/D17) -> 0.72 | H17: =IF(D17=0,IF(E17>0,"Unbudgeted","-"),IF(E17>D17,"OVER",IF(E17>=0.9*D17,"WATCH","OK"))) -> OK | I17: =D17*12 -> 30000 | J17: =D17*Settings!$B$11 -> 5000 | K17: ='Annual Matrix'!$O32 -> 17130 | L17: =J17-K17 -> -12130 | M17: =E17+ROW()/1000000 -> 1800
A18: =Settings!$K$28 -> Bus / Metro Rail / Train | B18: =Settings!$L$28 -> Transport | C18: =Settings!$M$28 -> Needs | D18: 500 | E18: =INDEX('Annual Matrix'!$C33:$N33,Settings!$B$11) -> 0 | F18: =D18-E18 -> 500 | G18: =IF(D18=0,"",E18/D18) -> 0 | H18: =IF(D18=0,IF(E18>0,"Unbudgeted","-"),IF(E18>D18,"OVER",IF(E18>=0.9*D18,"WATCH","OK"))) -> OK | I18: =D18*12 -> 6000 | J18: =D18*Settings!$B$11 -> 1000 | K18: ='Annual Matrix'!$O33 -> 0 | L18: =J18-K18 -> 1000 | M18: =E18+ROW()/1000000 -> 1.8e-05
A19: =Settings!$K$29 -> Fuel (Octane / Petrol / CNG) | B19: =Settings!$L$29 -> Transport | C19: =Settings!$M$29 -> Needs | D19: 1500 | E19: =INDEX('Annual Matrix'!$C34:$N34,Settings!$B$11) -> 1290 | F19: =D19-E19 -> 210 | G19: =IF(D19=0,"",E19/D19) -> 0.86 | H19: =IF(D19=0,IF(E19>0,"Unbudgeted","-"),IF(E19>D19,"OVER",IF(E19>=0.9*D19,"WATCH","OK"))) -> OK | I19: =D19*12 -> 18000 | J19: =D19*Settings!$B$11 -> 3000 | K19: ='Annual Matrix'!$O34 -> 13760 | L19: =J19-K19 -> -10760 | M19: =E19+ROW()/1000000 -> 1290
A20: =Settings!$K$30 -> Vehicle Maintenance & Parking | B20: =Settings!$L$30 -> Transport | C20: =Settings!$M$30 -> Needs | D20: 800 | E20: =INDEX('Annual Matrix'!$C35:$N35,Settings!$B$11) -> 0 | F20: =D20-E20 -> 800 | G20: =IF(D20=0,"",E20/D20) -> 0 | H20: =IF(D20=0,IF(E20>0,"Unbudgeted","-"),IF(E20>D20,"OVER",IF(E20>=0.9*D20,"WATCH","OK"))) -> OK | I20: =D20*12 -> 9600 | J20: =D20*Settings!$B$11 -> 1600 | K20: ='Annual Matrix'!$O35 -> 6420 | L20: =J20-K20 -> -4820 | M20: =E20+ROW()/1000000 -> 2e-05
A21: =Settings!$K$31 -> School / College / University Fees | B21: =Settings!$L$31 -> Family & Education | C21: =Settings!$M$31 -> Needs | D21: 3500 | E21: =INDEX('Annual Matrix'!$C36:$N36,Settings!$B$11) -> 3500 | F21: =D21-E21 -> 0 | G21: =IF(D21=0,"",E21/D21) -> 1 | H21: =IF(D21=0,IF(E21>0,"Unbudgeted","-"),IF(E21>D21,"OVER",IF(E21>=0.9*D21,"WATCH","OK"))) -> WATCH | I21: =D21*12 -> 42000 | J21: =D21*Settings!$B$11 -> 7000 | K21: ='Annual Matrix'!$O36 -> 35000 | L21: =J21-K21 -> -28000 | M21: =E21+ROW()/1000000 -> 3500
A22: =Settings!$K$32 -> Coaching & Books | B22: =Settings!$L$32 -> Family & Education | C22: =Settings!$M$32 -> Needs | D22: 0 | E22: =INDEX('Annual Matrix'!$C37:$N37,Settings!$B$11) -> 0 | F22: =D22-E22 -> 0 | G22: =IF(D22=0,"",E22/D22) | H22: =IF(D22=0,IF(E22>0,"Unbudgeted","-"),IF(E22>D22,"OVER",IF(E22>=0.9*D22,"WATCH","OK"))) -> - | I22: =D22*12 -> 0 | J22: =D22*Settings!$B$11 -> 0 | K22: ='Annual Matrix'!$O37 -> 0 | L22: =J22-K22 -> 0 | M22: =E22+ROW()/1000000 -> 2.2e-05
A23: =Settings!$K$33 -> Child Care & Baby Needs | B23: =Settings!$L$33 -> Family & Education | C23: =Settings!$M$33 -> Needs | D23: 1000 | E23: =INDEX('Annual Matrix'!$C38:$N38,Settings!$B$11) -> 0 | F23: =D23-E23 -> 1000 | G23: =IF(D23=0,"",E23/D23) -> 0 | H23: =IF(D23=0,IF(E23>0,"Unbudgeted","-"),IF(E23>D23,"OVER",IF(E23>=0.9*D23,"WATCH","OK"))) -> OK | I23: =D23*12 -> 12000 | J23: =D23*Settings!$B$11 -> 2000 | K23: ='Annual Matrix'!$O38 -> 0 | L23: =J23-K23 -> 2000 | M23: =E23+ROW()/1000000 -> 2.3e-05
A24: =Settings!$K$34 -> Parents / Family Support | B24: =Settings!$L$34 -> Family & Education | C24: =Settings!$M$34 -> Needs | D24: 5000 | E24: =INDEX('Annual Matrix'!$C39:$N39,Settings!$B$11) -> 5000 | F24: =D24-E24 -> 0 | G24: =IF(D24=0,"",E24/D24) -> 1 | H24: =IF(D24=0,IF(E24>0,"Unbudgeted","-"),IF(E24>D24,"OVER",IF(E24>=0.9*D24,"WATCH","OK"))) -> WATCH | I24: =D24*12 -> 60000 | J24: =D24*Settings!$B$11 -> 10000 | K24: ='Annual Matrix'!$O39 -> 50000 | L24: =J24-K24 -> -40000 | M24: =E24+ROW()/1000000 -> 5000
A25: =Settings!$K$35 -> Medicine & Doctor Visits | B25: =Settings!$L$35 -> Health | C25: =Settings!$M$35 -> Needs | D25: 1500 | E25: =INDEX('Annual Matrix'!$C40:$N40,Settings!$B$11) -> 1770 | F25: =D25-E25 -> -270 | G25: =IF(D25=0,"",E25/D25) -> 1.18 | H25: =IF(D25=0,IF(E25>0,"Unbudgeted","-"),IF(E25>D25,"OVER",IF(E25>=0.9*D25,"WATCH","OK"))) -> OVER | I25: =D25*12 -> 18000 | J25: =D25*Settings!$B$11 -> 3000 | K25: ='Annual Matrix'!$O40 -> 14170 | L25: =J25-K25 -> -11170 | M25: =E25+ROW()/1000000 -> 1770
A26: =Settings!$K$36 -> Medical Tests & Hospital | B26: =Settings!$L$36 -> Health | C26: =Settings!$M$36 -> Needs | D26: 500 | E26: =INDEX('Annual Matrix'!$C41:$N41,Settings!$B$11) -> 0 | F26: =D26-E26 -> 500 | G26: =IF(D26=0,"",E26/D26) -> 0 | H26: =IF(D26=0,IF(E26>0,"Unbudgeted","-"),IF(E26>D26,"OVER",IF(E26>=0.9*D26,"WATCH","OK"))) -> OK | I26: =D26*12 -> 6000 | J26: =D26*Settings!$B$11 -> 1000 | K26: ='Annual Matrix'!$O41 -> 3600 | L26: =J26-K26 -> -2600 | M26: =E26+ROW()/1000000 -> 2.6e-05
A27: =Settings!$K$37 -> Clothing & Footwear | B27: =Settings!$L$37 -> Lifestyle | C27: =Settings!$M$37 -> Wants | D27: 2000 | E27: =INDEX('Annual Matrix'!$C42:$N42,Settings!$B$11) -> 0 | F27: =D27-E27 -> 2000 | G27: =IF(D27=0,"",E27/D27) -> 0 | H27: =IF(D27=0,IF(E27>0,"Unbudgeted","-"),IF(E27>D27,"OVER",IF(E27>=0.9*D27,"WATCH","OK"))) -> OK | I27: =D27*12 -> 24000 | J27: =D27*Settings!$B$11 -> 4000 | K27: ='Annual Matrix'!$O42 -> 22000 | L27: =J27-K27 -> -18000 | M27: =E27+ROW()/1000000 -> 2.7e-05
A28: =Settings!$K$38 -> Personal Care & Salon | B28: =Settings!$L$38 -> Lifestyle | C28: =Settings!$M$38 -> Wants | D28: 800 | E28: =INDEX('Annual Matrix'!$C43:$N43,Settings!$B$11) -> 760 | F28: =D28-E28 -> 40 | G28: =IF(D28=0,"",E28/D28) -> 0.95 | H28: =IF(D28=0,IF(E28>0,"Unbudgeted","-"),IF(E28>D28,"OVER",IF(E28>=0.9*D28,"WATCH","OK"))) -> WATCH | I28: =D28*12 -> 9600 | J28: =D28*Settings!$B$11 -> 1600 | K28: ='Annual Matrix'!$O43 -> 7840 | L28: =J28-K28 -> -6240 | M28: =E28+ROW()/1000000 -> 760.00003
A29: =Settings!$K$39 -> Entertainment & Subscriptions | B29: =Settings!$L$39 -> Lifestyle | C29: =Settings!$M$39 -> Wants | D29: 1100 | E29: =INDEX('Annual Matrix'!$C44:$N44,Settings!$B$11) -> 1100 | F29: =D29-E29 -> 0 | G29: =IF(D29=0,"",E29/D29) -> 1 | H29: =IF(D29=0,IF(E29>0,"Unbudgeted","-"),IF(E29>D29,"OVER",IF(E29>=0.9*D29,"WATCH","OK"))) -> WATCH | I29: =D29*12 -> 13200 | J29: =D29*Settings!$B$11 -> 2200 | K29: ='Annual Matrix'!$O44 -> 11000 | L29: =J29-K29 -> -8800 | M29: =E29+ROW()/1000000 -> 1100
A30: =Settings!$K$40 -> Travel & Holidays | B30: =Settings!$L$40 -> Lifestyle | C30: =Settings!$M$40 -> Wants | D30: 2000 | E30: =INDEX('Annual Matrix'!$C45:$N45,Settings!$B$11) -> 12000 | F30: =D30-E30 -> -10000 | G30: =IF(D30=0,"",E30/D30) -> 6 | H30: =IF(D30=0,IF(E30>0,"Unbudgeted","-"),IF(E30>D30,"OVER",IF(E30>=0.9*D30,"WATCH","OK"))) -> OVER | I30: =D30*12 -> 24000 | J30: =D30*Settings!$B$11 -> 4000 | K30: ='Annual Matrix'!$O45 -> 21000 | L30: =J30-K30 -> -17000 | M30: =E30+ROW()/1000000 -> 12000
A31: =Settings!$K$41 -> Gifts & Social Events | B31: =Settings!$L$41 -> Lifestyle | C31: =Settings!$M$41 -> Wants | D31: 1000 | E31: =INDEX('Annual Matrix'!$C46:$N46,Settings!$B$11) -> 1690 | F31: =D31-E31 -> -690 | G31: =IF(D31=0,"",E31/D31) -> 1.69 | H31: =IF(D31=0,IF(E31>0,"Unbudgeted","-"),IF(E31>D31,"OVER",IF(E31>=0.9*D31,"WATCH","OK"))) -> OVER | I31: =D31*12 -> 12000 | J31: =D31*Settings!$B$11 -> 2000 | K31: ='Annual Matrix'!$O46 -> 7690 | L31: =J31-K31 -> -5690 | M31: =E31+ROW()/1000000 -> 1690
A32: =Settings!$K$42 -> Zakat, Fitra & Sadaqah | B32: =Settings!$L$42 -> Religious & Social | C32: =Settings!$M$42 -> Needs | D32: 3000 | E32: =INDEX('Annual Matrix'!$C47:$N47,Settings!$B$11) -> 0 | F32: =D32-E32 -> 3000 | G32: =IF(D32=0,"",E32/D32) -> 0 | H32: =IF(D32=0,IF(E32>0,"Unbudgeted","-"),IF(E32>D32,"OVER",IF(E32>=0.9*D32,"WATCH","OK"))) -> OK | I32: =D32*12 -> 36000 | J32: =D32*Settings!$B$11 -> 6000 | K32: ='Annual Matrix'!$O47 -> 36650 | L32: =J32-K32 -> -30650 | M32: =E32+ROW()/1000000 -> 3.2e-05
A33: =Settings!$K$43 -> Qurbani (Eid-ul-Adha) | B33: =Settings!$L$43 -> Religious & Social | C33: =Settings!$M$43 -> Wants | D33: 1500 | E33: =INDEX('Annual Matrix'!$C48:$N48,Settings!$B$11) -> 0 | F33: =D33-E33 -> 1500 | G33: =IF(D33=0,"",E33/D33) -> 0 | H33: =IF(D33=0,IF(E33>0,"Unbudgeted","-"),IF(E33>D33,"OVER",IF(E33>=0.9*D33,"WATCH","OK"))) -> OK | I33: =D33*12 -> 18000 | J33: =D33*Settings!$B$11 -> 3000 | K33: ='Annual Matrix'!$O48 -> 20000 | L33: =J33-K33 -> -17000 | M33: =E33+ROW()/1000000 -> 3.3e-05
A34: =Settings!$K$44 -> Festival Expenses (Eid / Puja / Boishakh) | B34: =Settings!$L$44 -> Religious & Social | C34: =Settings!$M$44 -> Wants | D34: 1000 | E34: =INDEX('Annual Matrix'!$C49:$N49,Settings!$B$11) -> 0 | F34: =D34-E34 -> 1000 | G34: =IF(D34=0,"",E34/D34) -> 0 | H34: =IF(D34=0,IF(E34>0,"Unbudgeted","-"),IF(E34>D34,"OVER",IF(E34>=0.9*D34,"WATCH","OK"))) -> OK | I34: =D34*12 -> 12000 | J34: =D34*Settings!$B$11 -> 2000 | K34: ='Annual Matrix'!$O49 -> 18500 | L34: =J34-K34 -> -16500 | M34: =E34+ROW()/1000000 -> 3.4e-05
A35: =Settings!$K$45 -> Loan EMI | B35: =Settings!$L$45 -> Financial Obligations | C35: =Settings!$M$45 -> Needs | D35: 15300 | E35: =INDEX('Annual Matrix'!$C50:$N50,Settings!$B$11) -> 15300 | F35: =D35-E35 -> 0 | G35: =IF(D35=0,"",E35/D35) -> 1 | H35: =IF(D35=0,IF(E35>0,"Unbudgeted","-"),IF(E35>D35,"OVER",IF(E35>=0.9*D35,"WATCH","OK"))) -> WATCH | I35: =D35*12 -> 183600 | J35: =D35*Settings!$B$11 -> 30600 | K35: ='Annual Matrix'!$O50 -> 153000 | L35: =J35-K35 -> -122400 | M35: =E35+ROW()/1000000 -> 15300
A36: =Settings!$K$46 -> Credit Card Payment | B36: =Settings!$L$46 -> Financial Obligations | C36: =Settings!$M$46 -> Needs | D36: 2800 | E36: =INDEX('Annual Matrix'!$C51:$N51,Settings!$B$11) -> 2800 | F36: =D36-E36 -> 0 | G36: =IF(D36=0,"",E36/D36) -> 1 | H36: =IF(D36=0,IF(E36>0,"Unbudgeted","-"),IF(E36>D36,"OVER",IF(E36>=0.9*D36,"WATCH","OK"))) -> WATCH | I36: =D36*12 -> 33600 | J36: =D36*Settings!$B$11 -> 5600 | K36: ='Annual Matrix'!$O51 -> 25200 | L36: =J36-K36 -> -19600 | M36: =E36+ROW()/1000000 -> 2800
A37: =Settings!$K$47 -> Insurance Premium | B37: =Settings!$L$47 -> Financial Obligations | C37: =Settings!$M$47 -> Needs | D37: 2500 | E37: =INDEX('Annual Matrix'!$C52:$N52,Settings!$B$11) -> 2500 | F37: =D37-E37 -> 0 | G37: =IF(D37=0,"",E37/D37) -> 1 | H37: =IF(D37=0,IF(E37>0,"Unbudgeted","-"),IF(E37>D37,"OVER",IF(E37>=0.9*D37,"WATCH","OK"))) -> WATCH | I37: =D37*12 -> 30000 | J37: =D37*Settings!$B$11 -> 5000 | K37: ='Annual Matrix'!$O52 -> 25000 | L37: =J37-K37 -> -20000 | M37: =E37+ROW()/1000000 -> 2500
A38: =Settings!$K$48 -> Income Tax & Govt Fees | B38: =Settings!$L$48 -> Financial Obligations | C38: =Settings!$M$48 -> Needs | D38: 500 | E38: =INDEX('Annual Matrix'!$C53:$N53,Settings!$B$11) -> 1200 | F38: =D38-E38 -> -700 | G38: =IF(D38=0,"",E38/D38) -> 2.4 | H38: =IF(D38=0,IF(E38>0,"Unbudgeted","-"),IF(E38>D38,"OVER",IF(E38>=0.9*D38,"WATCH","OK"))) -> OVER | I38: =D38*12 -> 6000 | J38: =D38*Settings!$B$11 -> 1000 | K38: ='Annual Matrix'!$O53 -> 6200 | L38: =J38-K38 -> -5200 | M38: =E38+ROW()/1000000 -> 1200
A39: =Settings!$K$49 -> Bank / MFS Charges | B39: =Settings!$L$49 -> Financial Obligations | C39: =Settings!$M$49 -> Needs | D39: 250 | E39: =INDEX('Annual Matrix'!$C54:$N54,Settings!$B$11) -> 250 | F39: =D39-E39 -> 0 | G39: =IF(D39=0,"",E39/D39) -> 1 | H39: =IF(D39=0,IF(E39>0,"Unbudgeted","-"),IF(E39>D39,"OVER",IF(E39>=0.9*D39,"WATCH","OK"))) -> WATCH | I39: =D39*12 -> 3000 | J39: =D39*Settings!$B$11 -> 500 | K39: ='Annual Matrix'!$O54 -> 2250 | L39: =J39-K39 -> -1750 | M39: =E39+ROW()/1000000 -> 250.00004
A40: =Settings!$K$50 -> DPS Deposit | B40: =Settings!$L$50 -> Savings & Investments | C40: =Settings!$M$50 -> Savings | D40: 5000 | E40: =INDEX('Annual Matrix'!$C55:$N55,Settings!$B$11) -> 5000 | F40: =D40-E40 -> 0 | G40: =IF(D40=0,"",E40/D40) -> 1 | H40: =IF(D40=0,IF(E40>0,"Unbudgeted","-"),IF(E40>D40,"OVER",IF(E40>=0.9*D40,"WATCH","OK"))) -> WATCH | I40: =D40*12 -> 60000 | J40: =D40*Settings!$B$11 -> 10000 | K40: ='Annual Matrix'!$O55 -> 50000 | L40: =J40-K40 -> -40000 | M40: =E40+ROW()/1000000 -> 5000
A41: =Settings!$K$51 -> FDR / Sanchayapatra Purchase | B41: =Settings!$L$51 -> Savings & Investments | C41: =Settings!$M$51 -> Savings | D41: 0 | E41: =INDEX('Annual Matrix'!$C56:$N56,Settings!$B$11) -> 0 | F41: =D41-E41 -> 0 | G41: =IF(D41=0,"",E41/D41) | H41: =IF(D41=0,IF(E41>0,"Unbudgeted","-"),IF(E41>D41,"OVER",IF(E41>=0.9*D41,"WATCH","OK"))) -> - | I41: =D41*12 -> 0 | J41: =D41*Settings!$B$11 -> 0 | K41: ='Annual Matrix'!$O56 -> 50000 | L41: =J41-K41 -> -50000 | M41: =E41+ROW()/1000000 -> 4.1e-05
A42: =Settings!$K$52 -> Stocks & Mutual Funds (DSE) | B42: =Settings!$L$52 -> Savings & Investments | C42: =Settings!$M$52 -> Savings | D42: 1500 | E42: =INDEX('Annual Matrix'!$C57:$N57,Settings!$B$11) -> 0 | F42: =D42-E42 -> 1500 | G42: =IF(D42=0,"",E42/D42) -> 0 | H42: =IF(D42=0,IF(E42>0,"Unbudgeted","-"),IF(E42>D42,"OVER",IF(E42>=0.9*D42,"WATCH","OK"))) -> OK | I42: =D42*12 -> 18000 | J42: =D42*Settings!$B$11 -> 3000 | K42: ='Annual Matrix'!$O57 -> 15000 | L42: =J42-K42 -> -12000 | M42: =E42+ROW()/1000000 -> 4.2e-05
A43: =Settings!$K$53 -> Gold Purchase | B43: =Settings!$L$53 -> Savings & Investments | C43: =Settings!$M$53 -> Savings | D43: 0 | E43: =INDEX('Annual Matrix'!$C58:$N58,Settings!$B$11) -> 0 | F43: =D43-E43 -> 0 | G43: =IF(D43=0,"",E43/D43) | H43: =IF(D43=0,IF(E43>0,"Unbudgeted","-"),IF(E43>D43,"OVER",IF(E43>=0.9*D43,"WATCH","OK"))) -> - | I43: =D43*12 -> 0 | J43: =D43*Settings!$B$11 -> 0 | K43: ='Annual Matrix'!$O58 -> 0 | L43: =J43-K43 -> 0 | M43: =E43+ROW()/1000000 -> 4.3e-05
A44: =Settings!$K$54 -> Emergency Fund Deposit | B44: =Settings!$L$54 -> Savings & Investments | C44: =Settings!$M$54 -> Savings | D44: 3000 | E44: =INDEX('Annual Matrix'!$C59:$N59,Settings!$B$11) -> 3000 | F44: =D44-E44 -> 0 | G44: =IF(D44=0,"",E44/D44) -> 1 | H44: =IF(D44=0,IF(E44>0,"Unbudgeted","-"),IF(E44>D44,"OVER",IF(E44>=0.9*D44,"WATCH","OK"))) -> WATCH | I44: =D44*12 -> 36000 | J44: =D44*Settings!$B$11 -> 6000 | K44: ='Annual Matrix'!$O59 -> 27000 | L44: =J44-K44 -> -21000 | M44: =E44+ROW()/1000000 -> 3000
A45: =Settings!$K$55 -> Provident / Pension Contribution | B45: =Settings!$L$55 -> Savings & Investments | C45: =Settings!$M$55 -> Savings | D45: 0 | E45: =INDEX('Annual Matrix'!$C60:$N60,Settings!$B$11) -> 0 | F45: =D45-E45 -> 0 | G45: =IF(D45=0,"",E45/D45) | H45: =IF(D45=0,IF(E45>0,"Unbudgeted","-"),IF(E45>D45,"OVER",IF(E45>=0.9*D45,"WATCH","OK"))) -> - | I45: =D45*12 -> 0 | J45: =D45*Settings!$B$11 -> 0 | K45: ='Annual Matrix'!$O60 -> 0 | L45: =J45-K45 -> 0 | M45: =E45+ROW()/1000000 -> 4.5e-05
A46: =Settings!$K$56 -> Miscellaneous | B46: =Settings!$L$56 -> Other | C46: =Settings!$M$56 -> Wants | D46: 1000 | E46: =INDEX('Annual Matrix'!$C61:$N61,Settings!$B$11) -> 0 | F46: =D46-E46 -> 1000 | G46: =IF(D46=0,"",E46/D46) -> 0 | H46: =IF(D46=0,IF(E46>0,"Unbudgeted","-"),IF(E46>D46,"OVER",IF(E46>=0.9*D46,"WATCH","OK"))) -> OK | I46: =D46*12 -> 12000 | J46: =D46*Settings!$B$11 -> 2000 | K46: ='Annual Matrix'!$O61 -> 1600 | L46: =J46-K46 -> 400 | M46: =E46+ROW()/1000000 -> 4.6e-05
A47: TOTAL | D47: =SUM(D6:D46) -> 106230 | E47: =SUM(E6:E46) -> 102240 | F47: =SUM(F6:F46) -> 3990 | G47: =IF(D47=0,"",E47/D47) -> 0.96243999 | I47: =SUM(I6:I46) -> 1274760 | J47: =SUM(J6:J46) -> 212460 | K47: =SUM(K6:K46) -> 1074950 | L47: =SUM(L6:L46) -> -862490
A50: MONTHLY PLAN vs ACTUAL INCOME
A51: Planned Monthly Income (BDT) | D51: 115000
A52: Actual Income - selected month | D52: =INDEX('Annual Matrix'!$C$18:$N$18,Settings!$B$11) -> 128330
A53: Total Budgeted Outflow (incl. savings) | D53: =D47 -> 106230
A54: Planned Surplus / (Deficit) | D54: =D51-D53 -> 8770
A57: 50 / 30 / 20 RULE CHECK (selected month, actuals vs income)
A58: Bucket | C58: Actual (BDT) | D58: % of Income | E58: Target % | F58: Status
A59: Needs | C59: =SUMIF($C$6:$C$46,"Needs",$E$6:$E$46) -> 77630 | D59: =IF($D$52=0,0,C59/$D$52) -> 0.6049248 | E59: =Settings!$B$12 -> 0.5 | F59: =IF($D$52=0,"-",IF(D59<=E59,"On Target","Over Target")) -> Over Target
A60: Wants | C60: =SUMIF($C$6:$C$46,"Wants",$E$6:$E$46) -> 16610 | D60: =IF($D$52=0,0,C60/$D$52) -> 0.12943193 | E60: =Settings!$B$13 -> 0.3 | F60: =IF($D$52=0,"-",IF(D60<=E60,"On Target","Over Target")) -> On Target
A61: Savings | C61: =SUMIF($C$6:$C$46,"Savings",$E$6:$E$46) -> 8000 | D61: =IF($D$52=0,0,C61/$D$52) -> 0.062339282 | E61: =Settings!$B$14 -> 0.2 | F61: =IF($D$52=0,"-",IF(D61>=E61,"On Target","Below Target")) -> Below Target
A63: Needs = essentials (rent, utilities, food, EMI, Zakat...). Wants = lifestyle. Savings = DPS/FDR/shares/emergency fund. Change a category's type in Settings.

Sheet Annual Matrix
A1: ANNUAL MATRIX | Category x Month
A2: Fully automatic - sums the Transaction Log by category and month for the tracking year set in Settings. Do not type here.
A3: month # (helper) | C3: 1 | D3: 2 | E3: 3 | F3: 4 | G3: 5 | H3: 6 | I3: 7 | J3: 8 | K3: 9 | L3: 10 | M3: 11 | N3: 12
A4: Category | B4: Group | C4: Jan | D4: Feb | E4: Mar | F4: Apr | G4: May | H4: Jun | I4: Jul | J4: Aug | K4: Sep | L4: Oct | M4: Nov | N4: Dec | O4: YTD Total | P4: Annual Budget | Q4: Budget - Actual | R4: % of Budget Used
A5: INCOME
A6: =Settings!$K$4 -> Salary | B6: Income | C6: =SUMIFS(Transactions!$G$6:$G$2005,Transactions!$B$6:$B$2005,"Income",Transactions!$C$6:$C$2005,$A6,Transactions!$I$6:$I$2005,C$3,Transactions!$J$6:$J$2005,Settings!$B$5) -> 115000 | D6: =SUMIFS(Transactions!$G$6:$G$2005,Transactions!$B$6:$B$2005,"Income",Transactions!$C$6:$C$2005,$A6,Transactions!$I$6:$I$2005,D$3,Transactions!$J$6:$J$2005,Settings!$B$5) -> 115000 | E6: =SUMIFS(Transactions!$G$6:$G$2005,Transactions!$B$6:$B$2005,"Income",Transactions!$C$6:$C$2005,$A6,Transactions!$I$6:$I$2005,E$3,Transactions!$J$6:$J$2005,Settings!$B$5) -> 115000 | F6: =SUMIFS(Transactions!$G$6:$G$2005,Transactions!$B$6:$B$2005,"Income",Transactions!$C$6:$C$2005,$A6,Transactions!$I$6:$I$2005,F$3,Transactions!$J$6:$J$2005,Settings!$B$5) -> 115000 | G6: =SUMIFS(Transactions!$G$6:$G$2005,Transactions!$B$6:$B$2005,"Income",Transactions!$C$6:$C$2005,$A6,Transactions!$I$6:$I$2005,G$3,Transactions!$J$6:$J$2005,Settings!$B$5) -> 115000 | H6: =SUMIFS(Transactions!$G$6:$G$2005,Transactions!$B$6:$B$2005,"Income",Transactions!$C$6:$C$2005,$A6,Transactions!$I$6:$I$2005,H$3,Transactions!$J$6:$J$2005,Settings!$B$5) -> 115000 | I6: =SUMIFS(Transactions!$G$6:$G$2005,Transactions!$B$6:$B$2005,"Income",Transactions!$C$6:$C$2005,$A6,Transactions!$I$6:$I$2005,I$3,Transactions!$J$6:$J$2005,Settings!$B$5) -> 115000 | J6: =SUMIFS(Transactions!$G$6:$G$2005,Transactions!$B$6:$B$2005,"Income",Transactions!$C$6:$C$2005,$A6,Transactions!$I$6:$I$2005,J$3,Transactions!$J$6:$J$2005,Settings!$B$5) -> 115000 | ... N6: =SUMIFS(Transactions!$G$6:$G$2005,Transactions!$B$6:$B$2005,"Income",Transactions!$C$6:$C$2005,$A6,Transactions!$I$6:$I$2005,N$3,Transactions!$J$6:$J$2005,Settings!$B$5) -> 0 | O6: =SUM(C6:N6) -> 1150000
A7: =Settings!$K$5 -> Festival Bonus (Eid) | B7: Income | C7: =SUMIFS(Transactions!$G$6:$G$2005,Transactions!$B$6:$B$2005,"Income",Transactions!$C$6:$C$2005,$A7,Transactions!$I$6:$I$2005,C$3,Transactions!$J$6:$J$2005,Settings!$B$5) -> 0 | D7: =SUMIFS(Transactions!$G$6:$G$2005,Transactions!$B$6:$B$2005,"Income",Transactions!$C$6:$C$2005,$A7,Transactions!$I$6:$I$2005,D$3,Transactions!$J$6:$J$2005,Settings!$B$5) -> 0 | E7: =SUMIFS(Transactions!$G$6:$G$2005,Transactions!$B$6:$B$2005,"Income",Transactions!$C$6:$C$2005,$A7,Transactions!$I$6:$I$2005,E$3,Transactions!$J$6:$J$2005,Settings!$B$5) -> 72000 | F7: =SUMIFS(Transactions!$G$6:$G$2005,Transactions!$B$6:$B$2005,"Income",Transactions!$C$6:$C$2005,$A7,Transactions!$I$6:$I$2005,F$3,Transactions!$J$6:$J$2005,Settings!$B$5) -> 0 | G7: =SUMIFS(Transactions!$G$6:$G$2005,Transactions!$B$6:$B$2005,"Income",Transactions!$C$6:$C$2005,$A7,Transactions!$I$6:$I$2005,G$3,Transactions!$J$6:$J$2005,Settings!$B$5) -> 72000 | H7: =SUMIFS(Transactions!$G$6:$G$2005,Transactions!$B$6:$B$2005,"Income",Transactions!$C$6:$C$2005,$A7,Transactions!$I$6:$I$2005,H$3,Transactions!$J$6:$J$2005,Settings!$B$5) -> 0 | I7: =SUMIFS(Transactions!$G$6:$G$2005,Transactions!$B$6:$B$2005,"Income",Transactions!$C$6:$C$2005,$A7,Transactions!$I$6:$I$2005,I$3,Transactions!$J$6:$J$2005,Settings!$B$5) -> 0 | J7: =SUMIFS(Transactions!$G$6:$G$2005,Transactions!$B$6:$B$2005,"Income",Transactions!$C$6:$C$2005,$A7,Transactions!$I$6:$I$2005,J$3,Transactions!$J$6:$J$2005,Settings!$B$5) -> 0 | ... N7: =SUMIFS(Transactions!$G$6:$G$2005,Transactions!$B$6:$B$2005,"Income",Transactions!$C$6:$C$2005,$A7,Transactions!$I$6:$I$2005,N$3,Transactions!$J$6:$J$2005,Settings!$B$5) -> 0 | O7: =SUM(C7:N7) -> 144000
A8: =Settings!$K$6 -> Business / Trade Income | B8: Income | C8: =SUMIFS(Transactions!$G$6:$G$2005,Transactions!$B$6:$B$2005,"Income",Transactions!$C$6:$C$2005,$A8,Transactions!$I$6:$I$2005,C$3,Transactions!$J$6:$J$2005,Settings!$B$5) -> 0 | D8: =SUMIFS(Transactions!$G$6:$G$2005,Transactions!$B$6:$B$2005,"Income",Transactions!$C$6:$C$2005,$A8,Transactions!$I$6:$I$2005,D$3,Transactions!$J$6:$J$2005,Settings!$B$5) -> 0 | E8: =SUMIFS(Transactions!$G$6:$G$2005,Transactions!$B$6:$B$2005,"Income",Transactions!$C$6:$C$2005,$A8,Transactions!$I$6:$I$2005,E$3,Transactions!$J$6:$J$2005,Settings!$B$5) -> 0 | F8: =SUMIFS(Transactions!$G$6:$G$2005,Transactions!$B$6:$B$2005,"Income",Transactions!$C$6:$C$2005,$A8,Transactions!$I$6:$I$2005,F$3,Transactions!$J$6:$J$2005,Settings!$B$5) -> 0 | G8: =SUMIFS(Transactions!$G$6:$G$2005,Transactions!$B$6:$B$2005,"Income",Transactions!$C$6:$C$2005,$A8,Transactions!$I$6:$I$2005,G$3,Transactions!$J$6:$J$2005,Settings!$B$5) -> 0 | H8: =SUMIFS(Transactions!$G$6:$G$2005,Transactions!$B$6:$B$2005,"Income",Transactions!$C$6:$C$2005,$A8,Transactions!$I$6:$I$2005,H$3,Transactions!$J$6:$J$2005,Settings!$B$5) -> 0 | I8: =SUMIFS(Transactions!$G$6:$G$2005,Transactions!$B$6:$B$2005,"Income",Transactions!$C$6:$C$2005,$A8,Transactions!$I$6:$I$2005,I$3,Transactions!$J$6:$J$2005,Settings!$B$5) -> 0 | J8: =SUMIFS(Transactions!$G$6:$G$2005,Transactions!$B$6:$B$2005,"Income",Transactions!$C$6:$C$2005,$A8,Transactions!$I$6:$I$2005,J$3,Transactions!$J$6:$J$2005,Settings!$B$5) -> 0 | ... N8: =SUMIFS(Transactions!$G$6:$G$2005,Transactions!$B$6:$B$2005,"Income",Transactions!$C$6:$C$2005,$A8,Transactions!$I$6:$I$2005,N$3,Transactions!$J$6:$J$2005,Settings!$B$5) -> 0 | O8: =SUM(C8:N8) -> 0
A9: =Settings!$K$7 -> Freelance / Side Income | B9: Income | C9: =SUMIFS(Transactions!$G$6:$G$2005,Transactions!$B$6:$B$2005,"Income",Transactions!$C$6:$C$2005,$A9,Transactions!$I$6:$I$2005,C$3,Transactions!$J$6:$J$2005,Settings!$B$5) -> 0 | D9: =SUMIFS(Transactions!$G$6:$G$2005,Transactions!$B$6:$B$2005,"Income",Transactions!$C$6:$C$2005,$A9,Transactions!$I$6:$I$2005,D$3,Transactions!$J$6:$J$2005,Settings!$B$5) -> 13330 | E9: =SUMIFS(Transactions!$G$6:$G$2005,Transactions!$B$6:$B$2005,"Income",Transactions!$C$6:$C$2005,$A9,Transactions!$I$6:$I$2005,E$3,Transactions!$J$6:$J$2005,Settings!$B$5) -> 0 | F9: =SUMIFS(Transactions!$G$6:$G$2005,Transactions!$B$6:$B$2005,"Income",Transactions!$C$6:$C$2005,$A9,Transactions!$I$6:$I$2005,F$3,Transactions!$J$6:$J$2005,Settings!$B$5) -> 14480 | G9: =SUMIFS(Transactions!$G$6:$G$2005,Transactions!$B$6:$B$2005,"Income",Transactions!$C$6:$C$2005,$A9,Transactions!$I$6:$I$2005,G$3,Transactions!$J$6:$J$2005,Settings!$B$5) -> 0 | H9: =SUMIFS(Transactions!$G$6:$G$2005,Transactions!$B$6:$B$2005,"Income",Transactions!$C$6:$C$2005,$A9,Transactions!$I$6:$I$2005,H$3,Transactions!$J$6:$J$2005,Settings!$B$5) -> 13120 | I9: =SUMIFS(Transactions!$G$6:$G$2005,Transactions!$B$6:$B$2005,"Income",Transactions!$C$6:$C$2005,$A9,Transactions!$I$6:$I$2005,I$3,Transactions!$J$6:$J$2005,Settings!$B$5) -> 0 | J9: =SUMIFS(Transactions!$G$6:$G$2005,Transactions!$B$6:$B$2005,"Income",Transactions!$C$6:$C$2005,$A9,Transactions!$I$6:$I$2005,J$3,Transactions!$J$6:$J$2005,Settings!$B$5) -> 12840 | ... N9: =SUMIFS(Transactions!$G$6:$G$2005,Transactions!$B$6:$B$2005,"Income",Transactions!$C$6:$C$2005,$A9,Transactions!$I$6:$I$2005,N$3,Transactions!$J$6:$J$2005,Settings!$B$5) -> 0 | O9: =SUM(C9:N9) -> 67170
A10: =Settings!$K$8 -> Remittance (Foreign) | B10: Income | C10: =SUMIFS(Transactions!$G$6:$G$2005,Transactions!$B$6:$B$2005,"Income",Transactions!$C$6:$C$2005,$A10,Transactions!$I$6:$I$2005,C$3,Transactions!$J$6:$J$2005,Settings!$B$5) -> 0 | D10: =SUMIFS(Transactions!$G$6:$G$2005,Transactions!$B$6:$B$2005,"Income",Transactions!$C$6:$C$2005,$A10,Transactions!$I$6:$I$2005,D$3,Transactions!$J$6:$J$2005,Settings!$B$5) -> 0 | E10: =SUMIFS(Transactions!$G$6:$G$2005,Transactions!$B$6:$B$2005,"Income",Transactions!$C$6:$C$2005,$A10,Transactions!$I$6:$I$2005,E$3,Transactions!$J$6:$J$2005,Settings!$B$5) -> 0 | F10: =SUMIFS(Transactions!$G$6:$G$2005,Transactions!$B$6:$B$2005,"Income",Transactions!$C$6:$C$2005,$A10,Transactions!$I$6:$I$2005,F$3,Transactions!$J$6:$J$2005,Settings!$B$5) -> 0 | G10: =SUMIFS(Transactions!$G$6:$G$2005,Transactions!$B$6:$B$2005,"Income",Transactions!$C$6:$C$2005,$A10,Transactions!$I$6:$I$2005,G$3,Transactions!$J$6:$J$2005,Settings!$B$5) -> 0 | H10: =SUMIFS(Transactions!$G$6:$G$2005,Transactions!$B$6:$B$2005,"Income",Transactions!$C$6:$C$2005,$A10,Transactions!$I$6:$I$2005,H$3,Transactions!$J$6:$J$2005,Settings!$B$5) -> 0 | I10: =SUMIFS(Transactions!$G$6:$G$2005,Transactions!$B$6:$B$2005,"Income",Transactions!$C$6:$C$2005,$A10,Transactions!$I$6:$I$2005,I$3,Transactions!$J$6:$J$2005,Settings!$B$5) -> 0 | J10: =SUMIFS(Transactions!$G$6:$G$2005,Transactions!$B$6:$B$2005,"Income",Transactions!$C$6:$C$2005,$A10,Transactions!$I$6:$I$2005,J$3,Transactions!$J$6:$J$2005,Settings!$B$5) -> 0 | ... N10: =SUMIFS(Transactions!$G$6:$G$2005,Transactions!$B$6:$B$2005,"Income",Transactions!$C$6:$C$2005,$A10,Transactions!$I$6:$I$2005,N$3,Transactions!$J$6:$J$2005,Settings!$B$5) -> 0 | O10: =SUM(C10:N10) -> 0
A11: =Settings!$K$9 -> Rental Income | B11: Income | C11: =SUMIFS(Transactions!$G$6:$G$2005,Transactions!$B$6:$B$2005,"Income",Transactions!$C$6:$C$2005,$A11,Transactions!$I$6:$I$2005,C$3,Transactions!$J$6:$J$2005,Settings!$B$5) -> 0 | D11: =SUMIFS(Transactions!$G$6:$G$2005,Transactions!$B$6:$B$2005,"Income",Transactions!$C$6:$C$2005,$A11,Transactions!$I$6:$I$2005,D$3,Transactions!$J$6:$J$2005,Settings!$B$5) -> 0 | E11: =SUMIFS(Transactions!$G$6:$G$2005,Transactions!$B$6:$B$2005,"Income",Transactions!$C$6:$C$2005,$A11,Transactions!$I$6:$I$2005,E$3,Transactions!$J$6:$J$2005,Settings!$B$5) -> 0 | F11: =SUMIFS(Transactions!$G$6:$G$2005,Transactions!$B$6:$B$2005,"Income",Transactions!$C$6:$C$2005,$A11,Transactions!$I$6:$I$2005,F$3,Transactions!$J$6:$J$2005,Settings!$B$5) -> 0 | G11: =SUMIFS(Transactions!$G$6:$G$2005,Transactions!$B$6:$B$2005,"Income",Transactions!$C$6:$C$2005,$A11,Transactions!$I$6:$I$2005,G$3,Transactions!$J$6:$J$2005,Settings!$B$5) -> 0 | H11: =SUMIFS(Transactions!$G$6:$G$2005,Transactions!$B$6:$B$2005,"Income",Transactions!$C$6:$C$2005,$A11,Transactions!$I$6:$I$2005,H$3,Transactions!$J$6:$J$2005,Settings!$B$5) -> 0 | I11: =SUMIFS(Transactions!$G$6:$G$2005,Transactions!$B$6:$B$2005,"Income",Transactions!$C$6:$C$2005,$A11,Transactions!$I$6:$I$2005,I$3,Transactions!$J$6:$J$2005,Settings!$B$5) -> 0 | J11: =SUMIFS(Transactions!$G$6:$G$2005,Transactions!$B$6:$B$2005,"Income",Transactions!$C$6:$C$2005,$A11,Transactions!$I$6:$I$2005,J$3,Transactions!$J$6:$J$2005,Settings!$B$5) -> 0 | ... N11: =SUMIFS(Transactions!$G$6:$G$2005,Transactions!$B$6:$B$2005,"Income",Transactions!$C$6:$C$2005,$A11,Transactions!$I$6:$I$2005,N$3,Transactions!$J$6:$J$2005,Settings!$B$5) -> 0 | O11: =SUM(C11:N11) -> 0
A12: =Settings!$K$10 -> Agricultural Income | B12: Income | C12: =SUMIFS(Transactions!$G$6:$G$2005,Transactions!$B$6:$B$2005,"Income",Transactions!$C$6:$C$2005,$A12,Transactions!$I$6:$I$2005,C$3,Transactions!$J$6:$J$2005,Settings!$B$5) -> 0 | D12: =SUMIFS(Transactions!$G$6:$G$2005,Transactions!$B$6:$B$2005,"Income",Transactions!$C$6:$C$2005,$A12,Transactions!$I$6:$I$2005,D$3,Transactions!$J$6:$J$2005,Settings!$B$5) -> 0 | E12: =SUMIFS(Transactions!$G$6:$G$2005,Transactions!$B$6:$B$2005,"Income",Transactions!$C$6:$C$2005,$A12,Transactions!$I$6:$I$2005,E$3,Transactions!$J$6:$J$2005,Settings!$B$5) -> 0 | F12: =SUMIFS(Transactions!$G$6:$G$2005,Transactions!$B$6:$B$2005,"Income",Transactions!$C$6:$C$2005,$A12,Transactions!$I$6:$I$2005,F$3,Transactions!$J$6:$J$2005,Settings!$B$5) -> 0 | G12: =SUMIFS(Transactions!$G$6:$G$2005,Transactions!$B$6:$B$2005,"Income",Transactions!$C$6:$C$2005,$A12,Transactions!$I$6:$I$2005,G$3,Transactions!$J$6:$J$2005,Settings!$B$5) -> 0 | H12: =SUMIFS(Transactions!$G$6:$G$2005,Transactions!$B$6:$B$2005,"Income",Transactions!$C$6:$C$2005,$A12,Transactions!$I$6:$I$2005,H$3,Transactions!$J$6:$J$2005,Settings!$B$5) -> 0 | I12: =SUMIFS(Transactions!$G$6:$G$2005,Transactions!$B$6:$B$2005,"Income",Transactions!$C$6:$C$2005,$A12,Transactions!$I$6:$I$2005,I$3,Transactions!$J$6:$J$2005,Settings!$B$5) -> 0 | J12: =SUMIFS(Transactions!$G$6:$G$2005,Transactions!$B$6:$B$2005,"Income",Transactions!$C$6:$C$2005,$A12,Transactions!$I$6:$I$2005,J$3,Transactions!$J$6:$J$2005,Settings!$B$5) -> 0 | ... N12: =SUMIFS(Transactions!$G$6:$G$2005,Transactions!$B$6:$B$2005,"Income",Transactions!$C$6:$C$2005,$A12,Transactions!$I$6:$I$2005,N$3,Transactions!$J$6:$J$2005,Settings!$B$5) -> 0 | O12: =SUM(C12:N12) -> 0
A13: =Settings!$K$11 -> Bank Interest | B13: Income | C13: =SUMIFS(Transactions!$G$6:$G$2005,Transactions!$B$6:$B$2005,"Income",Transactions!$C$6:$C$2005,$A13,Transactions!$I$6:$I$2005,C$3,Transactions!$J$6:$J$2005,Settings!$B$5) -> 0 | D13: =SUMIFS(Transactions!$G$6:$G$2005,Transactions!$B$6:$B$2005,"Income",Transactions!$C$6:$C$2005,$A13,Transactions!$I$6:$I$2005,D$3,Transactions!$J$6:$J$2005,Settings!$B$5) -> 0 | E13: =SUMIFS(Transactions!$G$6:$G$2005,Transactions!$B$6:$B$2005,"Income",Transactions!$C$6:$C$2005,$A13,Transactions!$I$6:$I$2005,E$3,Transactions!$J$6:$J$2005,Settings!$B$5) -> 3200 | F13: =SUMIFS(Transactions!$G$6:$G$2005,Transactions!$B$6:$B$2005,"Income",Transactions!$C$6:$C$2005,$A13,Transactions!$I$6:$I$2005,F$3,Transactions!$J$6:$J$2005,Settings!$B$5) -> 0 | G13: =SUMIFS(Transactions!$G$6:$G$2005,Transactions!$B$6:$B$2005,"Income",Transactions!$C$6:$C$2005,$A13,Transactions!$I$6:$I$2005,G$3,Transactions!$J$6:$J$2005,Settings!$B$5) -> 0 | H13: =SUMIFS(Transactions!$G$6:$G$2005,Transactions!$B$6:$B$2005,"Income",Transactions!$C$6:$C$2005,$A13,Transactions!$I$6:$I$2005,H$3,Transactions!$J$6:$J$2005,Settings!$B$5) -> 3200 | I13: =SUMIFS(Transactions!$G$6:$G$2005,Transactions!$B$6:$B$2005,"Income",Transactions!$C$6:$C$2005,$A13,Transactions!$I$6:$I$2005,I$3,Transactions!$J$6:$J$2005,Settings!$B$5) -> 0 | J13: =SUMIFS(Transactions!$G$6:$G$2005,Transactions!$B$6:$B$2005,"Income",Transactions!$C$6:$C$2005,$A13,Transactions!$I$6:$I$2005,J$3,Transactions!$J$6:$J$2005,Settings!$B$5) -> 0 | ... N13: =SUMIFS(Transactions!$G$6:$G$2005,Transactions!$B$6:$B$2005,"Income",Transactions!$C$6:$C$2005,$A13,Transactions!$I$6:$I$2005,N$3,Transactions!$J$6:$J$2005,Settings!$B$5) -> 0 | O13: =SUM(C13:N13) -> 9600
A14: =Settings!$K$12 -> Sanchayapatra Profit | B14: Income | C14: =SUMIFS(Transactions!$G$6:$G$2005,Transactions!$B$6:$B$2005,"Income",Transactions!$C$6:$C$2005,$A14,Transactions!$I$6:$I$2005,C$3,Transactions!$J$6:$J$2005,Settings!$B$5) -> 7776 | D14: =SUMIFS(Transactions!$G$6:$G$2005,Transactions!$B$6:$B$2005,"Income",Transactions!$C$6:$C$2005,$A14,Transactions!$I$6:$I$2005,D$3,Transactions!$J$6:$J$2005,Settings!$B$5) -> 0 | E14: =SUMIFS(Transactions!$G$6:$G$2005,Transactions!$B$6:$B$2005,"Income",Transactions!$C$6:$C$2005,$A14,Transactions!$I$6:$I$2005,E$3,Transactions!$J$6:$J$2005,Settings!$B$5) -> 0 | F14: =SUMIFS(Transactions!$G$6:$G$2005,Transactions!$B$6:$B$2005,"Income",Transactions!$C$6:$C$2005,$A14,Transactions!$I$6:$I$2005,F$3,Transactions!$J$6:$J$2005,Settings!$B$5) -> 7776 | G14: =SUMIFS(Transactions!$G$6:$G$2005,Transactions!$B$6:$B$2005,"Income",Transactions!$C$6:$C$2005,$A14,Transactions!$I$6:$I$2005,G$3,Transactions!$J$6:$J$2005,Settings!$B$5) -> 0 | H14: =SUMIFS(Transactions!$G$6:$G$2005,Transactions!$B$6:$B$2005,"Income",Transactions!$C$6:$C$2005,$A14,Transactions!$I$6:$I$2005,H$3,Transactions!$J$6:$J$2005,Settings!$B$5) -> 0 | I14: =SUMIFS(Transactions!$G$6:$G$2005,Transactions!$B$6:$B$2005,"Income",Transactions!$C$6:$C$2005,$A14,Transactions!$I$6:$I$2005,I$3,Transactions!$J$6:$J$2005,Settings!$B$5) -> 7776 | J14: =SUMIFS(Transactions!$G$6:$G$2005,Transactions!$B$6:$B$2005,"Income",Transactions!$C$6:$C$2005,$A14,Transactions!$I$6:$I$2005,J$3,Transactions!$J$6:$J$2005,Settings!$B$5) -> 0 | ... N14: =SUMIFS(Transactions!$G$6:$G$2005,Transactions!$B$6:$B$2005,"Income",Transactions!$C$6:$C$2005,$A14,Transactions!$I$6:$I$2005,N$3,Transactions!$J$6:$J$2005,Settings!$B$5) -> 0 | O14: =SUM(C14:N14) -> 31104
A15: =Settings!$K$13 -> Dividend (DSE / Mutual Fund) | B15: Income | C15: =SUMIFS(Transactions!$G$6:$G$2005,Transactions!$B$6:$B$2005,"Income",Transactions!$C$6:$C$2005,$A15,Transactions!$I$6:$I$2005,C$3,Transactions!$J$6:$J$2005,Settings!$B$5) -> 0 | D15: =SUMIFS(Transactions!$G$6:$G$2005,Transactions!$B$6:$B$2005,"Income",Transactions!$C$6:$C$2005,$A15,Transactions!$I$6:$I$2005,D$3,Transactions!$J$6:$J$2005,Settings!$B$5) -> 0 | E15: =SUMIFS(Transactions!$G$6:$G$2005,Transactions!$B$6:$B$2005,"Income",Transactions!$C$6:$C$2005,$A15,Transactions!$I$6:$I$2005,E$3,Transactions!$J$6:$J$2005,Settings!$B$5) -> 0 | F15: =SUMIFS(Transactions!$G$6:$G$2005,Transactions!$B$6:$B$2005,"Income",Transactions!$C$6:$C$2005,$A15,Transactions!$I$6:$I$2005,F$3,Transactions!$J$6:$J$2005,Settings!$B$5) -> 0 | G15: =SUMIFS(Transactions!$G$6:$G$2005,Transactions!$B$6:$B$2005,"Income",Transactions!$C$6:$C$2005,$A15,Transactions!$I$6:$I$2005,G$3,Transactions!$J$6:$J$2005,Settings!$B$5) -> 0 | H15: =SUMIFS(Transactions!$G$6:$G$2005,Transactions!$B$6:$B$2005,"Income",Transactions!$C$6:$C$2005,$A15,Transactions!$I$6:$I$2005,H$3,Transactions!$J$6:$J$2005,Settings!$B$5) -> 0 | I15: =SUMIFS(Transactions!$G$6:$G$2005,Transactions!$B$6:$B$2005,"Income",Transactions!$C$6:$C$2005,$A15,Transactions!$I$6:$I$2005,I$3,Transactions!$J$6:$J$2005,Settings!$B$5) -> 0 | J15: =SUMIFS(Transactions!$G$6:$G$2005,Transactions!$B$6:$B$2005,"Income",Transactions!$C$6:$C$2005,$A15,Transactions!$I$6:$I$2005,J$3,Transactions!$J$6:$J$2005,Settings!$B$5) -> 0 | ... N15: =SUMIFS(Transactions!$G$6:$G$2005,Transactions!$B$6:$B$2005,"Income",Transactions!$C$6:$C$2005,$A15,Transactions!$I$6:$I$2005,N$3,Transactions!$J$6:$J$2005,Settings!$B$5) -> 0 | O15: =SUM(C15:N15) -> 0
A16: =Settings!$K$14 -> DPS / FDR Maturity | B16: Income | C16: =SUMIFS(Transactions!$G$6:$G$2005,Transactions!$B$6:$B$2005,"Income",Transactions!$C$6:$C$2005,$A16,Transactions!$I$6:$I$2005,C$3,Transactions!$J$6:$J$2005,Settings!$B$5) -> 0 | D16: =SUMIFS(Transactions!$G$6:$G$2005,Transactions!$B$6:$B$2005,"Income",Transactions!$C$6:$C$2005,$A16,Transactions!$I$6:$I$2005,D$3,Transactions!$J$6:$J$2005,Settings!$B$5) -> 0 | E16: =SUMIFS(Transactions!$G$6:$G$2005,Transactions!$B$6:$B$2005,"Income",Transactions!$C$6:$C$2005,$A16,Transactions!$I$6:$I$2005,E$3,Transactions!$J$6:$J$2005,Settings!$B$5) -> 0 | F16: =SUMIFS(Transactions!$G$6:$G$2005,Transactions!$B$6:$B$2005,"Income",Transactions!$C$6:$C$2005,$A16,Transactions!$I$6:$I$2005,F$3,Transactions!$J$6:$J$2005,Settings!$B$5) -> 0 | G16: =SUMIFS(Transactions!$G$6:$G$2005,Transactions!$B$6:$B$2005,"Income",Transactions!$C$6:$C$2005,$A16,Transactions!$I$6:$I$2005,G$3,Transactions!$J$6:$J$2005,Settings!$B$5) -> 0 | H16: =SUMIFS(Transactions!$G$6:$G$2005,Transactions!$B$6:$B$2005,"Income",Transactions!$C$6:$C$2005,$A16,Transactions!$I$6:$I$2005,H$3,Transactions!$J$6:$J$2005,Settings!$B$5) -> 0 | I16: =SUMIFS(Transactions!$G$6:$G$2005,Transactions!$B$6:$B$2005,"Income",Transactions!$C$6:$C$2005,$A16,Transactions!$I$6:$I$2005,I$3,Transactions!$J$6:$J$2005,Settings!$B$5) -> 0 | J16: =SUMIFS(Transactions!$G$6:$G$2005,Transactions!$B$6:$B$2005,"Income",Transactions!$C$6:$C$2005,$A16,Transactions!$I$6:$I$2005,J$3,Transactions!$J$6:$J$2005,Settings!$B$5) -> 0 | ... N16: =SUMIFS(Transactions!$G$6:$G$2005,Transactions!$B$6:$B$2005,"Income",Transactions!$C$6:$C$2005,$A16,Transactions!$I$6:$I$2005,N$3,Transactions!$J$6:$J$2005,Settings!$B$5) -> 0 | O16: =SUM(C16:N16) -> 0
A17: =Settings!$K$15 -> Gift / Other Income | B17: Income | C17: =SUMIFS(Transactions!$G$6:$G$2005,Transactions!$B$6:$B$2005,"Income",Transactions!$C$6:$C$2005,$A17,Transactions!$I$6:$I$2005,C$3,Transactions!$J$6:$J$2005,Settings!$B$5) -> 0 | D17: =SUMIFS(Transactions!$G$6:$G$2005,Transactions!$B$6:$B$2005,"Income",Transactions!$C$6:$C$2005,$A17,Transactions!$I$6:$I$2005,D$3,Transactions!$J$6:$J$2005,Settings!$B$5) -> 0 | E17: =SUMIFS(Transactions!$G$6:$G$2005,Transactions!$B$6:$B$2005,"Income",Transactions!$C$6:$C$2005,$A17,Transactions!$I$6:$I$2005,E$3,Transactions!$J$6:$J$2005,Settings!$B$5) -> 0 | F17: =SUMIFS(Transactions!$G$6:$G$2005,Transactions!$B$6:$B$2005,"Income",Transactions!$C$6:$C$2005,$A17,Transactions!$I$6:$I$2005,F$3,Transactions!$J$6:$J$2005,Settings!$B$5) -> 0 | G17: =SUMIFS(Transactions!$G$6:$G$2005,Transactions!$B$6:$B$2005,"Income",Transactions!$C$6:$C$2005,$A17,Transactions!$I$6:$I$2005,G$3,Transactions!$J$6:$J$2005,Settings!$B$5) -> 0 | H17: =SUMIFS(Transactions!$G$6:$G$2005,Transactions!$B$6:$B$2005,"Income",Transactions!$C$6:$C$2005,$A17,Transactions!$I$6:$I$2005,H$3,Transactions!$J$6:$J$2005,Settings!$B$5) -> 0 | I17: =SUMIFS(Transactions!$G$6:$G$2005,Transactions!$B$6:$B$2005,"Income",Transactions!$C$6:$C$2005,$A17,Transactions!$I$6:$I$2005,I$3,Transactions!$J$6:$J$2005,Settings!$B$5) -> 0 | J17: =SUMIFS(Transactions!$G$6:$G$2005,Transactions!$B$6:$B$2005,"Income",Transactions!$C$6:$C$2005,$A17,Transactions!$I$6:$I$2005,J$3,Transactions!$J$6:$J$2005,Settings!$B$5) -> 0 | ... N17: =SUMIFS(Transactions!$G$6:$G$2005,Transactions!$B$6:$B$2005,"Income",Transactions!$C$6:$C$2005,$A17,Transactions!$I$6:$I$2005,N$3,Transactions!$J$6:$J$2005,Settings!$B$5) -> 0 | O17: =SUM(C17:N17) -> 0
A18: TOTAL INCOME | C18: =SUM(C6:C17) -> 122776 | D18: =SUM(D6:D17) -> 128330 | E18: =SUM(E6:E17) -> 190200 | F18: =SUM(F6:F17) -> 137256 | G18: =SUM(G6:G17) -> 187000 | H18: =SUM(H6:H17) -> 131320 | I18: =SUM(I6:I17) -> 122776 | J18: =SUM(J6:J17) -> 127840 | ... O18: =SUM(O6:O17) -> 1401874
A20: EXPENSES
A21: =Settings!$K$16 -> House Rent | B21: =Settings!$L$16 -> Housing & Utilities | C21: =SUMIFS(Transactions!$G$6:$G$2005,Transactions!$B$6:$B$2005,"Expense",Transactions!$C$6:$C$2005,$A21,Transactions!$I$6:$I$2005,C$3,Transactions!$J$6:$J$2005,Settings!$B$5) -> 22000 | D21: =SUMIFS(Transactions!$G$6:$G$2005,Transactions!$B$6:$B$2005,"Expense",Transactions!$C$6:$C$2005,$A21,Transactions!$I$6:$I$2005,D$3,Transactions!$J$6:$J$2005,Settings!$B$5) -> 22000 | E21: =SUMIFS(Transactions!$G$6:$G$2005,Transactions!$B$6:$B$2005,"Expense",Transactions!$C$6:$C$2005,$A21,Transactions!$I$6:$I$2005,E$3,Transactions!$J$6:$J$2005,Settings!$B$5) -> 22000 | F21: =SUMIFS(Transactions!$G$6:$G$2005,Transactions!$B$6:$B$2005,"Expense",Transactions!$C$6:$C$2005,$A21,Transactions!$I$6:$I$2005,F$3,Transactions!$J$6:$J$2005,Settings!$B$5) -> 22000 | G21: =SUMIFS(Transactions!$G$6:$G$2005,Transactions!$B$6:$B$2005,"Expense",Transactions!$C$6:$C$2005,$A21,Transactions!$I$6:$I$2005,G$3,Transactions!$J$6:$J$2005,Settings!$B$5) -> 22000 | H21: =SUMIFS(Transactions!$G$6:$G$2005,Transactions!$B$6:$B$2005,"Expense",Transactions!$C$6:$C$2005,$A21,Transactions!$I$6:$I$2005,H$3,Transactions!$J$6:$J$2005,Settings!$B$5) -> 22000 | I21: =SUMIFS(Transactions!$G$6:$G$2005,Transactions!$B$6:$B$2005,"Expense",Transactions!$C$6:$C$2005,$A21,Transactions!$I$6:$I$2005,I$3,Transactions!$J$6:$J$2005,Settings!$B$5) -> 22000 | J21: =SUMIFS(Transactions!$G$6:$G$2005,Transactions!$B$6:$B$2005,"Expense",Transactions!$C$6:$C$2005,$A21,Transactions!$I$6:$I$2005,J$3,Transactions!$J$6:$J$2005,Settings!$B$5) -> 22000 | ... N21: =SUMIFS(Transactions!$G$6:$G$2005,Transactions!$B$6:$B$2005,"Expense",Transactions!$C$6:$C$2005,$A21,Transactions!$I$6:$I$2005,N$3,Transactions!$J$6:$J$2005,Settings!$B$5) -> 0 | O21: =SUM(C21:N21) -> 220000 | P21: =Budget!$I$6 -> 264000 | Q21: =P21-O21 -> 44000 | R21: =IF(P21=0,"",O21/P21) -> 0.83333333
A22: =Settings!$K$17 -> Electricity (DESCO / DPDC / REB) | B22: =Settings!$L$17 -> Housing & Utilities | C22: =SUMIFS(Transactions!$G$6:$G$2005,Transactions!$B$6:$B$2005,"Expense",Transactions!$C$6:$C$2005,$A22,Transactions!$I$6:$I$2005,C$3,Transactions!$J$6:$J$2005,Settings!$B$5) -> 2150 | D22: =SUMIFS(Transactions!$G$6:$G$2005,Transactions!$B$6:$B$2005,"Expense",Transactions!$C$6:$C$2005,$A22,Transactions!$I$6:$I$2005,D$3,Transactions!$J$6:$J$2005,Settings!$B$5) -> 1930 | E22: =SUMIFS(Transactions!$G$6:$G$2005,Transactions!$B$6:$B$2005,"Expense",Transactions!$C$6:$C$2005,$A22,Transactions!$I$6:$I$2005,E$3,Transactions!$J$6:$J$2005,Settings!$B$5) -> 2270 | F22: =SUMIFS(Transactions!$G$6:$G$2005,Transactions!$B$6:$B$2005,"Expense",Transactions!$C$6:$C$2005,$A22,Transactions!$I$6:$I$2005,F$3,Transactions!$J$6:$J$2005,Settings!$B$5) -> 2830 | G22: =SUMIFS(Transactions!$G$6:$G$2005,Transactions!$B$6:$B$2005,"Expense",Transactions!$C$6:$C$2005,$A22,Transactions!$I$6:$I$2005,G$3,Transactions!$J$6:$J$2005,Settings!$B$5) -> 3410 | H22: =SUMIFS(Transactions!$G$6:$G$2005,Transactions!$B$6:$B$2005,"Expense",Transactions!$C$6:$C$2005,$A22,Transactions!$I$6:$I$2005,H$3,Transactions!$J$6:$J$2005,Settings!$B$5) -> 3640 | I22: =SUMIFS(Transactions!$G$6:$G$2005,Transactions!$B$6:$B$2005,"Expense",Transactions!$C$6:$C$2005,$A22,Transactions!$I$6:$I$2005,I$3,Transactions!$J$6:$J$2005,Settings!$B$5) -> 3840 | J22: =SUMIFS(Transactions!$G$6:$G$2005,Transactions!$B$6:$B$2005,"Expense",Transactions!$C$6:$C$2005,$A22,Transactions!$I$6:$I$2005,J$3,Transactions!$J$6:$J$2005,Settings!$B$5) -> 3630 | ... N22: =SUMIFS(Transactions!$G$6:$G$2005,Transactions!$B$6:$B$2005,"Expense",Transactions!$C$6:$C$2005,$A22,Transactions!$I$6:$I$2005,N$3,Transactions!$J$6:$J$2005,Settings!$B$5) -> 0 | O22: =SUM(C22:N22) -> 29640 | P22: =Budget!$I$7 -> 36000 | Q22: =P22-O22 -> 6360 | R22: =IF(P22=0,"",O22/P22) -> 0.82333333
A23: =Settings!$K$18 -> Gas (Titas / Bakhrabad / Jalalabad) | B23: =Settings!$L$18 -> Housing & Utilities | C23: =SUMIFS(Transactions!$G$6:$G$2005,Transactions!$B$6:$B$2005,"Expense",Transactions!$C$6:$C$2005,$A23,Transactions!$I$6:$I$2005,C$3,Transactions!$J$6:$J$2005,Settings!$B$5) -> 1080 | D23: =SUMIFS(Transactions!$G$6:$G$2005,Transactions!$B$6:$B$2005,"Expense",Transactions!$C$6:$C$2005,$A23,Transactions!$I$6:$I$2005,D$3,Transactions!$J$6:$J$2005,Settings!$B$5) -> 1080 | E23: =SUMIFS(Transactions!$G$6:$G$2005,Transactions!$B$6:$B$2005,"Expense",Transactions!$C$6:$C$2005,$A23,Transactions!$I$6:$I$2005,E$3,Transactions!$J$6:$J$2005,Settings!$B$5) -> 1080 | F23: =SUMIFS(Transactions!$G$6:$G$2005,Transactions!$B$6:$B$2005,"Expense",Transactions!$C$6:$C$2005,$A23,Transactions!$I$6:$I$2005,F$3,Transactions!$J$6:$J$2005,Settings!$B$5) -> 1080 | G23: =SUMIFS(Transactions!$G$6:$G$2005,Transactions!$B$6:$B$2005,"Expense",Transactions!$C$6:$C$2005,$A23,Transactions!$I$6:$I$2005,G$3,Transactions!$J$6:$J$2005,Settings!$B$5) -> 1080 | H23: =SUMIFS(Transactions!$G$6:$G$2005,Transactions!$B$6:$B$2005,"Expense",Transactions!$C$6:$C$2005,$A23,Transactions!$I$6:$I$2005,H$3,Transactions!$J$6:$J$2005,Settings!$B$5) -> 1080 | I23: =SUMIFS(Transactions!$G$6:$G$2005,Transactions!$B$6:$B$2005,"Expense",Transactions!$C$6:$C$2005,$A23,Transactions!$I$6:$I$2005,I$3,Transactions!$J$6:$J$2005,Settings!$B$5) -> 1080 | J23: =SUMIFS(Transactions!$G$6:$G$2005,Transactions!$B$6:$B$2005,"Expense",Transactions!$C$6:$C$2005,$A23,Transactions!$I$6:$I$2005,J$3,Transactions!$J$6:$J$2005,Settings!$B$5) -> 1080 | ... N23: =SUMIFS(Transactions!$G$6:$G$2005,Transactions!$B$6:$B$2005,"Expense",Transactions!$C$6:$C$2005,$A23,Transactions!$I$6:$I$2005,N$3,Transactions!$J$6:$J$2005,Settings!$B$5) -> 0 | O23: =SUM(C23:N23) -> 10800 | P23: =Budget!$I$8 -> 12960 | Q23: =P23-O23 -> 2160 | R23: =IF(P23=0,"",O23/P23) -> 0.83333333
A24: =Settings!$K$19 -> Water & Sewerage (WASA) | B24: =Settings!$L$19 -> Housing & Utilities | C24: =SUMIFS(Transactions!$G$6:$G$2005,Transactions!$B$6:$B$2005,"Expense",Transactions!$C$6:$C$2005,$A24,Transactions!$I$6:$I$2005,C$3,Transactions!$J$6:$J$2005,Settings!$B$5) -> 900 | D24: =SUMIFS(Transactions!$G$6:$G$2005,Transactions!$B$6:$B$2005,"Expense",Transactions!$C$6:$C$2005,$A24,Transactions!$I$6:$I$2005,D$3,Transactions!$J$6:$J$2005,Settings!$B$5) -> 900 | E24: =SUMIFS(Transactions!$G$6:$G$2005,Transactions!$B$6:$B$2005,"Expense",Transactions!$C$6:$C$2005,$A24,Transactions!$I$6:$I$2005,E$3,Transactions!$J$6:$J$2005,Settings!$B$5) -> 900 | F24: =SUMIFS(Transactions!$G$6:$G$2005,Transactions!$B$6:$B$2005,"Expense",Transactions!$C$6:$C$2005,$A24,Transactions!$I$6:$I$2005,F$3,Transactions!$J$6:$J$2005,Settings!$B$5) -> 900 | G24: =SUMIFS(Transactions!$G$6:$G$2005,Transactions!$B$6:$B$2005,"Expense",Transactions!$C$6:$C$2005,$A24,Transactions!$I$6:$I$2005,G$3,Transactions!$J$6:$J$2005,Settings!$B$5) -> 900 | H24: =SUMIFS(Transactions!$G$6:$G$2005,Transactions!$B$6:$B$2005,"Expense",Transactions!$C$6:$C$2005,$A24,Transactions!$I$6:$I$2005,H$3,Transactions!$J$6:$J$2005,Settings!$B$5) -> 900 | I24: =SUMIFS(Transactions!$G$6:$G$2005,Transactions!$B$6:$B$2005,"Expense",Transactions!$C$6:$C$2005,$A24,Transactions!$I$6:$I$2005,I$3,Transactions!$J$6:$J$2005,Settings!$B$5) -> 900 | J24: =SUMIFS(Transactions!$G$6:$G$2005,Transactions!$B$6:$B$2005,"Expense",Transactions!$C$6:$C$2005,$A24,Transactions!$I$6:$I$2005,J$3,Transactions!$J$6:$J$2005,Settings!$B$5) -> 900 | ... N24: =SUMIFS(Transactions!$G$6:$G$2005,Transactions!$B$6:$B$2005,"Expense",Transactions!$C$6:$C$2005,$A24,Transactions!$I$6:$I$2005,N$3,Transactions!$J$6:$J$2005,Settings!$B$5) -> 0 | O24: =SUM(C24:N24) -> 9000 | P24: =Budget!$I$9 -> 10800 | Q24: =P24-O24 -> 1800 | R24: =IF(P24=0,"",O24/P24) -> 0.83333333
A25: =Settings!$K$20 -> Internet / Broadband | B25: =Settings!$L$20 -> Housing & Utilities | C25: =SUMIFS(Transactions!$G$6:$G$2005,Transactions!$B$6:$B$2005,"Expense",Transactions!$C$6:$C$2005,$A25,Transactions!$I$6:$I$2005,C$3,Transactions!$J$6:$J$2005,Settings!$B$5) -> 1000 | D25: =SUMIFS(Transactions!$G$6:$G$2005,Transactions!$B$6:$B$2005,"Expense",Transactions!$C$6:$C$2005,$A25,Transactions!$I$6:$I$2005,D$3,Transactions!$J$6:$J$2005,Settings!$B$5) -> 1000 | E25: =SUMIFS(Transactions!$G$6:$G$2005,Transactions!$B$6:$B$2005,"Expense",Transactions!$C$6:$C$2005,$A25,Transactions!$I$6:$I$2005,E$3,Transactions!$J$6:$J$2005,Settings!$B$5) -> 1000 | F25: =SUMIFS(Transactions!$G$6:$G$2005,Transactions!$B$6:$B$2005,"Expense",Transactions!$C$6:$C$2005,$A25,Transactions!$I$6:$I$2005,F$3,Transactions!$J$6:$J$2005,Settings!$B$5) -> 1000 | G25: =SUMIFS(Transactions!$G$6:$G$2005,Transactions!$B$6:$B$2005,"Expense",Transactions!$C$6:$C$2005,$A25,Transactions!$I$6:$I$2005,G$3,Transactions!$J$6:$J$2005,Settings!$B$5) -> 1000 | H25: =SUMIFS(Transactions!$G$6:$G$2005,Transactions!$B$6:$B$2005,"Expense",Transactions!$C$6:$C$2005,$A25,Transactions!$I$6:$I$2005,H$3,Transactions!$J$6:$J$2005,Settings!$B$5) -> 1000 | I25: =SUMIFS(Transactions!$G$6:$G$2005,Transactions!$B$6:$B$2005,"Expense",Transactions!$C$6:$C$2005,$A25,Transactions!$I$6:$I$2005,I$3,Transactions!$J$6:$J$2005,Settings!$B$5) -> 1000 | J25: =SUMIFS(Transactions!$G$6:$G$2005,Transactions!$B$6:$B$2005,"Expense",Transactions!$C$6:$C$2005,$A25,Transactions!$I$6:$I$2005,J$3,Transactions!$J$6:$J$2005,Settings!$B$5) -> 1000 | ... N25: =SUMIFS(Transactions!$G$6:$G$2005,Transactions!$B$6:$B$2005,"Expense",Transactions!$C$6:$C$2005,$A25,Transactions!$I$6:$I$2005,N$3,Transactions!$J$6:$J$2005,Settings!$B$5) -> 0 | O25: =SUM(C25:N25) -> 10000 | P25: =Budget!$I$10 -> 12000 | Q25: =P25-O25 -> 2000 | R25: =IF(P25=0,"",O25/P25) -> 0.83333333
A26: =Settings!$K$21 -> Mobile Recharge & Data | B26: =Settings!$L$21 -> Housing & Utilities | C26: =SUMIFS(Transactions!$G$6:$G$2005,Transactions!$B$6:$B$2005,"Expense",Transactions!$C$6:$C$2005,$A26,Transactions!$I$6:$I$2005,C$3,Transactions!$J$6:$J$2005,Settings!$B$5) -> 700 | D26: =SUMIFS(Transactions!$G$6:$G$2005,Transactions!$B$6:$B$2005,"Expense",Transactions!$C$6:$C$2005,$A26,Transactions!$I$6:$I$2005,D$3,Transactions!$J$6:$J$2005,Settings!$B$5) -> 700 | E26: =SUMIFS(Transactions!$G$6:$G$2005,Transactions!$B$6:$B$2005,"Expense",Transactions!$C$6:$C$2005,$A26,Transactions!$I$6:$I$2005,E$3,Transactions!$J$6:$J$2005,Settings!$B$5) -> 700 | F26: =SUMIFS(Transactions!$G$6:$G$2005,Transactions!$B$6:$B$2005,"Expense",Transactions!$C$6:$C$2005,$A26,Transactions!$I$6:$I$2005,F$3,Transactions!$J$6:$J$2005,Settings!$B$5) -> 700 | G26: =SUMIFS(Transactions!$G$6:$G$2005,Transactions!$B$6:$B$2005,"Expense",Transactions!$C$6:$C$2005,$A26,Transactions!$I$6:$I$2005,G$3,Transactions!$J$6:$J$2005,Settings!$B$5) -> 700 | H26: =SUMIFS(Transactions!$G$6:$G$2005,Transactions!$B$6:$B$2005,"Expense",Transactions!$C$6:$C$2005,$A26,Transactions!$I$6:$I$2005,H$3,Transactions!$J$6:$J$2005,Settings!$B$5) -> 700 | I26: =SUMIFS(Transactions!$G$6:$G$2005,Transactions!$B$6:$B$2005,"Expense",Transactions!$C$6:$C$2005,$A26,Transactions!$I$6:$I$2005,I$3,Transactions!$J$6:$J$2005,Settings!$B$5) -> 700 | J26: =SUMIFS(Transactions!$G$6:$G$2005,Transactions!$B$6:$B$2005,"Expense",Transactions!$C$6:$C$2005,$A26,Transactions!$I$6:$I$2005,J$3,Transactions!$J$6:$J$2005,Settings!$B$5) -> 700 | ... N26: =SUMIFS(Transactions!$G$6:$G$2005,Transactions!$B$6:$B$2005,"Expense",Transactions!$C$6:$C$2005,$A26,Transactions!$I$6:$I$2005,N$3,Transactions!$J$6:$J$2005,Settings!$B$5) -> 0 | O26: =SUM(C26:N26) -> 7000 | P26: =Budget!$I$11 -> 8400 | Q26: =P26-O26 -> 1400 | R26: =IF(P26=0,"",O26/P26) -> 0.83333333
A27: =Settings!$K$22 -> Maid / Domestic Help | B27: =Settings!$L$22 -> Housing & Utilities | C27: =SUMIFS(Transactions!$G$6:$G$2005,Transactions!$B$6:$B$2005,"Expense",Transactions!$C$6:$C$2005,$A27,Transactions!$I$6:$I$2005,C$3,Transactions!$J$6:$J$2005,Settings!$B$5) -> 3000 | D27: =SUMIFS(Transactions!$G$6:$G$2005,Transactions!$B$6:$B$2005,"Expense",Transactions!$C$6:$C$2005,$A27,Transactions!$I$6:$I$2005,D$3,Transactions!$J$6:$J$2005,Settings!$B$5) -> 3000 | E27: =SUMIFS(Transactions!$G$6:$G$2005,Transactions!$B$6:$B$2005,"Expense",Transactions!$C$6:$C$2005,$A27,Transactions!$I$6:$I$2005,E$3,Transactions!$J$6:$J$2005,Settings!$B$5) -> 3000 | F27: =SUMIFS(Transactions!$G$6:$G$2005,Transactions!$B$6:$B$2005,"Expense",Transactions!$C$6:$C$2005,$A27,Transactions!$I$6:$I$2005,F$3,Transactions!$J$6:$J$2005,Settings!$B$5) -> 3000 | G27: =SUMIFS(Transactions!$G$6:$G$2005,Transactions!$B$6:$B$2005,"Expense",Transactions!$C$6:$C$2005,$A27,Transactions!$I$6:$I$2005,G$3,Transactions!$J$6:$J$2005,Settings!$B$5) -> 3000 | H27: =SUMIFS(Transactions!$G$6:$G$2005,Transactions!$B$6:$B$2005,"Expense",Transactions!$C$6:$C$2005,$A27,Transactions!$I$6:$I$2005,H$3,Transactions!$J$6:$J$2005,Settings!$B$5) -> 3000 | I27: =SUMIFS(Transactions!$G$6:$G$2005,Transactions!$B$6:$B$2005,"Expense",Transactions!$C$6:$C$2005,$A27,Transactions!$I$6:$I$2005,I$3,Transactions!$J$6:$J$2005,Settings!$B$5) -> 3000 | J27: =SUMIFS(Transactions!$G$6:$G$2005,Transactions!$B$6:$B$2005,"Expense",Transactions!$C$6:$C$2005,$A27,Transactions!$I$6:$I$2005,J$3,Transactions!$J$6:$J$2005,Settings!$B$5) -> 3000 | ... N27: =SUMIFS(Transactions!$G$6:$G$2005,Transactions!$B$6:$B$2005,"Expense",Transactions!$C$6:$C$2005,$A27,Transactions!$I$6:$I$2005,N$3,Transactions!$J$6:$J$2005,Settings!$B$5) -> 0 | O27: =SUM(C27:N27) -> 30000 | P27: =Budget!$I$12 -> 36000 | Q27: =P27-O27 -> 6000 | R27: =IF(P27=0,"",O27/P27) -> 0.83333333
A28: =Settings!$K$23 -> Home Repair & Maintenance | B28: =Settings!$L$23 -> Housing & Utilities | C28: =SUMIFS(Transactions!$G$6:$G$2005,Transactions!$B$6:$B$2005,"Expense",Transactions!$C$6:$C$2005,$A28,Transactions!$I$6:$I$2005,C$3,Transactions!$J$6:$J$2005,Settings!$B$5) -> 0 | D28: =SUMIFS(Transactions!$G$6:$G$2005,Transactions!$B$6:$B$2005,"Expense",Transactions!$C$6:$C$2005,$A28,Transactions!$I$6:$I$2005,D$3,Transactions!$J$6:$J$2005,Settings!$B$5) -> 0 | E28: =SUMIFS(Transactions!$G$6:$G$2005,Transactions!$B$6:$B$2005,"Expense",Transactions!$C$6:$C$2005,$A28,Transactions!$I$6:$I$2005,E$3,Transactions!$J$6:$J$2005,Settings!$B$5) -> 0 | F28: =SUMIFS(Transactions!$G$6:$G$2005,Transactions!$B$6:$B$2005,"Expense",Transactions!$C$6:$C$2005,$A28,Transactions!$I$6:$I$2005,F$3,Transactions!$J$6:$J$2005,Settings!$B$5) -> 0 | G28: =SUMIFS(Transactions!$G$6:$G$2005,Transactions!$B$6:$B$2005,"Expense",Transactions!$C$6:$C$2005,$A28,Transactions!$I$6:$I$2005,G$3,Transactions!$J$6:$J$2005,Settings!$B$5) -> 0 | H28: =SUMIFS(Transactions!$G$6:$G$2005,Transactions!$B$6:$B$2005,"Expense",Transactions!$C$6:$C$2005,$A28,Transactions!$I$6:$I$2005,H$3,Transactions!$J$6:$J$2005,Settings!$B$5) -> 0 | I28: =SUMIFS(Transactions!$G$6:$G$2005,Transactions!$B$6:$B$2005,"Expense",Transactions!$C$6:$C$2005,$A28,Transactions!$I$6:$I$2005,I$3,Transactions!$J$6:$J$2005,Settings!$B$5) -> 0 | J28: =SUMIFS(Transactions!$G$6:$G$2005,Transactions!$B$6:$B$2005,"Expense",Transactions!$C$6:$C$2005,$A28,Transactions!$I$6:$I$2005,J$3,Transactions!$J$6:$J$2005,Settings!$B$5) -> 0 | ... N28: =SUMIFS(Transactions!$G$6:$G$2005,Transactions!$B$6:$B$2005,"Expense",Transactions!$C$6:$C$2005,$A28,Transactions!$I$6:$I$2005,N$3,Transactions!$J$6:$J$2005,Settings!$B$5) -> 0 | O28: =SUM(C28:N28) -> 0 | P28: =Budget!$I$13 -> 6000 | Q28: =P28-O28 -> 6000 | R28: =IF(P28=0,"",O28/P28) -> 0
A29: =Settings!$K$24 -> Service Charge & Holding Tax | B29: =Settings!$L$24 -> Housing & Utilities | C29: =SUMIFS(Transactions!$G$6:$G$2005,Transactions!$B$6:$B$2005,"Expense",Transactions!$C$6:$C$2005,$A29,Transactions!$I$6:$I$2005,C$3,Transactions!$J$6:$J$2005,Settings!$B$5) -> 0 | D29: =SUMIFS(Transactions!$G$6:$G$2005,Transactions!$B$6:$B$2005,"Expense",Transactions!$C$6:$C$2005,$A29,Transactions!$I$6:$I$2005,D$3,Transactions!$J$6:$J$2005,Settings!$B$5) -> 0 | E29: =SUMIFS(Transactions!$G$6:$G$2005,Transactions!$B$6:$B$2005,"Expense",Transactions!$C$6:$C$2005,$A29,Transactions!$I$6:$I$2005,E$3,Transactions!$J$6:$J$2005,Settings!$B$5) -> 0 | F29: =SUMIFS(Transactions!$G$6:$G$2005,Transactions!$B$6:$B$2005,"Expense",Transactions!$C$6:$C$2005,$A29,Transactions!$I$6:$I$2005,F$3,Transactions!$J$6:$J$2005,Settings!$B$5) -> 0 | G29: =SUMIFS(Transactions!$G$6:$G$2005,Transactions!$B$6:$B$2005,"Expense",Transactions!$C$6:$C$2005,$A29,Transactions!$I$6:$I$2005,G$3,Transactions!$J$6:$J$2005,Settings!$B$5) -> 0 | H29: =SUMIFS(Transactions!$G$6:$G$2005,Transactions!$B$6:$B$2005,"Expense",Transactions!$C$6:$C$2005,$A29,Transactions!$I$6:$I$2005,H$3,Transactions!$J$6:$J$2005,Settings!$B$5) -> 0 | I29: =SUMIFS(Transactions!$G$6:$G$2005,Transactions!$B$6:$B$2005,"Expense",Transactions!$C$6:$C$2005,$A29,Transactions!$I$6:$I$2005,I$3,Transactions!$J$6:$J$2005,Settings!$B$5) -> 0 | J29: =SUMIFS(Transactions!$G$6:$G$2005,Transactions!$B$6:$B$2005,"Expense",Transactions!$C$6:$C$2005,$A29,Transactions!$I$6:$I$2005,J$3,Transactions!$J$6:$J$2005,Settings!$B$5) -> 0 | ... N29: =SUMIFS(Transactions!$G$6:$G$2005,Transactions!$B$6:$B$2005,"Expense",Transactions!$C$6:$C$2005,$A29,Transactions!$I$6:$I$2005,N$3,Transactions!$J$6:$J$2005,Settings!$B$5) -> 0 | O29: =SUM(C29:N29) -> 0 | P29: =Budget!$I$14 -> 0 | Q29: =P29-O29 -> 0 | R29: =IF(P29=0,"",O29/P29)
A30: =Settings!$K$25 -> Groceries & Bazar | B30: =Settings!$L$25 -> Food | C30: =SUMIFS(Transactions!$G$6:$G$2005,Transactions!$B$6:$B$2005,"Expense",Transactions!$C$6:$C$2005,$A30,Transactions!$I$6:$I$2005,C$3,Transactions!$J$6:$J$2005,Settings!$B$5) -> 10810 | D30: =SUMIFS(Transactions!$G$6:$G$2005,Transactions!$B$6:$B$2005,"Expense",Transactions!$C$6:$C$2005,$A30,Transactions!$I$6:$I$2005,D$3,Transactions!$J$6:$J$2005,Settings!$B$5) -> 11610 | E30: =SUMIFS(Transactions!$G$6:$G$2005,Transactions!$B$6:$B$2005,"Expense",Transactions!$C$6:$C$2005,$A30,Transactions!$I$6:$I$2005,E$3,Transactions!$J$6:$J$2005,Settings!$B$5) -> 11480 | F30: =SUMIFS(Transactions!$G$6:$G$2005,Transactions!$B$6:$B$2005,"Expense",Transactions!$C$6:$C$2005,$A30,Transactions!$I$6:$I$2005,F$3,Transactions!$J$6:$J$2005,Settings!$B$5) -> 11540 | G30: =SUMIFS(Transactions!$G$6:$G$2005,Transactions!$B$6:$B$2005,"Expense",Transactions!$C$6:$C$2005,$A30,Transactions!$I$6:$I$2005,G$3,Transactions!$J$6:$J$2005,Settings!$B$5) -> 10620 | H30: =SUMIFS(Transactions!$G$6:$G$2005,Transactions!$B$6:$B$2005,"Expense",Transactions!$C$6:$C$2005,$A30,Transactions!$I$6:$I$2005,H$3,Transactions!$J$6:$J$2005,Settings!$B$5) -> 11070 | I30: =SUMIFS(Transactions!$G$6:$G$2005,Transactions!$B$6:$B$2005,"Expense",Transactions!$C$6:$C$2005,$A30,Transactions!$I$6:$I$2005,I$3,Transactions!$J$6:$J$2005,Settings!$B$5) -> 11650 | J30: =SUMIFS(Transactions!$G$6:$G$2005,Transactions!$B$6:$B$2005,"Expense",Transactions!$C$6:$C$2005,$A30,Transactions!$I$6:$I$2005,J$3,Transactions!$J$6:$J$2005,Settings!$B$5) -> 11430 | ... N30: =SUMIFS(Transactions!$G$6:$G$2005,Transactions!$B$6:$B$2005,"Expense",Transactions!$C$6:$C$2005,$A30,Transactions!$I$6:$I$2005,N$3,Transactions!$J$6:$J$2005,Settings!$B$5) -> 0 | O30: =SUM(C30:N30) -> 108460 | P30: =Budget!$I$15 -> 132000 | Q30: =P30-O30 -> 23540 | R30: =IF(P30=0,"",O30/P30) -> 0.82166667
A31: =Settings!$K$26 -> Dining Out & Food Delivery | B31: =Settings!$L$26 -> Food | C31: =SUMIFS(Transactions!$G$6:$G$2005,Transactions!$B$6:$B$2005,"Expense",Transactions!$C$6:$C$2005,$A31,Transactions!$I$6:$I$2005,C$3,Transactions!$J$6:$J$2005,Settings!$B$5) -> 930 | D31: =SUMIFS(Transactions!$G$6:$G$2005,Transactions!$B$6:$B$2005,"Expense",Transactions!$C$6:$C$2005,$A31,Transactions!$I$6:$I$2005,D$3,Transactions!$J$6:$J$2005,Settings!$B$5) -> 1060 | E31: =SUMIFS(Transactions!$G$6:$G$2005,Transactions!$B$6:$B$2005,"Expense",Transactions!$C$6:$C$2005,$A31,Transactions!$I$6:$I$2005,E$3,Transactions!$J$6:$J$2005,Settings!$B$5) -> 920 | F31: =SUMIFS(Transactions!$G$6:$G$2005,Transactions!$B$6:$B$2005,"Expense",Transactions!$C$6:$C$2005,$A31,Transactions!$I$6:$I$2005,F$3,Transactions!$J$6:$J$2005,Settings!$B$5) -> 990 | G31: =SUMIFS(Transactions!$G$6:$G$2005,Transactions!$B$6:$B$2005,"Expense",Transactions!$C$6:$C$2005,$A31,Transactions!$I$6:$I$2005,G$3,Transactions!$J$6:$J$2005,Settings!$B$5) -> 1030 | H31: =SUMIFS(Transactions!$G$6:$G$2005,Transactions!$B$6:$B$2005,"Expense",Transactions!$C$6:$C$2005,$A31,Transactions!$I$6:$I$2005,H$3,Transactions!$J$6:$J$2005,Settings!$B$5) -> 1070 | I31: =SUMIFS(Transactions!$G$6:$G$2005,Transactions!$B$6:$B$2005,"Expense",Transactions!$C$6:$C$2005,$A31,Transactions!$I$6:$I$2005,I$3,Transactions!$J$6:$J$2005,Settings!$B$5) -> 1070 | J31: =SUMIFS(Transactions!$G$6:$G$2005,Transactions!$B$6:$B$2005,"Expense",Transactions!$C$6:$C$2005,$A31,Transactions!$I$6:$I$2005,J$3,Transactions!$J$6:$J$2005,Settings!$B$5) -> 1020 | ... N31: =SUMIFS(Transactions!$G$6:$G$2005,Transactions!$B$6:$B$2005,"Expense",Transactions!$C$6:$C$2005,$A31,Transactions!$I$6:$I$2005,N$3,Transactions!$J$6:$J$2005,Settings!$B$5) -> 0 | O31: =SUM(C31:N31) -> 10040 | P31: =Budget!$I$16 -> 24000 | Q31: =P31-O31 -> 13960 | R31: =IF(P31=0,"",O31/P31) -> 0.41833333
A32: =Settings!$K$27 -> Rickshaw / CNG / Ride-share | B32: =Settings!$L$27 -> Transport | C32: =SUMIFS(Transactions!$G$6:$G$2005,Transactions!$B$6:$B$2005,"Expense",Transactions!$C$6:$C$2005,$A32,Transactions!$I$6:$I$2005,C$3,Transactions!$J$6:$J$2005,Settings!$B$5) -> 1770 | D32: =SUMIFS(Transactions!$G$6:$G$2005,Transactions!$B$6:$B$2005,"Expense",Transactions!$C$6:$C$2005,$A32,Transactions!$I$6:$I$2005,D$3,Transactions!$J$6:$J$2005,Settings!$B$5) -> 1800 | E32: =SUMIFS(Transactions!$G$6:$G$2005,Transactions!$B$6:$B$2005,"Expense",Transactions!$C$6:$C$2005,$A32,Transactions!$I$6:$I$2005,E$3,Transactions!$J$6:$J$2005,Settings!$B$5) -> 1740 | F32: =SUMIFS(Transactions!$G$6:$G$2005,Transactions!$B$6:$B$2005,"Expense",Transactions!$C$6:$C$2005,$A32,Transactions!$I$6:$I$2005,F$3,Transactions!$J$6:$J$2005,Settings!$B$5) -> 1710 | G32: =SUMIFS(Transactions!$G$6:$G$2005,Transactions!$B$6:$B$2005,"Expense",Transactions!$C$6:$C$2005,$A32,Transactions!$I$6:$I$2005,G$3,Transactions!$J$6:$J$2005,Settings!$B$5) -> 1620 | H32: =SUMIFS(Transactions!$G$6:$G$2005,Transactions!$B$6:$B$2005,"Expense",Transactions!$C$6:$C$2005,$A32,Transactions!$I$6:$I$2005,H$3,Transactions!$J$6:$J$2005,Settings!$B$5) -> 1740 | I32: =SUMIFS(Transactions!$G$6:$G$2005,Transactions!$B$6:$B$2005,"Expense",Transactions!$C$6:$C$2005,$A32,Transactions!$I$6:$I$2005,I$3,Transactions!$J$6:$J$2005,Settings!$B$5) -> 1710 | J32: =SUMIFS(Transactions!$G$6:$G$2005,Transactions!$B$6:$B$2005,"Expense",Transactions!$C$6:$C$2005,$A32,Transactions!$I$6:$I$2005,J$3,Transactions!$J$6:$J$2005,Settings!$B$5) -> 1750 | ... N32: =SUMIFS(Transactions!$G$6:$G$2005,Transactions!$B$6:$B$2005,"Expense",Transactions!$C$6:$C$2005,$A32,Transactions!$I$6:$I$2005,N$3,Transactions!$J$6:$J$2005,Settings!$B$5) -> 0 | O32: =SUM(C32:N32) -> 17130 | P32: =Budget!$I$17 -> 30000 | Q32: =P32-O32 -> 12870 | R32: =IF(P32=0,"",O32/P32) -> 0.571
A33: =Settings!$K$28 -> Bus / Metro Rail / Train | B33: =Settings!$L$28 -> Transport | C33: =SUMIFS(Transactions!$G$6:$G$2005,Transactions!$B$6:$B$2005,"Expense",Transactions!$C$6:$C$2005,$A33,Transactions!$I$6:$I$2005,C$3,Transactions!$J$6:$J$2005,Settings!$B$5) -> 0 | D33: =SUMIFS(Transactions!$G$6:$G$2005,Transactions!$B$6:$B$2005,"Expense",Transactions!$C$6:$C$2005,$A33,Transactions!$I$6:$I$2005,D$3,Transactions!$J$6:$J$2005,Settings!$B$5) -> 0 | E33: =SUMIFS(Transactions!$G$6:$G$2005,Transactions!$B$6:$B$2005,"Expense",Transactions!$C$6:$C$2005,$A33,Transactions!$I$6:$I$2005,E$3,Transactions!$J$6:$J$2005,Settings!$B$5) -> 0 | F33: =SUMIFS(Transactions!$G$6:$G$2005,Transactions!$B$6:$B$2005,"Expense",Transactions!$C$6:$C$2005,$A33,Transactions!$I$6:$I$2005,F$3,Transactions!$J$6:$J$2005,Settings!$B$5) -> 0 | G33: =SUMIFS(Transactions!$G$6:$G$2005,Transactions!$B$6:$B$2005,"Expense",Transactions!$C$6:$C$2005,$A33,Transactions!$I$6:$I$2005,G$3,Transactions!$J$6:$J$2005,Settings!$B$5) -> 0 | H33: =SUMIFS(Transactions!$G$6:$G$2005,Transactions!$B$6:$B$2005,"Expense",Transactions!$C$6:$C$2005,$A33,Transactions!$I$6:$I$2005,H$3,Transactions!$J$6:$J$2005,Settings!$B$5) -> 0 | I33: =SUMIFS(Transactions!$G$6:$G$2005,Transactions!$B$6:$B$2005,"Expense",Transactions!$C$6:$C$2005,$A33,Transactions!$I$6:$I$2005,I$3,Transactions!$J$6:$J$2005,Settings!$B$5) -> 0 | J33: =SUMIFS(Transactions!$G$6:$G$2005,Transactions!$B$6:$B$2005,"Expense",Transactions!$C$6:$C$2005,$A33,Transactions!$I$6:$I$2005,J$3,Transactions!$J$6:$J$2005,Settings!$B$5) -> 0 | ... N33: =SUMIFS(Transactions!$G$6:$G$2005,Transactions!$B$6:$B$2005,"Expense",Transactions!$C$6:$C$2005,$A33,Transactions!$I$6:$I$2005,N$3,Transactions!$J$6:$J$2005,Settings!$B$5) -> 0 | O33: =SUM(C33:N33) -> 0 | P33: =Budget!$I$18 -> 6000 | Q33: =P33-O33 -> 6000 | R33: =IF(P33=0,"",O33/P33) -> 0
A34: =Settings!$K$29 -> Fuel (Octane / Petrol / CNG) | B34: =Settings!$L$29 -> Transport | C34: =SUMIFS(Transactions!$G$6:$G$2005,Transactions!$B$6:$B$2005,"Expense",Transactions!$C$6:$C$2005,$A34,Transactions!$I$6:$I$2005,C$3,Transactions!$J$6:$J$2005,Settings!$B$5) -> 1300 | D34: =SUMIFS(Transactions!$G$6:$G$2005,Transactions!$B$6:$B$2005,"Expense",Transactions!$C$6:$C$2005,$A34,Transactions!$I$6:$I$2005,D$3,Transactions!$J$6:$J$2005,Settings!$B$5) -> 1290 | E34: =SUMIFS(Transactions!$G$6:$G$2005,Transactions!$B$6:$B$2005,"Expense",Transactions!$C$6:$C$2005,$A34,Transactions!$I$6:$I$2005,E$3,Transactions!$J$6:$J$2005,Settings!$B$5) -> 1410 | F34: =SUMIFS(Transactions!$G$6:$G$2005,Transactions!$B$6:$B$2005,"Expense",Transactions!$C$6:$C$2005,$A34,Transactions!$I$6:$I$2005,F$3,Transactions!$J$6:$J$2005,Settings!$B$5) -> 1490 | G34: =SUMIFS(Transactions!$G$6:$G$2005,Transactions!$B$6:$B$2005,"Expense",Transactions!$C$6:$C$2005,$A34,Transactions!$I$6:$I$2005,G$3,Transactions!$J$6:$J$2005,Settings!$B$5) -> 1370 | H34: =SUMIFS(Transactions!$G$6:$G$2005,Transactions!$B$6:$B$2005,"Expense",Transactions!$C$6:$C$2005,$A34,Transactions!$I$6:$I$2005,H$3,Transactions!$J$6:$J$2005,Settings!$B$5) -> 1300 | I34: =SUMIFS(Transactions!$G$6:$G$2005,Transactions!$B$6:$B$2005,"Expense",Transactions!$C$6:$C$2005,$A34,Transactions!$I$6:$I$2005,I$3,Transactions!$J$6:$J$2005,Settings!$B$5) -> 1390 | J34: =SUMIFS(Transactions!$G$6:$G$2005,Transactions!$B$6:$B$2005,"Expense",Transactions!$C$6:$C$2005,$A34,Transactions!$I$6:$I$2005,J$3,Transactions!$J$6:$J$2005,Settings!$B$5) -> 1420 | ... N34: =SUMIFS(Transactions!$G$6:$G$2005,Transactions!$B$6:$B$2005,"Expense",Transactions!$C$6:$C$2005,$A34,Transactions!$I$6:$I$2005,N$3,Transactions!$J$6:$J$2005,Settings!$B$5) -> 0 | O34: =SUM(C34:N34) -> 13760 | P34: =Budget!$I$19 -> 18000 | Q34: =P34-O34 -> 4240 | R34: =IF(P34=0,"",O34/P34) -> 0.76444444
A35: =Settings!$K$30 -> Vehicle Maintenance & Parking | B35: =Settings!$L$30 -> Transport | C35: =SUMIFS(Transactions!$G$6:$G$2005,Transactions!$B$6:$B$2005,"Expense",Transactions!$C$6:$C$2005,$A35,Transactions!$I$6:$I$2005,C$3,Transactions!$J$6:$J$2005,Settings!$B$5) -> 0 | D35: =SUMIFS(Transactions!$G$6:$G$2005,Transactions!$B$6:$B$2005,"Expense",Transactions!$C$6:$C$2005,$A35,Transactions!$I$6:$I$2005,D$3,Transactions!$J$6:$J$2005,Settings!$B$5) -> 0 | E35: =SUMIFS(Transactions!$G$6:$G$2005,Transactions!$B$6:$B$2005,"Expense",Transactions!$C$6:$C$2005,$A35,Transactions!$I$6:$I$2005,E$3,Transactions!$J$6:$J$2005,Settings!$B$5) -> 2030 | F35: =SUMIFS(Transactions!$G$6:$G$2005,Transactions!$B$6:$B$2005,"Expense",Transactions!$C$6:$C$2005,$A35,Transactions!$I$6:$I$2005,F$3,Transactions!$J$6:$J$2005,Settings!$B$5) -> 0 | G35: =SUMIFS(Transactions!$G$6:$G$2005,Transactions!$B$6:$B$2005,"Expense",Transactions!$C$6:$C$2005,$A35,Transactions!$I$6:$I$2005,G$3,Transactions!$J$6:$J$2005,Settings!$B$5) -> 0 | H35: =SUMIFS(Transactions!$G$6:$G$2005,Transactions!$B$6:$B$2005,"Expense",Transactions!$C$6:$C$2005,$A35,Transactions!$I$6:$I$2005,H$3,Transactions!$J$6:$J$2005,Settings!$B$5) -> 2360 | I35: =SUMIFS(Transactions!$G$6:$G$2005,Transactions!$B$6:$B$2005,"Expense",Transactions!$C$6:$C$2005,$A35,Transactions!$I$6:$I$2005,I$3,Transactions!$J$6:$J$2005,Settings!$B$5) -> 0 | J35: =SUMIFS(Transactions!$G$6:$G$2005,Transactions!$B$6:$B$2005,"Expense",Transactions!$C$6:$C$2005,$A35,Transactions!$I$6:$I$2005,J$3,Transactions!$J$6:$J$2005,Settings!$B$5) -> 0 | ... N35: =SUMIFS(Transactions!$G$6:$G$2005,Transactions!$B$6:$B$2005,"Expense",Transactions!$C$6:$C$2005,$A35,Transactions!$I$6:$I$2005,N$3,Transactions!$J$6:$J$2005,Settings!$B$5) -> 0 | O35: =SUM(C35:N35) -> 6420 | P35: =Budget!$I$20 -> 9600 | Q35: =P35-O35 -> 3180 | R35: =IF(P35=0,"",O35/P35) -> 0.66875
A36: =Settings!$K$31 -> School / College / University Fees | B36: =Settings!$L$31 -> Family & Education | C36: =SUMIFS(Transactions!$G$6:$G$2005,Transactions!$B$6:$B$2005,"Expense",Transactions!$C$6:$C$2005,$A36,Transactions!$I$6:$I$2005,C$3,Transactions!$J$6:$J$2005,Settings!$B$5) -> 3500 | D36: =SUMIFS(Transactions!$G$6:$G$2005,Transactions!$B$6:$B$2005,"Expense",Transactions!$C$6:$C$2005,$A36,Transactions!$I$6:$I$2005,D$3,Transactions!$J$6:$J$2005,Settings!$B$5) -> 3500 | E36: =SUMIFS(Transactions!$G$6:$G$2005,Transactions!$B$6:$B$2005,"Expense",Transactions!$C$6:$C$2005,$A36,Transactions!$I$6:$I$2005,E$3,Transactions!$J$6:$J$2005,Settings!$B$5) -> 3500 | F36: =SUMIFS(Transactions!$G$6:$G$2005,Transactions!$B$6:$B$2005,"Expense",Transactions!$C$6:$C$2005,$A36,Transactions!$I$6:$I$2005,F$3,Transactions!$J$6:$J$2005,Settings!$B$5) -> 3500 | G36: =SUMIFS(Transactions!$G$6:$G$2005,Transactions!$B$6:$B$2005,"Expense",Transactions!$C$6:$C$2005,$A36,Transactions!$I$6:$I$2005,G$3,Transactions!$J$6:$J$2005,Settings!$B$5) -> 3500 | H36: =SUMIFS(Transactions!$G$6:$G$2005,Transactions!$B$6:$B$2005,"Expense",Transactions!$C$6:$C$2005,$A36,Transactions!$I$6:$I$2005,H$3,Transactions!$J$6:$J$2005,Settings!$B$5) -> 3500 | I36: =SUMIFS(Transactions!$G$6:$G$2005,Transactions!$B$6:$B$2005,"Expense",Transactions!$C$6:$C$2005,$A36,Transactions!$I$6:$I$2005,I$3,Transactions!$J$6:$J$2005,Settings!$B$5) -> 3500 | J36: =SUMIFS(Transactions!$G$6:$G$2005,Transactions!$B$6:$B$2005,"Expense",Transactions!$C$6:$C$2005,$A36,Transactions!$I$6:$I$2005,J$3,Transactions!$J$6:$J$2005,Settings!$B$5) -> 3500 | ... N36: =SUMIFS(Transactions!$G$6:$G$2005,Transactions!$B$6:$B$2005,"Expense",Transactions!$C$6:$C$2005,$A36,Transactions!$I$6:$I$2005,N$3,Transactions!$J$6:$J$2005,Settings!$B$5) -> 0 | O36: =SUM(C36:N36) -> 35000 | P36: =Budget!$I$21 -> 42000 | Q36: =P36-O36 -> 7000 | R36: =IF(P36=0,"",O36/P36) -> 0.83333333
A37: =Settings!$K$32 -> Coaching & Books | B37: =Settings!$L$32 -> Family & Education | C37: =SUMIFS(Transactions!$G$6:$G$2005,Transactions!$B$6:$B$2005,"Expense",Transactions!$C$6:$C$2005,$A37,Transactions!$I$6:$I$2005,C$3,Transactions!$J$6:$J$2005,Settings!$B$5) -> 0 | D37: =SUMIFS(Transactions!$G$6:$G$2005,Transactions!$B$6:$B$2005,"Expense",Transactions!$C$6:$C$2005,$A37,Transactions!$I$6:$I$2005,D$3,Transactions!$J$6:$J$2005,Settings!$B$5) -> 0 | E37: =SUMIFS(Transactions!$G$6:$G$2005,Transactions!$B$6:$B$2005,"Expense",Transactions!$C$6:$C$2005,$A37,Transactions!$I$6:$I$2005,E$3,Transactions!$J$6:$J$2005,Settings!$B$5) -> 0 | F37: =SUMIFS(Transactions!$G$6:$G$2005,Transactions!$B$6:$B$2005,"Expense",Transactions!$C$6:$C$2005,$A37,Transactions!$I$6:$I$2005,F$3,Transactions!$J$6:$J$2005,Settings!$B$5) -> 0 | G37: =SUMIFS(Transactions!$G$6:$G$2005,Transactions!$B$6:$B$2005,"Expense",Transactions!$C$6:$C$2005,$A37,Transactions!$I$6:$I$2005,G$3,Transactions!$J$6:$J$2005,Settings!$B$5) -> 0 | H37: =SUMIFS(Transactions!$G$6:$G$2005,Transactions!$B$6:$B$2005,"Expense",Transactions!$C$6:$C$2005,$A37,Transactions!$I$6:$I$2005,H$3,Transactions!$J$6:$J$2005,Settings!$B$5) -> 0 | I37: =SUMIFS(Transactions!$G$6:$G$2005,Transactions!$B$6:$B$2005,"Expense",Transactions!$C$6:$C$2005,$A37,Transactions!$I$6:$I$2005,I$3,Transactions!$J$6:$J$2005,Settings!$B$5) -> 0 | J37: =SUMIFS(Transactions!$G$6:$G$2005,Transactions!$B$6:$B$2005,"Expense",Transactions!$C$6:$C$2005,$A37,Transactions!$I$6:$I$2005,J$3,Transactions!$J$6:$J$2005,Settings!$B$5) -> 0 | ... N37: =SUMIFS(Transactions!$G$6:$G$2005,Transactions!$B$6:$B$2005,"Expense",Transactions!$C$6:$C$2005,$A37,Transactions!$I$6:$I$2005,N$3,Transactions!$J$6:$J$2005,Settings!$B$5) -> 0 | O37: =SUM(C37:N37) -> 0 | P37: =Budget!$I$22 -> 0 | Q37: =P37-O37 -> 0 | R37: =IF(P37=0,"",O37/P37)
A38: =Settings!$K$33 -> Child Care & Baby Needs | B38: =Settings!$L$33 -> Family & Education | C38: =SUMIFS(Transactions!$G$6:$G$2005,Transactions!$B$6:$B$2005,"Expense",Transactions!$C$6:$C$2005,$A38,Transactions!$I$6:$I$2005,C$3,Transactions!$J$6:$J$2005,Settings!$B$5) -> 0 | D38: =SUMIFS(Transactions!$G$6:$G$2005,Transactions!$B$6:$B$2005,"Expense",Transactions!$C$6:$C$2005,$A38,Transactions!$I$6:$I$2005,D$3,Transactions!$J$6:$J$2005,Settings!$B$5) -> 0 | E38: =SUMIFS(Transactions!$G$6:$G$2005,Transactions!$B$6:$B$2005,"Expense",Transactions!$C$6:$C$2005,$A38,Transactions!$I$6:$I$2005,E$3,Transactions!$J$6:$J$2005,Settings!$B$5) -> 0 | F38: =SUMIFS(Transactions!$G$6:$G$2005,Transactions!$B$6:$B$2005,"Expense",Transactions!$C$6:$C$2005,$A38,Transactions!$I$6:$I$2005,F$3,Transactions!$J$6:$J$2005,Settings!$B$5) -> 0 | G38: =SUMIFS(Transactions!$G$6:$G$2005,Transactions!$B$6:$B$2005,"Expense",Transactions!$C$6:$C$2005,$A38,Transactions!$I$6:$I$2005,G$3,Transactions!$J$6:$J$2005,Settings!$B$5) -> 0 | H38: =SUMIFS(Transactions!$G$6:$G$2005,Transactions!$B$6:$B$2005,"Expense",Transactions!$C$6:$C$2005,$A38,Transactions!$I$6:$I$2005,H$3,Transactions!$J$6:$J$2005,Settings!$B$5) -> 0 | I38: =SUMIFS(Transactions!$G$6:$G$2005,Transactions!$B$6:$B$2005,"Expense",Transactions!$C$6:$C$2005,$A38,Transactions!$I$6:$I$2005,I$3,Transactions!$J$6:$J$2005,Settings!$B$5) -> 0 | J38: =SUMIFS(Transactions!$G$6:$G$2005,Transactions!$B$6:$B$2005,"Expense",Transactions!$C$6:$C$2005,$A38,Transactions!$I$6:$I$2005,J$3,Transactions!$J$6:$J$2005,Settings!$B$5) -> 0 | ... N38: =SUMIFS(Transactions!$G$6:$G$2005,Transactions!$B$6:$B$2005,"Expense",Transactions!$C$6:$C$2005,$A38,Transactions!$I$6:$I$2005,N$3,Transactions!$J$6:$J$2005,Settings!$B$5) -> 0 | O38: =SUM(C38:N38) -> 0 | P38: =Budget!$I$23 -> 12000 | Q38: =P38-O38 -> 12000 | R38: =IF(P38=0,"",O38/P38) -> 0
A39: =Settings!$K$34 -> Parents / Family Support | B39: =Settings!$L$34 -> Family & Education | C39: =SUMIFS(Transactions!$G$6:$G$2005,Transactions!$B$6:$B$2005,"Expense",Transactions!$C$6:$C$2005,$A39,Transactions!$I$6:$I$2005,C$3,Transactions!$J$6:$J$2005,Settings!$B$5) -> 5000 | D39: =SUMIFS(Transactions!$G$6:$G$2005,Transactions!$B$6:$B$2005,"Expense",Transactions!$C$6:$C$2005,$A39,Transactions!$I$6:$I$2005,D$3,Transactions!$J$6:$J$2005,Settings!$B$5) -> 5000 | E39: =SUMIFS(Transactions!$G$6:$G$2005,Transactions!$B$6:$B$2005,"Expense",Transactions!$C$6:$C$2005,$A39,Transactions!$I$6:$I$2005,E$3,Transactions!$J$6:$J$2005,Settings!$B$5) -> 5000 | F39: =SUMIFS(Transactions!$G$6:$G$2005,Transactions!$B$6:$B$2005,"Expense",Transactions!$C$6:$C$2005,$A39,Transactions!$I$6:$I$2005,F$3,Transactions!$J$6:$J$2005,Settings!$B$5) -> 5000 | G39: =SUMIFS(Transactions!$G$6:$G$2005,Transactions!$B$6:$B$2005,"Expense",Transactions!$C$6:$C$2005,$A39,Transactions!$I$6:$I$2005,G$3,Transactions!$J$6:$J$2005,Settings!$B$5) -> 5000 | H39: =SUMIFS(Transactions!$G$6:$G$2005,Transactions!$B$6:$B$2005,"Expense",Transactions!$C$6:$C$2005,$A39,Transactions!$I$6:$I$2005,H$3,Transactions!$J$6:$J$2005,Settings!$B$5) -> 5000 | I39: =SUMIFS(Transactions!$G$6:$G$2005,Transactions!$B$6:$B$2005,"Expense",Transactions!$C$6:$C$2005,$A39,Transactions!$I$6:$I$2005,I$3,Transactions!$J$6:$J$2005,Settings!$B$5) -> 5000 | J39: =SUMIFS(Transactions!$G$6:$G$2005,Transactions!$B$6:$B$2005,"Expense",Transactions!$C$6:$C$2005,$A39,Transactions!$I$6:$I$2005,J$3,Transactions!$J$6:$J$2005,Settings!$B$5) -> 5000 | ... N39: =SUMIFS(Transactions!$G$6:$G$2005,Transactions!$B$6:$B$2005,"Expense",Transactions!$C$6:$C$2005,$A39,Transactions!$I$6:$I$2005,N$3,Transactions!$J$6:$J$2005,Settings!$B$5) -> 0 | O39: =SUM(C39:N39) -> 50000 | P39: =Budget!$I$24 -> 60000 | Q39: =P39-O39 -> 10000 | R39: =IF(P39=0,"",O39/P39) -> 0.83333333
A40: =Settings!$K$35 -> Medicine & Doctor Visits | B40: =Settings!$L$35 -> Health | C40: =SUMIFS(Transactions!$G$6:$G$2005,Transactions!$B$6:$B$2005,"Expense",Transactions!$C$6:$C$2005,$A40,Transactions!$I$6:$I$2005,C$3,Transactions!$J$6:$J$2005,Settings!$B$5) -> 1550 | D40: =SUMIFS(Transactions!$G$6:$G$2005,Transactions!$B$6:$B$2005,"Expense",Transactions!$C$6:$C$2005,$A40,Transactions!$I$6:$I$2005,D$3,Transactions!$J$6:$J$2005,Settings!$B$5) -> 1770 | E40: =SUMIFS(Transactions!$G$6:$G$2005,Transactions!$B$6:$B$2005,"Expense",Transactions!$C$6:$C$2005,$A40,Transactions!$I$6:$I$2005,E$3,Transactions!$J$6:$J$2005,Settings!$B$5) -> 1080 | F40: =SUMIFS(Transactions!$G$6:$G$2005,Transactions!$B$6:$B$2005,"Expense",Transactions!$C$6:$C$2005,$A40,Transactions!$I$6:$I$2005,F$3,Transactions!$J$6:$J$2005,Settings!$B$5) -> 1190 | G40: =SUMIFS(Transactions!$G$6:$G$2005,Transactions!$B$6:$B$2005,"Expense",Transactions!$C$6:$C$2005,$A40,Transactions!$I$6:$I$2005,G$3,Transactions!$J$6:$J$2005,Settings!$B$5) -> 1640 | H40: =SUMIFS(Transactions!$G$6:$G$2005,Transactions!$B$6:$B$2005,"Expense",Transactions!$C$6:$C$2005,$A40,Transactions!$I$6:$I$2005,H$3,Transactions!$J$6:$J$2005,Settings!$B$5) -> 1060 | I40: =SUMIFS(Transactions!$G$6:$G$2005,Transactions!$B$6:$B$2005,"Expense",Transactions!$C$6:$C$2005,$A40,Transactions!$I$6:$I$2005,I$3,Transactions!$J$6:$J$2005,Settings!$B$5) -> 1310 | J40: =SUMIFS(Transactions!$G$6:$G$2005,Transactions!$B$6:$B$2005,"Expense",Transactions!$C$6:$C$2005,$A40,Transactions!$I$6:$I$2005,J$3,Transactions!$J$6:$J$2005,Settings!$B$5) -> 1670 | ... N40: =SUMIFS(Transactions!$G$6:$G$2005,Transactions!$B$6:$B$2005,"Expense",Transactions!$C$6:$C$2005,$A40,Transactions!$I$6:$I$2005,N$3,Transactions!$J$6:$J$2005,Settings!$B$5) -> 0 | O40: =SUM(C40:N40) -> 14170 | P40: =Budget!$I$25 -> 18000 | Q40: =P40-O40 -> 3830 | R40: =IF(P40=0,"",O40/P40) -> 0.78722222
A41: =Settings!$K$36 -> Medical Tests & Hospital | B41: =Settings!$L$36 -> Health | C41: =SUMIFS(Transactions!$G$6:$G$2005,Transactions!$B$6:$B$2005,"Expense",Transactions!$C$6:$C$2005,$A41,Transactions!$I$6:$I$2005,C$3,Transactions!$J$6:$J$2005,Settings!$B$5) -> 0 | D41: =SUMIFS(Transactions!$G$6:$G$2005,Transactions!$B$6:$B$2005,"Expense",Transactions!$C$6:$C$2005,$A41,Transactions!$I$6:$I$2005,D$3,Transactions!$J$6:$J$2005,Settings!$B$5) -> 0 | E41: =SUMIFS(Transactions!$G$6:$G$2005,Transactions!$B$6:$B$2005,"Expense",Transactions!$C$6:$C$2005,$A41,Transactions!$I$6:$I$2005,E$3,Transactions!$J$6:$J$2005,Settings!$B$5) -> 0 | F41: =SUMIFS(Transactions!$G$6:$G$2005,Transactions!$B$6:$B$2005,"Expense",Transactions!$C$6:$C$2005,$A41,Transactions!$I$6:$I$2005,F$3,Transactions!$J$6:$J$2005,Settings!$B$5) -> 1800 | G41: =SUMIFS(Transactions!$G$6:$G$2005,Transactions!$B$6:$B$2005,"Expense",Transactions!$C$6:$C$2005,$A41,Transactions!$I$6:$I$2005,G$3,Transactions!$J$6:$J$2005,Settings!$B$5) -> 0 | H41: =SUMIFS(Transactions!$G$6:$G$2005,Transactions!$B$6:$B$2005,"Expense",Transactions!$C$6:$C$2005,$A41,Transactions!$I$6:$I$2005,H$3,Transactions!$J$6:$J$2005,Settings!$B$5) -> 0 | I41: =SUMIFS(Transactions!$G$6:$G$2005,Transactions!$B$6:$B$2005,"Expense",Transactions!$C$6:$C$2005,$A41,Transactions!$I$6:$I$2005,I$3,Transactions!$J$6:$J$2005,Settings!$B$5) -> 0 | J41: =SUMIFS(Transactions!$G$6:$G$2005,Transactions!$B$6:$B$2005,"Expense",Transactions!$C$6:$C$2005,$A41,Transactions!$I$6:$I$2005,J$3,Transactions!$J$6:$J$2005,Settings!$B$5) -> 0 | ... N41: =SUMIFS(Transactions!$G$6:$G$2005,Transactions!$B$6:$B$2005,"Expense",Transactions!$C$6:$C$2005,$A41,Transactions!$I$6:$I$2005,N$3,Transactions!$J$6:$J$2005,Settings!$B$5) -> 0 | O41: =SUM(C41:N41) -> 3600 | P41: =Budget!$I$26 -> 6000 | Q41: =P41-O41 -> 2400 | R41: =IF(P41=0,"",O41/P41) -> 0.6
A42: =Settings!$K$37 -> Clothing & Footwear | B42: =Settings!$L$37 -> Lifestyle | C42: =SUMIFS(Transactions!$G$6:$G$2005,Transactions!$B$6:$B$2005,"Expense",Transactions!$C$6:$C$2005,$A42,Transactions!$I$6:$I$2005,C$3,Transactions!$J$6:$J$2005,Settings!$B$5) -> 0 | D42: =SUMIFS(Transactions!$G$6:$G$2005,Transactions!$B$6:$B$2005,"Expense",Transactions!$C$6:$C$2005,$A42,Transactions!$I$6:$I$2005,D$3,Transactions!$J$6:$J$2005,Settings!$B$5) -> 0 | E42: =SUMIFS(Transactions!$G$6:$G$2005,Transactions!$B$6:$B$2005,"Expense",Transactions!$C$6:$C$2005,$A42,Transactions!$I$6:$I$2005,E$3,Transactions!$J$6:$J$2005,Settings!$B$5) -> 9000 | F42: =SUMIFS(Transactions!$G$6:$G$2005,Transactions!$B$6:$B$2005,"Expense",Transactions!$C$6:$C$2005,$A42,Transactions!$I$6:$I$2005,F$3,Transactions!$J$6:$J$2005,Settings!$B$5) -> 2500 | G42: =SUMIFS(Transactions!$G$6:$G$2005,Transactions!$B$6:$B$2005,"Expense",Transactions!$C$6:$C$2005,$A42,Transactions!$I$6:$I$2005,G$3,Transactions!$J$6:$J$2005,Settings!$B$5) -> 7500 | H42: =SUMIFS(Transactions!$G$6:$G$2005,Transactions!$B$6:$B$2005,"Expense",Transactions!$C$6:$C$2005,$A42,Transactions!$I$6:$I$2005,H$3,Transactions!$J$6:$J$2005,Settings!$B$5) -> 0 | I42: =SUMIFS(Transactions!$G$6:$G$2005,Transactions!$B$6:$B$2005,"Expense",Transactions!$C$6:$C$2005,$A42,Transactions!$I$6:$I$2005,I$3,Transactions!$J$6:$J$2005,Settings!$B$5) -> 0 | J42: =SUMIFS(Transactions!$G$6:$G$2005,Transactions!$B$6:$B$2005,"Expense",Transactions!$C$6:$C$2005,$A42,Transactions!$I$6:$I$2005,J$3,Transactions!$J$6:$J$2005,Settings!$B$5) -> 3000 | ... N42: =SUMIFS(Transactions!$G$6:$G$2005,Transactions!$B$6:$B$2005,"Expense",Transactions!$C$6:$C$2005,$A42,Transactions!$I$6:$I$2005,N$3,Transactions!$J$6:$J$2005,Settings!$B$5) -> 0 | O42: =SUM(C42:N42) -> 22000 | P42: =Budget!$I$27 -> 24000 | Q42: =P42-O42 -> 2000 | R42: =IF(P42=0,"",O42/P42) -> 0.91666667
A43: =Settings!$K$38 -> Personal Care & Salon | B43: =Settings!$L$38 -> Lifestyle | C43: =SUMIFS(Transactions!$G$6:$G$2005,Transactions!$B$6:$B$2005,"Expense",Transactions!$C$6:$C$2005,$A43,Transactions!$I$6:$I$2005,C$3,Transactions!$J$6:$J$2005,Settings!$B$5) -> 800 | D43: =SUMIFS(Transactions!$G$6:$G$2005,Transactions!$B$6:$B$2005,"Expense",Transactions!$C$6:$C$2005,$A43,Transactions!$I$6:$I$2005,D$3,Transactions!$J$6:$J$2005,Settings!$B$5) -> 760 | E43: =SUMIFS(Transactions!$G$6:$G$2005,Transactions!$B$6:$B$2005,"Expense",Transactions!$C$6:$C$2005,$A43,Transactions!$I$6:$I$2005,E$3,Transactions!$J$6:$J$2005,Settings!$B$5) -> 740 | F43: =SUMIFS(Transactions!$G$6:$G$2005,Transactions!$B$6:$B$2005,"Expense",Transactions!$C$6:$C$2005,$A43,Transactions!$I$6:$I$2005,F$3,Transactions!$J$6:$J$2005,Settings!$B$5) -> 860 | G43: =SUMIFS(Transactions!$G$6:$G$2005,Transactions!$B$6:$B$2005,"Expense",Transactions!$C$6:$C$2005,$A43,Transactions!$I$6:$I$2005,G$3,Transactions!$J$6:$J$2005,Settings!$B$5) -> 860 | H43: =SUMIFS(Transactions!$G$6:$G$2005,Transactions!$B$6:$B$2005,"Expense",Transactions!$C$6:$C$2005,$A43,Transactions!$I$6:$I$2005,H$3,Transactions!$J$6:$J$2005,Settings!$B$5) -> 770 | I43: =SUMIFS(Transactions!$G$6:$G$2005,Transactions!$B$6:$B$2005,"Expense",Transactions!$C$6:$C$2005,$A43,Transactions!$I$6:$I$2005,I$3,Transactions!$J$6:$J$2005,Settings!$B$5) -> 740 | J43: =SUMIFS(Transactions!$G$6:$G$2005,Transactions!$B$6:$B$2005,"Expense",Transactions!$C$6:$C$2005,$A43,Transactions!$I$6:$I$2005,J$3,Transactions!$J$6:$J$2005,Settings!$B$5) -> 740 | ... N43: =SUMIFS(Transactions!$G$6:$G$2005,Transactions!$B$6:$B$2005,"Expense",Transactions!$C$6:$C$2005,$A43,Transactions!$I$6:$I$2005,N$3,Transactions!$J$6:$J$2005,Settings!$B$5) -> 0 | O43: =SUM(C43:N43) -> 7840 | P43: =Budget!$I$28 -> 9600 | Q43: =P43-O43 -> 1760 | R43: =IF(P43=0,"",O43/P43) -> 0.81666667
A44: =Settings!$K$39 -> Entertainment & Subscriptions | B44: =Settings!$L$39 -> Lifestyle | C44: =SUMIFS(Transactions!$G$6:$G$2005,Transactions!$B$6:$B$2005,"Expense",Transactions!$C$6:$C$2005,$A44,Transactions!$I$6:$I$2005,C$3,Transactions!$J$6:$J$2005,Settings!$B$5) -> 1100 | D44: =SUMIFS(Transactions!$G$6:$G$2005,Transactions!$B$6:$B$2005,"Expense",Transactions!$C$6:$C$2005,$A44,Transactions!$I$6:$I$2005,D$3,Transactions!$J$6:$J$2005,Settings!$B$5) -> 1100 | E44: =SUMIFS(Transactions!$G$6:$G$2005,Transactions!$B$6:$B$2005,"Expense",Transactions!$C$6:$C$2005,$A44,Transactions!$I$6:$I$2005,E$3,Transactions!$J$6:$J$2005,Settings!$B$5) -> 1100 | F44: =SUMIFS(Transactions!$G$6:$G$2005,Transactions!$B$6:$B$2005,"Expense",Transactions!$C$6:$C$2005,$A44,Transactions!$I$6:$I$2005,F$3,Transactions!$J$6:$J$2005,Settings!$B$5) -> 1100 | G44: =SUMIFS(Transactions!$G$6:$G$2005,Transactions!$B$6:$B$2005,"Expense",Transactions!$C$6:$C$2005,$A44,Transactions!$I$6:$I$2005,G$3,Transactions!$J$6:$J$2005,Settings!$B$5) -> 1100 | H44: =SUMIFS(Transactions!$G$6:$G$2005,Transactions!$B$6:$B$2005,"Expense",Transactions!$C$6:$C$2005,$A44,Transactions!$I$6:$I$2005,H$3,Transactions!$J$6:$J$2005,Settings!$B$5) -> 1100 | I44: =SUMIFS(Transactions!$G$6:$G$2005,Transactions!$B$6:$B$2005,"Expense",Transactions!$C$6:$C$2005,$A44,Transactions!$I$6:$I$2005,I$3,Transactions!$J$6:$J$2005,Settings!$B$5) -> 1100 | J44: =SUMIFS(Transactions!$G$6:$G$2005,Transactions!$B$6:$B$2005,"Expense",Transactions!$C$6:$C$2005,$A44,Transactions!$I$6:$I$2005,J$3,Transactions!$J$6:$J$2005,Settings!$B$5) -> 1100 | ... N44: =SUMIFS(Transactions!$G$6:$G$2005,Transactions!$B$6:$B$2005,"Expense",Transactions!$C$6:$C$2005,$A44,Transactions!$I$6:$I$2005,N$3,Transactions!$J$6:$J$2005,Settings!$B$5) -> 0 | O44: =SUM(C44:N44) -> 11000 | P44: =Budget!$I$29 -> 13200 | Q44: =P44-O44 -> 2200 | R44: =IF(P44=0,"",O44/P44) -> 0.83333333
A45: =Settings!$K$40 -> Travel & Holidays | B45: =Settings!$L$40 -> Lifestyle | C45: =SUMIFS(Transactions!$G$6:$G$2005,Transactions!$B$6:$B$2005,"Expense",Transactions!$C$6:$C$2005,$A45,Transactions!$I$6:$I$2005,C$3,Transactions!$J$6:$J$2005,Settings!$B$5) -> 0 | D45: =SUMIFS(Transactions!$G$6:$G$2005,Transactions!$B$6:$B$2005,"Expense",Transactions!$C$6:$C$2005,$A45,Transactions!$I$6:$I$2005,D$3,Transactions!$J$6:$J$2005,Settings!$B$5) -> 12000 | E45: =SUMIFS(Transactions!$G$6:$G$2005,Transactions!$B$6:$B$2005,"Expense",Transactions!$C$6:$C$2005,$A45,Transactions!$I$6:$I$2005,E$3,Transactions!$J$6:$J$2005,Settings!$B$5) -> 0 | F45: =SUMIFS(Transactions!$G$6:$G$2005,Transactions!$B$6:$B$2005,"Expense",Transactions!$C$6:$C$2005,$A45,Transactions!$I$6:$I$2005,F$3,Transactions!$J$6:$J$2005,Settings!$B$5) -> 0 | G45: =SUMIFS(Transactions!$G$6:$G$2005,Transactions!$B$6:$B$2005,"Expense",Transactions!$C$6:$C$2005,$A45,Transactions!$I$6:$I$2005,G$3,Transactions!$J$6:$J$2005,Settings!$B$5) -> 0 | H45: =SUMIFS(Transactions!$G$6:$G$2005,Transactions!$B$6:$B$2005,"Expense",Transactions!$C$6:$C$2005,$A45,Transactions!$I$6:$I$2005,H$3,Transactions!$J$6:$J$2005,Settings!$B$5) -> 0 | I45: =SUMIFS(Transactions!$G$6:$G$2005,Transactions!$B$6:$B$2005,"Expense",Transactions!$C$6:$C$2005,$A45,Transactions!$I$6:$I$2005,I$3,Transactions!$J$6:$J$2005,Settings!$B$5) -> 0 | J45: =SUMIFS(Transactions!$G$6:$G$2005,Transactions!$B$6:$B$2005,"Expense",Transactions!$C$6:$C$2005,$A45,Transactions!$I$6:$I$2005,J$3,Transactions!$J$6:$J$2005,Settings!$B$5) -> 0 | ... N45: =SUMIFS(Transactions!$G$6:$G$2005,Transactions!$B$6:$B$2005,"Expense",Transactions!$C$6:$C$2005,$A45,Transactions!$I$6:$I$2005,N$3,Transactions!$J$6:$J$2005,Settings!$B$5) -> 0 | O45: =SUM(C45:N45) -> 21000 | P45: =Budget!$I$30 -> 24000 | Q45: =P45-O45 -> 3000 | R45: =IF(P45=0,"",O45/P45) -> 0.875
A46: =Settings!$K$41 -> Gifts & Social Events | B46: =Settings!$L$41 -> Lifestyle | C46: =SUMIFS(Transactions!$G$6:$G$2005,Transactions!$B$6:$B$2005,"Expense",Transactions!$C$6:$C$2005,$A46,Transactions!$I$6:$I$2005,C$3,Transactions!$J$6:$J$2005,Settings!$B$5) -> 0 | D46: =SUMIFS(Transactions!$G$6:$G$2005,Transactions!$B$6:$B$2005,"Expense",Transactions!$C$6:$C$2005,$A46,Transactions!$I$6:$I$2005,D$3,Transactions!$J$6:$J$2005,Settings!$B$5) -> 1690 | E46: =SUMIFS(Transactions!$G$6:$G$2005,Transactions!$B$6:$B$2005,"Expense",Transactions!$C$6:$C$2005,$A46,Transactions!$I$6:$I$2005,E$3,Transactions!$J$6:$J$2005,Settings!$B$5) -> 0 | F46: =SUMIFS(Transactions!$G$6:$G$2005,Transactions!$B$6:$B$2005,"Expense",Transactions!$C$6:$C$2005,$A46,Transactions!$I$6:$I$2005,F$3,Transactions!$J$6:$J$2005,Settings!$B$5) -> 1530 | G46: =SUMIFS(Transactions!$G$6:$G$2005,Transactions!$B$6:$B$2005,"Expense",Transactions!$C$6:$C$2005,$A46,Transactions!$I$6:$I$2005,G$3,Transactions!$J$6:$J$2005,Settings!$B$5) -> 0 | H46: =SUMIFS(Transactions!$G$6:$G$2005,Transactions!$B$6:$B$2005,"Expense",Transactions!$C$6:$C$2005,$A46,Transactions!$I$6:$I$2005,H$3,Transactions!$J$6:$J$2005,Settings!$B$5) -> 1250 | I46: =SUMIFS(Transactions!$G$6:$G$2005,Transactions!$B$6:$B$2005,"Expense",Transactions!$C$6:$C$2005,$A46,Transactions!$I$6:$I$2005,I$3,Transactions!$J$6:$J$2005,Settings!$B$5) -> 0 | J46: =SUMIFS(Transactions!$G$6:$G$2005,Transactions!$B$6:$B$2005,"Expense",Transactions!$C$6:$C$2005,$A46,Transactions!$I$6:$I$2005,J$3,Transactions!$J$6:$J$2005,Settings!$B$5) -> 1530 | ... N46: =SUMIFS(Transactions!$G$6:$G$2005,Transactions!$B$6:$B$2005,"Expense",Transactions!$C$6:$C$2005,$A46,Transactions!$I$6:$I$2005,N$3,Transactions!$J$6:$J$2005,Settings!$B$5) -> 0 | O46: =SUM(C46:N46) -> 7690 | P46: =Budget!$I$31 -> 12000 | Q46: =P46-O46 -> 4310 | R46: =IF(P46=0,"",O46/P46) -> 0.64083333
A47: =Settings!$K$42 -> Zakat, Fitra & Sadaqah | B47: =Settings!$L$42 -> Religious & Social | C47: =SUMIFS(Transactions!$G$6:$G$2005,Transactions!$B$6:$B$2005,"Expense",Transactions!$C$6:$C$2005,$A47,Transactions!$I$6:$I$2005,C$3,Transactions!$J$6:$J$2005,Settings!$B$5) -> 0 | D47: =SUMIFS(Transactions!$G$6:$G$2005,Transactions!$B$6:$B$2005,"Expense",Transactions!$C$6:$C$2005,$A47,Transactions!$I$6:$I$2005,D$3,Transactions!$J$6:$J$2005,Settings!$B$5) -> 0 | E47: =SUMIFS(Transactions!$G$6:$G$2005,Transactions!$B$6:$B$2005,"Expense",Transactions!$C$6:$C$2005,$A47,Transactions!$I$6:$I$2005,E$3,Transactions!$J$6:$J$2005,Settings!$B$5) -> 36650 | F47: =SUMIFS(Transactions!$G$6:$G$2005,Transactions!$B$6:$B$2005,"Expense",Transactions!$C$6:$C$2005,$A47,Transactions!$I$6:$I$2005,F$3,Transactions!$J$6:$J$2005,Settings!$B$5) -> 0 | G47: =SUMIFS(Transactions!$G$6:$G$2005,Transactions!$B$6:$B$2005,"Expense",Transactions!$C$6:$C$2005,$A47,Transactions!$I$6:$I$2005,G$3,Transactions!$J$6:$J$2005,Settings!$B$5) -> 0 | H47: =SUMIFS(Transactions!$G$6:$G$2005,Transactions!$B$6:$B$2005,"Expense",Transactions!$C$6:$C$2005,$A47,Transactions!$I$6:$I$2005,H$3,Transactions!$J$6:$J$2005,Settings!$B$5) -> 0 | I47: =SUMIFS(Transactions!$G$6:$G$2005,Transactions!$B$6:$B$2005,"Expense",Transactions!$C$6:$C$2005,$A47,Transactions!$I$6:$I$2005,I$3,Transactions!$J$6:$J$2005,Settings!$B$5) -> 0 | J47: =SUMIFS(Transactions!$G$6:$G$2005,Transactions!$B$6:$B$2005,"Expense",Transactions!$C$6:$C$2005,$A47,Transactions!$I$6:$I$2005,J$3,Transactions!$J$6:$J$2005,Settings!$B$5) -> 0 | ... N47: =SUMIFS(Transactions!$G$6:$G$2005,Transactions!$B$6:$B$2005,"Expense",Transactions!$C$6:$C$2005,$A47,Transactions!$I$6:$I$2005,N$3,Transactions!$J$6:$J$2005,Settings!$B$5) -> 0 | O47: =SUM(C47:N47) -> 36650 | P47: =Budget!$I$32 -> 36000 | Q47: =P47-O47 -> -650 | R47: =IF(P47=0,"",O47/P47) -> 1.0180556
A48: =Settings!$K$43 -> Qurbani (Eid-ul-Adha) | B48: =Settings!$L$43 -> Religious & Social | C48: =SUMIFS(Transactions!$G$6:$G$2005,Transactions!$B$6:$B$2005,"Expense",Transactions!$C$6:$C$2005,$A48,Transactions!$I$6:$I$2005,C$3,Transactions!$J$6:$J$2005,Settings!$B$5) -> 0 | D48: =SUMIFS(Transactions!$G$6:$G$2005,Transactions!$B$6:$B$2005,"Expense",Transactions!$C$6:$C$2005,$A48,Transactions!$I$6:$I$2005,D$3,Transactions!$J$6:$J$2005,Settings!$B$5) -> 0 | E48: =SUMIFS(Transactions!$G$6:$G$2005,Transactions!$B$6:$B$2005,"Expense",Transactions!$C$6:$C$2005,$A48,Transactions!$I$6:$I$2005,E$3,Transactions!$J$6:$J$2005,Settings!$B$5) -> 0 | F48: =SUMIFS(Transactions!$G$6:$G$2005,Transactions!$B$6:$B$2005,"Expense",Transactions!$C$6:$C$2005,$A48,Transactions!$I$6:$I$2005,F$3,Transactions!$J$6:$J$2005,Settings!$B$5) -> 0 | G48: =SUMIFS(Transactions!$G$6:$G$2005,Transactions!$B$6:$B$2005,"Expense",Transactions!$C$6:$C$2005,$A48,Transactions!$I$6:$I$2005,G$3,Transactions!$J$6:$J$2005,Settings!$B$5) -> 20000 | H48: =SUMIFS(Transactions!$G$6:$G$2005,Transactions!$B$6:$B$2005,"Expense",Transactions!$C$6:$C$2005,$A48,Transactions!$I$6:$I$2005,H$3,Transactions!$J$6:$J$2005,Settings!$B$5) -> 0 | I48: =SUMIFS(Transactions!$G$6:$G$2005,Transactions!$B$6:$B$2005,"Expense",Transactions!$C$6:$C$2005,$A48,Transactions!$I$6:$I$2005,I$3,Transactions!$J$6:$J$2005,Settings!$B$5) -> 0 | J48: =SUMIFS(Transactions!$G$6:$G$2005,Transactions!$B$6:$B$2005,"Expense",Transactions!$C$6:$C$2005,$A48,Transactions!$I$6:$I$2005,J$3,Transactions!$J$6:$J$2005,Settings!$B$5) -> 0 | ... N48: =SUMIFS(Transactions!$G$6:$G$2005,Transactions!$B$6:$B$2005,"Expense",Transactions!$C$6:$C$2005,$A48,Transactions!$I$6:$I$2005,N$3,Transactions!$J$6:$J$2005,Settings!$B$5) -> 0 | O48: =SUM(C48:N48) -> 20000 | P48: =Budget!$I$33 -> 18000 | Q48: =P48-O48 -> -2000 | R48: =IF(P48=0,"",O48/P48) -> 1.1111111
A49: =Settings!$K$44 -> Festival Expenses (Eid / Puja / Boishakh) | B49: =Settings!$L$44 -> Religious & Social | C49: =SUMIFS(Transactions!$G$6:$G$2005,Transactions!$B$6:$B$2005,"Expense",Transactions!$C$6:$C$2005,$A49,Transactions!$I$6:$I$2005,C$3,Transactions!$J$6:$J$2005,Settings!$B$5) -> 0 | D49: =SUMIFS(Transactions!$G$6:$G$2005,Transactions!$B$6:$B$2005,"Expense",Transactions!$C$6:$C$2005,$A49,Transactions!$I$6:$I$2005,D$3,Transactions!$J$6:$J$2005,Settings!$B$5) -> 0 | E49: =SUMIFS(Transactions!$G$6:$G$2005,Transactions!$B$6:$B$2005,"Expense",Transactions!$C$6:$C$2005,$A49,Transactions!$I$6:$I$2005,E$3,Transactions!$J$6:$J$2005,Settings!$B$5) -> 9000 | F49: =SUMIFS(Transactions!$G$6:$G$2005,Transactions!$B$6:$B$2005,"Expense",Transactions!$C$6:$C$2005,$A49,Transactions!$I$6:$I$2005,F$3,Transactions!$J$6:$J$2005,Settings!$B$5) -> 3000 | G49: =SUMIFS(Transactions!$G$6:$G$2005,Transactions!$B$6:$B$2005,"Expense",Transactions!$C$6:$C$2005,$A49,Transactions!$I$6:$I$2005,G$3,Transactions!$J$6:$J$2005,Settings!$B$5) -> 6500 | H49: =SUMIFS(Transactions!$G$6:$G$2005,Transactions!$B$6:$B$2005,"Expense",Transactions!$C$6:$C$2005,$A49,Transactions!$I$6:$I$2005,H$3,Transactions!$J$6:$J$2005,Settings!$B$5) -> 0 | I49: =SUMIFS(Transactions!$G$6:$G$2005,Transactions!$B$6:$B$2005,"Expense",Transactions!$C$6:$C$2005,$A49,Transactions!$I$6:$I$2005,I$3,Transactions!$J$6:$J$2005,Settings!$B$5) -> 0 | J49: =SUMIFS(Transactions!$G$6:$G$2005,Transactions!$B$6:$B$2005,"Expense",Transactions!$C$6:$C$2005,$A49,Transactions!$I$6:$I$2005,J$3,Transactions!$J$6:$J$2005,Settings!$B$5) -> 0 | ... N49: =SUMIFS(Transactions!$G$6:$G$2005,Transactions!$B$6:$B$2005,"Expense",Transactions!$C$6:$C$2005,$A49,Transactions!$I$6:$I$2005,N$3,Transactions!$J$6:$J$2005,Settings!$B$5) -> 0 | O49: =SUM(C49:N49) -> 18500 | P49: =Budget!$I$34 -> 12000 | Q49: =P49-O49 -> -6500 | R49: =IF(P49=0,"",O49/P49) -> 1.5416667
A50: =Settings!$K$45 -> Loan EMI | B50: =Settings!$L$45 -> Financial Obligations | C50: =SUMIFS(Transactions!$G$6:$G$2005,Transactions!$B$6:$B$2005,"Expense",Transactions!$C$6:$C$2005,$A50,Transactions!$I$6:$I$2005,C$3,Transactions!$J$6:$J$2005,Settings!$B$5) -> 15300 | D50: =SUMIFS(Transactions!$G$6:$G$2005,Transactions!$B$6:$B$2005,"Expense",Transactions!$C$6:$C$2005,$A50,Transactions!$I$6:$I$2005,D$3,Transactions!$J$6:$J$2005,Settings!$B$5) -> 15300 | E50: =SUMIFS(Transactions!$G$6:$G$2005,Transactions!$B$6:$B$2005,"Expense",Transactions!$C$6:$C$2005,$A50,Transactions!$I$6:$I$2005,E$3,Transactions!$J$6:$J$2005,Settings!$B$5) -> 15300 | F50: =SUMIFS(Transactions!$G$6:$G$2005,Transactions!$B$6:$B$2005,"Expense",Transactions!$C$6:$C$2005,$A50,Transactions!$I$6:$I$2005,F$3,Transactions!$J$6:$J$2005,Settings!$B$5) -> 15300 | G50: =SUMIFS(Transactions!$G$6:$G$2005,Transactions!$B$6:$B$2005,"Expense",Transactions!$C$6:$C$2005,$A50,Transactions!$I$6:$I$2005,G$3,Transactions!$J$6:$J$2005,Settings!$B$5) -> 15300 | H50: =SUMIFS(Transactions!$G$6:$G$2005,Transactions!$B$6:$B$2005,"Expense",Transactions!$C$6:$C$2005,$A50,Transactions!$I$6:$I$2005,H$3,Transactions!$J$6:$J$2005,Settings!$B$5) -> 15300 | I50: =SUMIFS(Transactions!$G$6:$G$2005,Transactions!$B$6:$B$2005,"Expense",Transactions!$C$6:$C$2005,$A50,Transactions!$I$6:$I$2005,I$3,Transactions!$J$6:$J$2005,Settings!$B$5) -> 15300 | J50: =SUMIFS(Transactions!$G$6:$G$2005,Transactions!$B$6:$B$2005,"Expense",Transactions!$C$6:$C$2005,$A50,Transactions!$I$6:$I$2005,J$3,Transactions!$J$6:$J$2005,Settings!$B$5) -> 15300 | ... N50: =SUMIFS(Transactions!$G$6:$G$2005,Transactions!$B$6:$B$2005,"Expense",Transactions!$C$6:$C$2005,$A50,Transactions!$I$6:$I$2005,N$3,Transactions!$J$6:$J$2005,Settings!$B$5) -> 0 | O50: =SUM(C50:N50) -> 153000 | P50: =Budget!$I$35 -> 183600 | Q50: =P50-O50 -> 30600 | R50: =IF(P50=0,"",O50/P50) -> 0.83333333
A51: =Settings!$K$46 -> Credit Card Payment | B51: =Settings!$L$46 -> Financial Obligations | C51: =SUMIFS(Transactions!$G$6:$G$2005,Transactions!$B$6:$B$2005,"Expense",Transactions!$C$6:$C$2005,$A51,Transactions!$I$6:$I$2005,C$3,Transactions!$J$6:$J$2005,Settings!$B$5) -> 2800 | D51: =SUMIFS(Transactions!$G$6:$G$2005,Transactions!$B$6:$B$2005,"Expense",Transactions!$C$6:$C$2005,$A51,Transactions!$I$6:$I$2005,D$3,Transactions!$J$6:$J$2005,Settings!$B$5) -> 2800 | E51: =SUMIFS(Transactions!$G$6:$G$2005,Transactions!$B$6:$B$2005,"Expense",Transactions!$C$6:$C$2005,$A51,Transactions!$I$6:$I$2005,E$3,Transactions!$J$6:$J$2005,Settings!$B$5) -> 2800 | F51: =SUMIFS(Transactions!$G$6:$G$2005,Transactions!$B$6:$B$2005,"Expense",Transactions!$C$6:$C$2005,$A51,Transactions!$I$6:$I$2005,F$3,Transactions!$J$6:$J$2005,Settings!$B$5) -> 2800 | G51: =SUMIFS(Transactions!$G$6:$G$2005,Transactions!$B$6:$B$2005,"Expense",Transactions!$C$6:$C$2005,$A51,Transactions!$I$6:$I$2005,G$3,Transactions!$J$6:$J$2005,Settings!$B$5) -> 2800 | H51: =SUMIFS(Transactions!$G$6:$G$2005,Transactions!$B$6:$B$2005,"Expense",Transactions!$C$6:$C$2005,$A51,Transactions!$I$6:$I$2005,H$3,Transactions!$J$6:$J$2005,Settings!$B$5) -> 2800 | I51: =SUMIFS(Transactions!$G$6:$G$2005,Transactions!$B$6:$B$2005,"Expense",Transactions!$C$6:$C$2005,$A51,Transactions!$I$6:$I$2005,I$3,Transactions!$J$6:$J$2005,Settings!$B$5) -> 2800 | J51: =SUMIFS(Transactions!$G$6:$G$2005,Transactions!$B$6:$B$2005,"Expense",Transactions!$C$6:$C$2005,$A51,Transactions!$I$6:$I$2005,J$3,Transactions!$J$6:$J$2005,Settings!$B$5) -> 2800 | ... N51: =SUMIFS(Transactions!$G$6:$G$2005,Transactions!$B$6:$B$2005,"Expense",Transactions!$C$6:$C$2005,$A51,Transactions!$I$6:$I$2005,N$3,Transactions!$J$6:$J$2005,Settings!$B$5) -> 0 | O51: =SUM(C51:N51) -> 25200 | P51: =Budget!$I$36 -> 33600 | Q51: =P51-O51 -> 8400 | R51: =IF(P51=0,"",O51/P51) -> 0.75
A52: =Settings!$K$47 -> Insurance Premium | B52: =Settings!$L$47 -> Financial Obligations | C52: =SUMIFS(Transactions!$G$6:$G$2005,Transactions!$B$6:$B$2005,"Expense",Transactions!$C$6:$C$2005,$A52,Transactions!$I$6:$I$2005,C$3,Transactions!$J$6:$J$2005,Settings!$B$5) -> 2500 | D52: =SUMIFS(Transactions!$G$6:$G$2005,Transactions!$B$6:$B$2005,"Expense",Transactions!$C$6:$C$2005,$A52,Transactions!$I$6:$I$2005,D$3,Transactions!$J$6:$J$2005,Settings!$B$5) -> 2500 | E52: =SUMIFS(Transactions!$G$6:$G$2005,Transactions!$B$6:$B$2005,"Expense",Transactions!$C$6:$C$2005,$A52,Transactions!$I$6:$I$2005,E$3,Transactions!$J$6:$J$2005,Settings!$B$5) -> 2500 | F52: =SUMIFS(Transactions!$G$6:$G$2005,Transactions!$B$6:$B$2005,"Expense",Transactions!$C$6:$C$2005,$A52,Transactions!$I$6:$I$2005,F$3,Transactions!$J$6:$J$2005,Settings!$B$5) -> 2500 | G52: =SUMIFS(Transactions!$G$6:$G$2005,Transactions!$B$6:$B$2005,"Expense",Transactions!$C$6:$C$2005,$A52,Transactions!$I$6:$I$2005,G$3,Transactions!$J$6:$J$2005,Settings!$B$5) -> 2500 | H52: =SUMIFS(Transactions!$G$6:$G$2005,Transactions!$B$6:$B$2005,"Expense",Transactions!$C$6:$C$2005,$A52,Transactions!$I$6:$I$2005,H$3,Transactions!$J$6:$J$2005,Settings!$B$5) -> 2500 | I52: =SUMIFS(Transactions!$G$6:$G$2005,Transactions!$B$6:$B$2005,"Expense",Transactions!$C$6:$C$2005,$A52,Transactions!$I$6:$I$2005,I$3,Transactions!$J$6:$J$2005,Settings!$B$5) -> 2500 | J52: =SUMIFS(Transactions!$G$6:$G$2005,Transactions!$B$6:$B$2005,"Expense",Transactions!$C$6:$C$2005,$A52,Transactions!$I$6:$I$2005,J$3,Transactions!$J$6:$J$2005,Settings!$B$5) -> 2500 | ... N52: =SUMIFS(Transactions!$G$6:$G$2005,Transactions!$B$6:$B$2005,"Expense",Transactions!$C$6:$C$2005,$A52,Transactions!$I$6:$I$2005,N$3,Transactions!$J$6:$J$2005,Settings!$B$5) -> 0 | O52: =SUM(C52:N52) -> 25000 | P52: =Budget!$I$37 -> 30000 | Q52: =P52-O52 -> 5000 | R52: =IF(P52=0,"",O52/P52) -> 0.83333333
A53: =Settings!$K$48 -> Income Tax & Govt Fees | B53: =Settings!$L$48 -> Financial Obligations | C53: =SUMIFS(Transactions!$G$6:$G$2005,Transactions!$B$6:$B$2005,"Expense",Transactions!$C$6:$C$2005,$A53,Transactions!$I$6:$I$2005,C$3,Transactions!$J$6:$J$2005,Settings!$B$5) -> 0 | D53: =SUMIFS(Transactions!$G$6:$G$2005,Transactions!$B$6:$B$2005,"Expense",Transactions!$C$6:$C$2005,$A53,Transactions!$I$6:$I$2005,D$3,Transactions!$J$6:$J$2005,Settings!$B$5) -> 1200 | E53: =SUMIFS(Transactions!$G$6:$G$2005,Transactions!$B$6:$B$2005,"Expense",Transactions!$C$6:$C$2005,$A53,Transactions!$I$6:$I$2005,E$3,Transactions!$J$6:$J$2005,Settings!$B$5) -> 0 | F53: =SUMIFS(Transactions!$G$6:$G$2005,Transactions!$B$6:$B$2005,"Expense",Transactions!$C$6:$C$2005,$A53,Transactions!$I$6:$I$2005,F$3,Transactions!$J$6:$J$2005,Settings!$B$5) -> 0 | G53: =SUMIFS(Transactions!$G$6:$G$2005,Transactions!$B$6:$B$2005,"Expense",Transactions!$C$6:$C$2005,$A53,Transactions!$I$6:$I$2005,G$3,Transactions!$J$6:$J$2005,Settings!$B$5) -> 0 | H53: =SUMIFS(Transactions!$G$6:$G$2005,Transactions!$B$6:$B$2005,"Expense",Transactions!$C$6:$C$2005,$A53,Transactions!$I$6:$I$2005,H$3,Transactions!$J$6:$J$2005,Settings!$B$5) -> 5000 | I53: =SUMIFS(Transactions!$G$6:$G$2005,Transactions!$B$6:$B$2005,"Expense",Transactions!$C$6:$C$2005,$A53,Transactions!$I$6:$I$2005,I$3,Transactions!$J$6:$J$2005,Settings!$B$5) -> 0 | J53: =SUMIFS(Transactions!$G$6:$G$2005,Transactions!$B$6:$B$2005,"Expense",Transactions!$C$6:$C$2005,$A53,Transactions!$I$6:$I$2005,J$3,Transactions!$J$6:$J$2005,Settings!$B$5) -> 0 | ... N53: =SUMIFS(Transactions!$G$6:$G$2005,Transactions!$B$6:$B$2005,"Expense",Transactions!$C$6:$C$2005,$A53,Transactions!$I$6:$I$2005,N$3,Transactions!$J$6:$J$2005,Settings!$B$5) -> 0 | O53: =SUM(C53:N53) -> 6200 | P53: =Budget!$I$38 -> 6000 | Q53: =P53-O53 -> -200 | R53: =IF(P53=0,"",O53/P53) -> 1.0333333
A54: =Settings!$K$49 -> Bank / MFS Charges | B54: =Settings!$L$49 -> Financial Obligations | C54: =SUMIFS(Transactions!$G$6:$G$2005,Transactions!$B$6:$B$2005,"Expense",Transactions!$C$6:$C$2005,$A54,Transactions!$I$6:$I$2005,C$3,Transactions!$J$6:$J$2005,Settings!$B$5) -> 250 | D54: =SUMIFS(Transactions!$G$6:$G$2005,Transactions!$B$6:$B$2005,"Expense",Transactions!$C$6:$C$2005,$A54,Transactions!$I$6:$I$2005,D$3,Transactions!$J$6:$J$2005,Settings!$B$5) -> 250 | E54: =SUMIFS(Transactions!$G$6:$G$2005,Transactions!$B$6:$B$2005,"Expense",Transactions!$C$6:$C$2005,$A54,Transactions!$I$6:$I$2005,E$3,Transactions!$J$6:$J$2005,Settings!$B$5) -> 250 | F54: =SUMIFS(Transactions!$G$6:$G$2005,Transactions!$B$6:$B$2005,"Expense",Transactions!$C$6:$C$2005,$A54,Transactions!$I$6:$I$2005,F$3,Transactions!$J$6:$J$2005,Settings!$B$5) -> 250 | G54: =SUMIFS(Transactions!$G$6:$G$2005,Transactions!$B$6:$B$2005,"Expense",Transactions!$C$6:$C$2005,$A54,Transactions!$I$6:$I$2005,G$3,Transactions!$J$6:$J$2005,Settings!$B$5) -> 250 | H54: =SUMIFS(Transactions!$G$6:$G$2005,Transactions!$B$6:$B$2005,"Expense",Transactions!$C$6:$C$2005,$A54,Transactions!$I$6:$I$2005,H$3,Transactions!$J$6:$J$2005,Settings!$B$5) -> 250 | I54: =SUMIFS(Transactions!$G$6:$G$2005,Transactions!$B$6:$B$2005,"Expense",Transactions!$C$6:$C$2005,$A54,Transactions!$I$6:$I$2005,I$3,Transactions!$J$6:$J$2005,Settings!$B$5) -> 250 | J54: =SUMIFS(Transactions!$G$6:$G$2005,Transactions!$B$6:$B$2005,"Expense",Transactions!$C$6:$C$2005,$A54,Transactions!$I$6:$I$2005,J$3,Transactions!$J$6:$J$2005,Settings!$B$5) -> 250 | ... N54: =SUMIFS(Transactions!$G$6:$G$2005,Transactions!$B$6:$B$2005,"Expense",Transactions!$C$6:$C$2005,$A54,Transactions!$I$6:$I$2005,N$3,Transactions!$J$6:$J$2005,Settings!$B$5) -> 0 | O54: =SUM(C54:N54) -> 2250 | P54: =Budget!$I$39 -> 3000 | Q54: =P54-O54 -> 750 | R54: =IF(P54=0,"",O54/P54) -> 0.75
A55: =Settings!$K$50 -> DPS Deposit | B55: =Settings!$L$50 -> Savings & Investments | C55: =SUMIFS(Transactions!$G$6:$G$2005,Transactions!$B$6:$B$2005,"Expense",Transactions!$C$6:$C$2005,$A55,Transactions!$I$6:$I$2005,C$3,Transactions!$J$6:$J$2005,Settings!$B$5) -> 5000 | D55: =SUMIFS(Transactions!$G$6:$G$2005,Transactions!$B$6:$B$2005,"Expense",Transactions!$C$6:$C$2005,$A55,Transactions!$I$6:$I$2005,D$3,Transactions!$J$6:$J$2005,Settings!$B$5) -> 5000 | E55: =SUMIFS(Transactions!$G$6:$G$2005,Transactions!$B$6:$B$2005,"Expense",Transactions!$C$6:$C$2005,$A55,Transactions!$I$6:$I$2005,E$3,Transactions!$J$6:$J$2005,Settings!$B$5) -> 5000 | F55: =SUMIFS(Transactions!$G$6:$G$2005,Transactions!$B$6:$B$2005,"Expense",Transactions!$C$6:$C$2005,$A55,Transactions!$I$6:$I$2005,F$3,Transactions!$J$6:$J$2005,Settings!$B$5) -> 5000 | G55: =SUMIFS(Transactions!$G$6:$G$2005,Transactions!$B$6:$B$2005,"Expense",Transactions!$C$6:$C$2005,$A55,Transactions!$I$6:$I$2005,G$3,Transactions!$J$6:$J$2005,Settings!$B$5) -> 5000 | H55: =SUMIFS(Transactions!$G$6:$G$2005,Transactions!$B$6:$B$2005,"Expense",Transactions!$C$6:$C$2005,$A55,Transactions!$I$6:$I$2005,H$3,Transactions!$J$6:$J$2005,Settings!$B$5) -> 5000 | I55: =SUMIFS(Transactions!$G$6:$G$2005,Transactions!$B$6:$B$2005,"Expense",Transactions!$C$6:$C$2005,$A55,Transactions!$I$6:$I$2005,I$3,Transactions!$J$6:$J$2005,Settings!$B$5) -> 5000 | J55: =SUMIFS(Transactions!$G$6:$G$2005,Transactions!$B$6:$B$2005,"Expense",Transactions!$C$6:$C$2005,$A55,Transactions!$I$6:$I$2005,J$3,Transactions!$J$6:$J$2005,Settings!$B$5) -> 5000 | ... N55: =SUMIFS(Transactions!$G$6:$G$2005,Transactions!$B$6:$B$2005,"Expense",Transactions!$C$6:$C$2005,$A55,Transactions!$I$6:$I$2005,N$3,Transactions!$J$6:$J$2005,Settings!$B$5) -> 0 | O55: =SUM(C55:N55) -> 50000 | P55: =Budget!$I$40 -> 60000 | Q55: =P55-O55 -> 10000 | R55: =IF(P55=0,"",O55/P55) -> 0.83333333
A56: =Settings!$K$51 -> FDR / Sanchayapatra Purchase | B56: =Settings!$L$51 -> Savings & Investments | C56: =SUMIFS(Transactions!$G$6:$G$2005,Transactions!$B$6:$B$2005,"Expense",Transactions!$C$6:$C$2005,$A56,Transactions!$I$6:$I$2005,C$3,Transactions!$J$6:$J$2005,Settings!$B$5) -> 0 | D56: =SUMIFS(Transactions!$G$6:$G$2005,Transactions!$B$6:$B$2005,"Expense",Transactions!$C$6:$C$2005,$A56,Transactions!$I$6:$I$2005,D$3,Transactions!$J$6:$J$2005,Settings!$B$5) -> 0 | E56: =SUMIFS(Transactions!$G$6:$G$2005,Transactions!$B$6:$B$2005,"Expense",Transactions!$C$6:$C$2005,$A56,Transactions!$I$6:$I$2005,E$3,Transactions!$J$6:$J$2005,Settings!$B$5) -> 50000 | F56: =SUMIFS(Transactions!$G$6:$G$2005,Transactions!$B$6:$B$2005,"Expense",Transactions!$C$6:$C$2005,$A56,Transactions!$I$6:$I$2005,F$3,Transactions!$J$6:$J$2005,Settings!$B$5) -> 0 | G56: =SUMIFS(Transactions!$G$6:$G$2005,Transactions!$B$6:$B$2005,"Expense",Transactions!$C$6:$C$2005,$A56,Transactions!$I$6:$I$2005,G$3,Transactions!$J$6:$J$2005,Settings!$B$5) -> 0 | H56: =SUMIFS(Transactions!$G$6:$G$2005,Transactions!$B$6:$B$2005,"Expense",Transactions!$C$6:$C$2005,$A56,Transactions!$I$6:$I$2005,H$3,Transactions!$J$6:$J$2005,Settings!$B$5) -> 0 | I56: =SUMIFS(Transactions!$G$6:$G$2005,Transactions!$B$6:$B$2005,"Expense",Transactions!$C$6:$C$2005,$A56,Transactions!$I$6:$I$2005,I$3,Transactions!$J$6:$J$2005,Settings!$B$5) -> 0 | J56: =SUMIFS(Transactions!$G$6:$G$2005,Transactions!$B$6:$B$2005,"Expense",Transactions!$C$6:$C$2005,$A56,Transactions!$I$6:$I$2005,J$3,Transactions!$J$6:$J$2005,Settings!$B$5) -> 0 | ... N56: =SUMIFS(Transactions!$G$6:$G$2005,Transactions!$B$6:$B$2005,"Expense",Transactions!$C$6:$C$2005,$A56,Transactions!$I$6:$I$2005,N$3,Transactions!$J$6:$J$2005,Settings!$B$5) -> 0 | O56: =SUM(C56:N56) -> 50000 | P56: =Budget!$I$41 -> 0 | Q56: =P56-O56 -> -50000 | R56: =IF(P56=0,"",O56/P56)
A57: =Settings!$K$52 -> Stocks & Mutual Funds (DSE) | B57: =Settings!$L$52 -> Savings & Investments | C57: =SUMIFS(Transactions!$G$6:$G$2005,Transactions!$B$6:$B$2005,"Expense",Transactions!$C$6:$C$2005,$A57,Transactions!$I$6:$I$2005,C$3,Transactions!$J$6:$J$2005,Settings!$B$5) -> 5000 | D57: =SUMIFS(Transactions!$G$6:$G$2005,Transactions!$B$6:$B$2005,"Expense",Transactions!$C$6:$C$2005,$A57,Transactions!$I$6:$I$2005,D$3,Transactions!$J$6:$J$2005,Settings!$B$5) -> 0 | E57: =SUMIFS(Transactions!$G$6:$G$2005,Transactions!$B$6:$B$2005,"Expense",Transactions!$C$6:$C$2005,$A57,Transactions!$I$6:$I$2005,E$3,Transactions!$J$6:$J$2005,Settings!$B$5) -> 0 | F57: =SUMIFS(Transactions!$G$6:$G$2005,Transactions!$B$6:$B$2005,"Expense",Transactions!$C$6:$C$2005,$A57,Transactions!$I$6:$I$2005,F$3,Transactions!$J$6:$J$2005,Settings!$B$5) -> 5000 | G57: =SUMIFS(Transactions!$G$6:$G$2005,Transactions!$B$6:$B$2005,"Expense",Transactions!$C$6:$C$2005,$A57,Transactions!$I$6:$I$2005,G$3,Transactions!$J$6:$J$2005,Settings!$B$5) -> 0 | H57: =SUMIFS(Transactions!$G$6:$G$2005,Transactions!$B$6:$B$2005,"Expense",Transactions!$C$6:$C$2005,$A57,Transactions!$I$6:$I$2005,H$3,Transactions!$J$6:$J$2005,Settings!$B$5) -> 0 | I57: =SUMIFS(Transactions!$G$6:$G$2005,Transactions!$B$6:$B$2005,"Expense",Transactions!$C$6:$C$2005,$A57,Transactions!$I$6:$I$2005,I$3,Transactions!$J$6:$J$2005,Settings!$B$5) -> 5000 | J57: =SUMIFS(Transactions!$G$6:$G$2005,Transactions!$B$6:$B$2005,"Expense",Transactions!$C$6:$C$2005,$A57,Transactions!$I$6:$I$2005,J$3,Transactions!$J$6:$J$2005,Settings!$B$5) -> 0 | ... N57: =SUMIFS(Transactions!$G$6:$G$2005,Transactions!$B$6:$B$2005,"Expense",Transactions!$C$6:$C$2005,$A57,Transactions!$I$6:$I$2005,N$3,Transactions!$J$6:$J$2005,Settings!$B$5) -> 0 | O57: =SUM(C57:N57) -> 15000 | P57: =Budget!$I$42 -> 18000 | Q57: =P57-O57 -> 3000 | R57: =IF(P57=0,"",O57/P57) -> 0.83333333
A58: =Settings!$K$53 -> Gold Purchase | B58: =Settings!$L$53 -> Savings & Investments | C58: =SUMIFS(Transactions!$G$6:$G$2005,Transactions!$B$6:$B$2005,"Expense",Transactions!$C$6:$C$2005,$A58,Transactions!$I$6:$I$2005,C$3,Transactions!$J$6:$J$2005,Settings!$B$5) -> 0 | D58: =SUMIFS(Transactions!$G$6:$G$2005,Transactions!$B$6:$B$2005,"Expense",Transactions!$C$6:$C$2005,$A58,Transactions!$I$6:$I$2005,D$3,Transactions!$J$6:$J$2005,Settings!$B$5) -> 0 | E58: =SUMIFS(Transactions!$G$6:$G$2005,Transactions!$B$6:$B$2005,"Expense",Transactions!$C$6:$C$2005,$A58,Transactions!$I$6:$I$2005,E$3,Transactions!$J$6:$J$2005,Settings!$B$5) -> 0 | F58: =SUMIFS(Transactions!$G$6:$G$2005,Transactions!$B$6:$B$2005,"Expense",Transactions!$C$6:$C$2005,$A58,Transactions!$I$6:$I$2005,F$3,Transactions!$J$6:$J$2005,Settings!$B$5) -> 0 | G58: =SUMIFS(Transactions!$G$6:$G$2005,Transactions!$B$6:$B$2005,"Expense",Transactions!$C$6:$C$2005,$A58,Transactions!$I$6:$I$2005,G$3,Transactions!$J$6:$J$2005,Settings!$B$5) -> 0 | H58: =SUMIFS(Transactions!$G$6:$G$2005,Transactions!$B$6:$B$2005,"Expense",Transactions!$C$6:$C$2005,$A58,Transactions!$I$6:$I$2005,H$3,Transactions!$J$6:$J$2005,Settings!$B$5) -> 0 | I58: =SUMIFS(Transactions!$G$6:$G$2005,Transactions!$B$6:$B$2005,"Expense",Transactions!$C$6:$C$2005,$A58,Transactions!$I$6:$I$2005,I$3,Transactions!$J$6:$J$2005,Settings!$B$5) -> 0 | J58: =SUMIFS(Transactions!$G$6:$G$2005,Transactions!$B$6:$B$2005,"Expense",Transactions!$C$6:$C$2005,$A58,Transactions!$I$6:$I$2005,J$3,Transactions!$J$6:$J$2005,Settings!$B$5) -> 0 | ... N58: =SUMIFS(Transactions!$G$6:$G$2005,Transactions!$B$6:$B$2005,"Expense",Transactions!$C$6:$C$2005,$A58,Transactions!$I$6:$I$2005,N$3,Transactions!$J$6:$J$2005,Settings!$B$5) -> 0 | O58: =SUM(C58:N58) -> 0 | P58: =Budget!$I$43 -> 0 | Q58: =P58-O58 -> 0 | R58: =IF(P58=0,"",O58/P58)
A59: =Settings!$K$54 -> Emergency Fund Deposit | B59: =Settings!$L$54 -> Savings & Investments | C59: =SUMIFS(Transactions!$G$6:$G$2005,Transactions!$B$6:$B$2005,"Expense",Transactions!$C$6:$C$2005,$A59,Transactions!$I$6:$I$2005,C$3,Transactions!$J$6:$J$2005,Settings!$B$5) -> 3000 | D59: =SUMIFS(Transactions!$G$6:$G$2005,Transactions!$B$6:$B$2005,"Expense",Transactions!$C$6:$C$2005,$A59,Transactions!$I$6:$I$2005,D$3,Transactions!$J$6:$J$2005,Settings!$B$5) -> 3000 | E59: =SUMIFS(Transactions!$G$6:$G$2005,Transactions!$B$6:$B$2005,"Expense",Transactions!$C$6:$C$2005,$A59,Transactions!$I$6:$I$2005,E$3,Transactions!$J$6:$J$2005,Settings!$B$5) -> 3000 | F59: =SUMIFS(Transactions!$G$6:$G$2005,Transactions!$B$6:$B$2005,"Expense",Transactions!$C$6:$C$2005,$A59,Transactions!$I$6:$I$2005,F$3,Transactions!$J$6:$J$2005,Settings!$B$5) -> 3000 | G59: =SUMIFS(Transactions!$G$6:$G$2005,Transactions!$B$6:$B$2005,"Expense",Transactions!$C$6:$C$2005,$A59,Transactions!$I$6:$I$2005,G$3,Transactions!$J$6:$J$2005,Settings!$B$5) -> 3000 | H59: =SUMIFS(Transactions!$G$6:$G$2005,Transactions!$B$6:$B$2005,"Expense",Transactions!$C$6:$C$2005,$A59,Transactions!$I$6:$I$2005,H$3,Transactions!$J$6:$J$2005,Settings!$B$5) -> 3000 | I59: =SUMIFS(Transactions!$G$6:$G$2005,Transactions!$B$6:$B$2005,"Expense",Transactions!$C$6:$C$2005,$A59,Transactions!$I$6:$I$2005,I$3,Transactions!$J$6:$J$2005,Settings!$B$5) -> 3000 | J59: =SUMIFS(Transactions!$G$6:$G$2005,Transactions!$B$6:$B$2005,"Expense",Transactions!$C$6:$C$2005,$A59,Transactions!$I$6:$I$2005,J$3,Transactions!$J$6:$J$2005,Settings!$B$5) -> 3000 | ... N59: =SUMIFS(Transactions!$G$6:$G$2005,Transactions!$B$6:$B$2005,"Expense",Transactions!$C$6:$C$2005,$A59,Transactions!$I$6:$I$2005,N$3,Transactions!$J$6:$J$2005,Settings!$B$5) -> 0 | O59: =SUM(C59:N59) -> 27000 | P59: =Budget!$I$44 -> 36000 | Q59: =P59-O59 -> 9000 | R59: =IF(P59=0,"",O59/P59) -> 0.75
A60: =Settings!$K$55 -> Provident / Pension Contribution | B60: =Settings!$L$55 -> Savings & Investments | C60: =SUMIFS(Transactions!$G$6:$G$2005,Transactions!$B$6:$B$2005,"Expense",Transactions!$C$6:$C$2005,$A60,Transactions!$I$6:$I$2005,C$3,Transactions!$J$6:$J$2005,Settings!$B$5) -> 0 | D60: =SUMIFS(Transactions!$G$6:$G$2005,Transactions!$B$6:$B$2005,"Expense",Transactions!$C$6:$C$2005,$A60,Transactions!$I$6:$I$2005,D$3,Transactions!$J$6:$J$2005,Settings!$B$5) -> 0 | E60: =SUMIFS(Transactions!$G$6:$G$2005,Transactions!$B$6:$B$2005,"Expense",Transactions!$C$6:$C$2005,$A60,Transactions!$I$6:$I$2005,E$3,Transactions!$J$6:$J$2005,Settings!$B$5) -> 0 | F60: =SUMIFS(Transactions!$G$6:$G$2005,Transactions!$B$6:$B$2005,"Expense",Transactions!$C$6:$C$2005,$A60,Transactions!$I$6:$I$2005,F$3,Transactions!$J$6:$J$2005,Settings!$B$5) -> 0 | G60: =SUMIFS(Transactions!$G$6:$G$2005,Transactions!$B$6:$B$2005,"Expense",Transactions!$C$6:$C$2005,$A60,Transactions!$I$6:$I$2005,G$3,Transactions!$J$6:$J$2005,Settings!$B$5) -> 0 | H60: =SUMIFS(Transactions!$G$6:$G$2005,Transactions!$B$6:$B$2005,"Expense",Transactions!$C$6:$C$2005,$A60,Transactions!$I$6:$I$2005,H$3,Transactions!$J$6:$J$2005,Settings!$B$5) -> 0 | I60: =SUMIFS(Transactions!$G$6:$G$2005,Transactions!$B$6:$B$2005,"Expense",Transactions!$C$6:$C$2005,$A60,Transactions!$I$6:$I$2005,I$3,Transactions!$J$6:$J$2005,Settings!$B$5) -> 0 | J60: =SUMIFS(Transactions!$G$6:$G$2005,Transactions!$B$6:$B$2005,"Expense",Transactions!$C$6:$C$2005,$A60,Transactions!$I$6:$I$2005,J$3,Transactions!$J$6:$J$2005,Settings!$B$5) -> 0 | ... N60: =SUMIFS(Transactions!$G$6:$G$2005,Transactions!$B$6:$B$2005,"Expense",Transactions!$C$6:$C$2005,$A60,Transactions!$I$6:$I$2005,N$3,Transactions!$J$6:$J$2005,Settings!$B$5) -> 0 | O60: =SUM(C60:N60) -> 0 | P60: =Budget!$I$45 -> 0 | Q60: =P60-O60 -> 0 | R60: =IF(P60=0,"",O60/P60)
A61: =Settings!$K$56 -> Miscellaneous | B61: =Settings!$L$56 -> Other | C61: =SUMIFS(Transactions!$G$6:$G$2005,Transactions!$B$6:$B$2005,"Expense",Transactions!$C$6:$C$2005,$A61,Transactions!$I$6:$I$2005,C$3,Transactions!$J$6:$J$2005,Settings!$B$5) -> 700 | D61: =SUMIFS(Transactions!$G$6:$G$2005,Transactions!$B$6:$B$2005,"Expense",Transactions!$C$6:$C$2005,$A61,Transactions!$I$6:$I$2005,D$3,Transactions!$J$6:$J$2005,Settings!$B$5) -> 0 | E61: =SUMIFS(Transactions!$G$6:$G$2005,Transactions!$B$6:$B$2005,"Expense",Transactions!$C$6:$C$2005,$A61,Transactions!$I$6:$I$2005,E$3,Transactions!$J$6:$J$2005,Settings!$B$5) -> 0 | F61: =SUMIFS(Transactions!$G$6:$G$2005,Transactions!$B$6:$B$2005,"Expense",Transactions!$C$6:$C$2005,$A61,Transactions!$I$6:$I$2005,F$3,Transactions!$J$6:$J$2005,Settings!$B$5) -> 0 | G61: =SUMIFS(Transactions!$G$6:$G$2005,Transactions!$B$6:$B$2005,"Expense",Transactions!$C$6:$C$2005,$A61,Transactions!$I$6:$I$2005,G$3,Transactions!$J$6:$J$2005,Settings!$B$5) -> 0 | H61: =SUMIFS(Transactions!$G$6:$G$2005,Transactions!$B$6:$B$2005,"Expense",Transactions!$C$6:$C$2005,$A61,Transactions!$I$6:$I$2005,H$3,Transactions!$J$6:$J$2005,Settings!$B$5) -> 0 | I61: =SUMIFS(Transactions!$G$6:$G$2005,Transactions!$B$6:$B$2005,"Expense",Transactions!$C$6:$C$2005,$A61,Transactions!$I$6:$I$2005,I$3,Transactions!$J$6:$J$2005,Settings!$B$5) -> 900 | J61: =SUMIFS(Transactions!$G$6:$G$2005,Transactions!$B$6:$B$2005,"Expense",Transactions!$C$6:$C$2005,$A61,Transactions!$I$6:$I$2005,J$3,Transactions!$J$6:$J$2005,Settings!$B$5) -> 0 | ... N61: =SUMIFS(Transactions!$G$6:$G$2005,Transactions!$B$6:$B$2005,"Expense",Transactions!$C$6:$C$2005,$A61,Transactions!$I$6:$I$2005,N$3,Transactions!$J$6:$J$2005,Settings!$B$5) -> 0 | O61: =SUM(C61:N61) -> 1600 | P61: =Budget!$I$46 -> 12000 | Q61: =P61-O61 -> 10400 | R61: =IF(P61=0,"",O61/P61) -> 0.13333333
A62: TOTAL EXPENSES (all outflows) | C62: =SUM(C21:C61) -> 92140 | D62: =SUM(D21:D61) -> 102240 | E62: =SUM(E21:E61) -> 193450 | F62: =SUM(F21:F61) -> 101570 | G62: =SUM(G21:G61) -> 121680 | H62: =SUM(H21:H61) -> 96390 | I62: =SUM(I21:I61) -> 94740 | J62: =SUM(J21:J61) -> 93320 | ... P62: =SUM(P21:P61) -> 1274760 | Q62: =P62-O62 -> 199810 | R62: =IF(P62=0,"",O62/P62) -> 0.84325677
A63: of which: Savings & Investments outflow | C63: =SUMIF($B$21:$B$61,"Savings & Investments",C21:C61) -> 13000 | D63: =SUMIF($B$21:$B$61,"Savings & Investments",D21:D61) -> 8000 | E63: =SUMIF($B$21:$B$61,"Savings & Investments",E21:E61) -> 58000 | F63: =SUMIF($B$21:$B$61,"Savings & Investments",F21:F61) -> 13000 | G63: =SUMIF($B$21:$B$61,"Savings & Investments",G21:G61) -> 8000 | H63: =SUMIF($B$21:$B$61,"Savings & Investments",H21:H61) -> 8000 | I63: =SUMIF($B$21:$B$61,"Savings & Investments",I21:I61) -> 13000 | J63: =SUMIF($B$21:$B$61,"Savings & Investments",J21:J61) -> 8000 | ... O63: =SUMIF($B$21:$B$61,"Savings & Investments",O21:O61) -> 142000
A64: SPENDING (excl. savings & investments) | C64: =C62-C63 -> 79140 | D64: =D62-D63 -> 94240 | E64: =E62-E63 -> 135450 | F64: =F62-F63 -> 88570 | G64: =G62-G63 -> 113680 | H64: =H62-H63 -> 88390 | I64: =I62-I63 -> 81740 | J64: =J62-J63 -> 85320 | ... O64: =O62-O63 -> 932950
A65: NET SAVINGS (Income - Spending) | C65: =C18-C64 -> 43636 | D65: =D18-D64 -> 34090 | E65: =E18-E64 -> 54750 | F65: =F18-F64 -> 48686 | G65: =G18-G64 -> 73320 | H65: =H18-H64 -> 42930 | I65: =I18-I64 -> 41036 | J65: =J18-J64 -> 42520 | ... O65: =O18-O64 -> 468924
A66: SAVINGS RATE | C66: =IF(C18=0,0,C65/C18) -> 0.35541148 | D66: =IF(D18=0,0,D65/D18) -> 0.26564326 | E66: =IF(E18=0,0,E65/E18) -> 0.28785489 | F66: =IF(F18=0,0,F65/F18) -> 0.35470945 | G66: =IF(G18=0,0,G65/G18) -> 0.39208556 | H66: =IF(H18=0,0,H65/H18) -> 0.32691136 | I66: =IF(I18=0,0,I65/I18) -> 0.3342347 | J66: =IF(J18=0,0,J65/J18) -> 0.33260325 | ... O66: =IF(O18=0,0,O65/O18) -> 0.33449796

Sheet Monthly Summary
A1: MONTHLY SUMMARY | Cash-flow & Savings Rate
A2: Spending excludes money moved into savings/investments (DPS, FDR, shares, gold, emergency fund). Savings = Income - Spending.
A4: Month | B4: Income | C4: Total Outflow | D4: Savings & Investments | E4: Spending | F4: Net Savings | G4: Savings Rate | H4: Cumulative Savings | I4: Unallocated Cash | J4: Savings Target | K4: Target Gap | L4: Target Rate
A5: =Settings!$E$4 -> Jan | B5: ='Annual Matrix'!C18 -> 122776 | C5: ='Annual Matrix'!C62 -> 92140 | D5: ='Annual Matrix'!C63 -> 13000 | E5: =C5-D5 -> 79140 | F5: =B5-E5 -> 43636 | G5: =IF(B5=0,0,F5/B5) -> 0.35541148 | H5: =SUM($F$5:F5) -> 43636 | I5: =B5-C5 -> 30636 | J5: =B5*Settings!$B$7 -> 24555.2 | K5: =F5-J5 -> 19080.8 | L5: =Settings!$B$7 -> 0.2
A6: =Settings!$E$5 -> Feb | B6: ='Annual Matrix'!D18 -> 128330 | C6: ='Annual Matrix'!D62 -> 102240 | D6: ='Annual Matrix'!D63 -> 8000 | E6: =C6-D6 -> 94240 | F6: =B6-E6 -> 34090 | G6: =IF(B6=0,0,F6/B6) -> 0.26564326 | H6: =SUM($F$5:F6) -> 77726 | I6: =B6-C6 -> 26090 | J6: =B6*Settings!$B$7 -> 25666 | K6: =F6-J6 -> 8424 | L6: =Settings!$B$7 -> 0.2
A7: =Settings!$E$6 -> Mar | B7: ='Annual Matrix'!E18 -> 190200 | C7: ='Annual Matrix'!E62 -> 193450 | D7: ='Annual Matrix'!E63 -> 58000 | E7: =C7-D7 -> 135450 | F7: =B7-E7 -> 54750 | G7: =IF(B7=0,0,F7/B7) -> 0.28785489 | H7: =SUM($F$5:F7) -> 132476 | I7: =B7-C7 -> -3250 | J7: =B7*Settings!$B$7 -> 38040 | K7: =F7-J7 -> 16710 | L7: =Settings!$B$7 -> 0.2
A8: =Settings!$E$7 -> Apr | B8: ='Annual Matrix'!F18 -> 137256 | C8: ='Annual Matrix'!F62 -> 101570 | D8: ='Annual Matrix'!F63 -> 13000 | E8: =C8-D8 -> 88570 | F8: =B8-E8 -> 48686 | G8: =IF(B8=0,0,F8/B8) -> 0.35470945 | H8: =SUM($F$5:F8) -> 181162 | I8: =B8-C8 -> 35686 | J8: =B8*Settings!$B$7 -> 27451.2 | K8: =F8-J8 -> 21234.8 | L8: =Settings!$B$7 -> 0.2
A9: =Settings!$E$8 -> May | B9: ='Annual Matrix'!G18 -> 187000 | C9: ='Annual Matrix'!G62 -> 121680 | D9: ='Annual Matrix'!G63 -> 8000 | E9: =C9-D9 -> 113680 | F9: =B9-E9 -> 73320 | G9: =IF(B9=0,0,F9/B9) -> 0.39208556 | H9: =SUM($F$5:F9) -> 254482 | I9: =B9-C9 -> 65320 | J9: =B9*Settings!$B$7 -> 37400 | K9: =F9-J9 -> 35920 | L9: =Settings!$B$7 -> 0.2
A10: =Settings!$E$9 -> Jun | B10: ='Annual Matrix'!H18 -> 131320 | C10: ='Annual Matrix'!H62 -> 96390 | D10: ='Annual Matrix'!H63 -> 8000 | E10: =C10-D10 -> 88390 | F10: =B10-E10 -> 42930 | G10: =IF(B10=0,0,F10/B10) -> 0.32691136 | H10: =SUM($F$5:F10) -> 297412 | I10: =B10-C10 -> 34930 | J10: =B10*Settings!$B$7 -> 26264 | K10: =F10-J10 -> 16666 | L10: =Settings!$B$7 -> 0.2
A11: =Settings!$E$10 -> Jul | B11: ='Annual Matrix'!I18 -> 122776 | C11: ='Annual Matrix'!I62 -> 94740 | D11: ='Annual Matrix'!I63 -> 13000 | E11: =C11-D11 -> 81740 | F11: =B11-E11 -> 41036 | G11: =IF(B11=0,0,F11/B11) -> 0.3342347 | H11: =SUM($F$5:F11) -> 338448 | I11: =B11-C11 -> 28036 | J11: =B11*Settings!$B$7 -> 24555.2 | K11: =F11-J11 -> 16480.8 | L11: =Settings!$B$7 -> 0.2
A12: =Settings!$E$11 -> Aug | B12: ='Annual Matrix'!J18 -> 127840 | C12: ='Annual Matrix'!J62 -> 93320 | D12: ='Annual Matrix'!J63 -> 8000 | E12: =C12-D12 -> 85320 | F12: =B12-E12 -> 42520 | G12: =IF(B12=0,0,F12/B12) -> 0.33260325 | H12: =SUM($F$5:F12) -> 380968 | I12: =B12-C12 -> 34520 | J12: =B12*Settings!$B$7 -> 25568 | K12: =F12-J12 -> 16952 | L12: =Settings!$B$7 -> 0.2
A13: =Settings!$E$12 -> Sep | B13: ='Annual Matrix'!K18 -> 118200 | C13: ='Annual Matrix'!K62 -> 100020 | D13: ='Annual Matrix'!K63 -> 8000 | E13: =C13-D13 -> 92020 | F13: =B13-E13 -> 26180 | G13: =IF(B13=0,0,F13/B13) -> 0.221489 | H13: =SUM($F$5:F13) -> 407148 | I13: =B13-C13 -> 18180 | J13: =B13*Settings!$B$7 -> 23640 | K13: =F13-J13 -> 2540 | L13: =Settings!$B$7 -> 0.2
A14: =Settings!$E$13 -> Oct | B14: ='Annual Matrix'!L18 -> 136176 | C14: ='Annual Matrix'!L62 -> 79400 | D14: ='Annual Matrix'!L63 -> 5000 | E14: =C14-D14 -> 74400 | F14: =B14-E14 -> 61776 | G14: =IF(B14=0,0,F14/B14) -> 0.45364822 | H14: =SUM($F$5:F14) -> 468924 | I14: =B14-C14 -> 56776 | J14: =B14*Settings!$B$7 -> 27235.2 | K14: =F14-J14 -> 34540.8 | L14: =Settings!$B$7 -> 0.2
A15: =Settings!$E$14 -> Nov | B15: ='Annual Matrix'!M18 -> 0 | C15: ='Annual Matrix'!M62 -> 0 | D15: ='Annual Matrix'!M63 -> 0 | E15: =C15-D15 -> 0 | F15: =B15-E15 -> 0 | G15: =IF(B15=0,0,F15/B15) -> 0 | H15: =SUM($F$5:F15) -> 468924 | I15: =B15-C15 -> 0 | J15: =B15*Settings!$B$7 -> 0 | K15: =F15-J15 -> 0 | L15: =Settings!$B$7 -> 0.2
A16: =Settings!$E$15 -> Dec | B16: ='Annual Matrix'!N18 -> 0 | C16: ='Annual Matrix'!N62 -> 0 | D16: ='Annual Matrix'!N63 -> 0 | E16: =C16-D16 -> 0 | F16: =B16-E16 -> 0 | G16: =IF(B16=0,0,F16/B16) -> 0 | H16: =SUM($F$5:F16) -> 468924 | I16: =B16-C16 -> 0 | J16: =B16*Settings!$B$7 -> 0 | K16: =F16-J16 -> 0 | L16: =Settings!$B$7 -> 0.2
A17: YEAR TOTAL | B17: =SUM(B5:B16) -> 1401874 | C17: =SUM(C5:C16) -> 1074950 | D17: =SUM(D5:D16) -> 142000 | E17: =SUM(E5:E16) -> 932950 | F17: =SUM(F5:F16) -> 468924 | G17: =IF(B17=0,0,F17/B17) -> 0.33449796 | H17: =H16 -> 468924 | I17: =SUM(I5:I16) -> 326924 | J17: =SUM(J5:J16) -> 280374.8 | K17: =SUM(K5:K16) -> 188549.2 | L17: =Settings!$B$7 -> 0.2
A19: Average / month* | B19: =IFERROR(B17/COUNTIF($B$5:$B$16,">0"),0) -> 140187.4 | C19: =IFERROR(C17/COUNTIF($B$5:$B$16,">0"),0) -> 107495 | D19: =IFERROR(D17/COUNTIF($B$5:$B$16,">0"),0) -> 14200 | E19: =IFERROR(E17/COUNTIF($B$5:$B$16,">0"),0) -> 93295 | F19: =IFERROR(F17/COUNTIF($B$5:$B$16,">0"),0) -> 46892.4 | G19: =IF(B19=0,0,F19/B19) -> 0.33449796 | I19: =IFERROR(I17/COUNTIF($B$5:$B$16,">0"),0) -> 32692.4 | J19: =IFERROR(J17/COUNTIF($B$5:$B$16,">0"),0) -> 28037.48
A20: * Average over months that have income recorded.

Sheet Savings Goals
A1: SAVINGS GOALS | লক্ষ্য
A2: Set a target, a date and what you can save each month. The sheet shows the required monthly saving (with expected returns) and whether you are on track. SAMPLE goals shown.
A5: Goal | B5: Priority | C5: Target Amount (BDT) | D5: Saved So Far (BDT) | E5: Target Date | F5: Expected Annual Return | G5: Planned Monthly Saving (BDT) | H5: Remaining (BDT) | I5: Progress | J5: Months Left | K5: Required Monthly Saving (BDT) | L5: Projected Value at Target Date | M5: Surplus / (Shortfall) | N5: Status
A6: Emergency Fund (months of spending) | B6: High | C6: =ROUND(Settings!$B$8*'Monthly Summary'!$E$19,-3) -> 560000 | D6: ='Net Worth'!$C$26 -> 267000 | E6: 46752 | F6: 0.06 | G6: 10000 | H6: =IF(C6="","",MAX(0,C6-D6)) -> 293000 | I6: =IF(C6="","",IF(C6=0,0,MIN(1,D6/C6))) -> 0.47678571 | J6: =IF(E6="","",MAX(0,(YEAR(E6)-YEAR(TODAY()))*12+MONTH(E6)-MONTH(TODAY()))) -> 14 | K6: =IF(OR(C6="",E6=""),"",IF(H6=0,0,IF(J6=0,H6,IF(F6=0,H6/J6,MAX(0,-PMT(F6/12,J6,-D6,C6)))))) -> 18921.873 | L6: =IF(OR(C6="",E6=""),"",FV(F6/12,J6,-G6,-D6)) -> 430952.01 | M6: =IF(L6="","",L6-C6) -> -129047.99 | N6: =IF(C6="","",IF(D6>=C6,"Achieved",IF(J6=0,"Overdue",IF(L6>=C6,"On Track",IF(L6>=0.8*C6,"Slightly Behind","Behind"))))) -> Behind
A7: Hajj Fund | B7: High | C7: 1200000 | D7: 150000 | E7: 47664 | F7: 0.09 | G7: 6000 | H7: =IF(C7="","",MAX(0,C7-D7)) -> 1050000 | I7: =IF(C7="","",IF(C7=0,0,MIN(1,D7/C7))) -> 0.125 | J7: =IF(E7="","",MAX(0,(YEAR(E7)-YEAR(TODAY()))*12+MONTH(E7)-MONTH(TODAY()))) -> 44 | K7: =IF(OR(C7="",E7=""),"",IF(H7=0,0,IF(J7=0,H7,IF(F7=0,H7/J7,MAX(0,-PMT(F7/12,J7,-D7,C7)))))) -> 19105.88 | L7: =IF(OR(C7="",E7=""),"",FV(F7/12,J7,-G7,-D7)) -> 519793.6 | M7: =IF(L7="","",L7-C7) -> -680206.4 | N7: =IF(C7="","",IF(D7>=C7,"Achieved",IF(J7=0,"Overdue",IF(L7>=C7,"On Track",IF(L7>=0.8*C7,"Slightly Behind","Behind"))))) -> Behind
A8: Child's Higher Education | B8: High | C8: 2500000 | D8: 200000 | E8: 50221 | F8: 0.1 | G8: 9000 | H8: =IF(C8="","",MAX(0,C8-D8)) -> 2300000 | I8: =IF(C8="","",IF(C8=0,0,MIN(1,D8/C8))) -> 0.08 | J8: =IF(E8="","",MAX(0,(YEAR(E8)-YEAR(TODAY()))*12+MONTH(E8)-MONTH(TODAY()))) -> 128 | K8: =IF(OR(C8="",E8=""),"",IF(H8=0,0,IF(J8=0,H8,IF(F8=0,H8/J8,MAX(0,-PMT(F8/12,J8,-D8,C8)))))) -> 8459.0868 | L8: =IF(OR(C8="",E8=""),"",FV(F8/12,J8,-G8,-D8)) -> 2622865 | M8: =IF(L8="","",L8-C8) -> 122864.98 | N8: =IF(C8="","",IF(D8>=C8,"Achieved",IF(J8=0,"Overdue",IF(L8>=C8,"On Track",IF(L8>=0.8*C8,"Slightly Behind","Behind"))))) -> On Track
A9: Flat Down Payment (Dhaka) | B9: Medium | C9: 3000000 | D9: 400000 | E9: 47848 | F9: 0.09 | G9: 8000 | H9: =IF(C9="","",MAX(0,C9-D9)) -> 2600000 | I9: =IF(C9="","",IF(C9=0,0,MIN(1,D9/C9))) -> 0.13333333 | J9: =IF(E9="","",MAX(0,(YEAR(E9)-YEAR(TODAY()))*12+MONTH(E9)-MONTH(TODAY()))) -> 50 | K9: =IF(OR(C9="",E9=""),"",IF(H9=0,0,IF(J9=0,H9,IF(F9=0,H9/J9,MAX(0,-PMT(F9/12,J9,-D9,C9)))))) -> 40050.451 | L9: =IF(OR(C9="",E9=""),"",FV(F9/12,J9,-G9,-D9)) -> 1064336.8 | M9: =IF(L9="","",L9-C9) -> -1935663.2 | N9: =IF(C9="","",IF(D9>=C9,"Achieved",IF(J9=0,"Overdue",IF(L9>=C9,"On Track",IF(L9>=0.8*C9,"Slightly Behind","Behind"))))) -> Behind
A10: Eid-ul-Adha 2027 Qurbani | B10: Medium | C10: 25000 | D10: 5000 | E10: 46517 | F10: 0 | G10: 3000 | H10: =IF(C10="","",MAX(0,C10-D10)) -> 20000 | I10: =IF(C10="","",IF(C10=0,0,MIN(1,D10/C10))) -> 0.2 | J10: =IF(E10="","",MAX(0,(YEAR(E10)-YEAR(TODAY()))*12+MONTH(E10)-MONTH(TODAY()))) -> 7 | K10: =IF(OR(C10="",E10=""),"",IF(H10=0,0,IF(J10=0,H10,IF(F10=0,H10/J10,MAX(0,-PMT(F10/12,J10,-D10,C10)))))) -> 2857.1429 | L10: =IF(OR(C10="",E10=""),"",FV(F10/12,J10,-G10,-D10)) -> 26000 | M10: =IF(L10="","",L10-C10) -> 1000 | N10: =IF(C10="","",IF(D10>=C10,"Achieved",IF(J10=0,"Overdue",IF(L10>=C10,"On Track",IF(L10>=0.8*C10,"Slightly Behind","Behind"))))) -> On Track
A11: Laptop / Electronics | B11: Low | C11: 60000 | D11: 20000 | E11: 46477 | F11: 0 | G11: 6000 | H11: =IF(C11="","",MAX(0,C11-D11)) -> 40000 | I11: =IF(C11="","",IF(C11=0,0,MIN(1,D11/C11))) -> 0.33333333 | J11: =IF(E11="","",MAX(0,(YEAR(E11)-YEAR(TODAY()))*12+MONTH(E11)-MONTH(TODAY()))) -> 5 | K11: =IF(OR(C11="",E11=""),"",IF(H11=0,0,IF(J11=0,H11,IF(F11=0,H11/J11,MAX(0,-PMT(F11/12,J11,-D11,C11)))))) -> 8000 | L11: =IF(OR(C11="",E11=""),"",FV(F11/12,J11,-G11,-D11)) -> 50000 | M11: =IF(L11="","",L11-C11) -> -10000 | N11: =IF(C11="","",IF(D11>=C11,"Achieved",IF(J11=0,"Overdue",IF(L11>=C11,"On Track",IF(L11>=0.8*C11,"Slightly Behind","Behind"))))) -> Slightly Behind
A12: Family Trip (Thailand / Malaysia) | B12: Low | C12: 150000 | D12: 40000 | E12: 46721 | F12: 0 | G12: 7000 | H12: =IF(C12="","",MAX(0,C12-D12)) -> 110000 | I12: =IF(C12="","",IF(C12=0,0,MIN(1,D12/C12))) -> 0.26666667 | J12: =IF(E12="","",MAX(0,(YEAR(E12)-YEAR(TODAY()))*12+MONTH(E12)-MONTH(TODAY()))) -> 13 | K12: =IF(OR(C12="",E12=""),"",IF(H12=0,0,IF(J12=0,H12,IF(F12=0,H12/J12,MAX(0,-PMT(F12/12,J12,-D12,C12)))))) -> 8461.5385 | L12: =IF(OR(C12="",E12=""),"",FV(F12/12,J12,-G12,-D12)) -> 131000 | M12: =IF(L12="","",L12-C12) -> -19000 | N12: =IF(C12="","",IF(D12>=C12,"Achieved",IF(J12=0,"Overdue",IF(L12>=C12,"On Track",IF(L12>=0.8*C12,"Slightly Behind","Behind"))))) -> Slightly Behind
A13: Parents' Medical Reserve | B13: Medium | C13: 100000 | D13: 30000 | E13: 46568 | F13: 0.06 | G13: 8500 | H13: =IF(C13="","",MAX(0,C13-D13)) -> 70000 | I13: =IF(C13="","",IF(C13=0,0,MIN(1,D13/C13))) -> 0.3 | J13: =IF(E13="","",MAX(0,(YEAR(E13)-YEAR(TODAY()))*12+MONTH(E13)-MONTH(TODAY()))) -> 8 | K13: =IF(OR(C13="",E13=""),"",IF(H13=0,0,IF(J13=0,H13,IF(F13=0,H13/J13,MAX(0,-PMT(F13/12,J13,-D13,C13)))))) -> 8448.0205 | L13: =IF(OR(C13="",E13=""),"",FV(F13/12,J13,-G13,-D13)) -> 100423.19 | M13: =IF(L13="","",L13-C13) -> 423.18599 | N13: =IF(C13="","",IF(D13>=C13,"Achieved",IF(J13=0,"Overdue",IF(L13>=C13,"On Track",IF(L13>=0.8*C13,"Slightly Behind","Behind"))))) -> On Track
H14: =IF(C14="","",MAX(0,C14-D14)) | I14: =IF(C14="","",IF(C14=0,0,MIN(1,D14/C14))) | J14: =IF(E14="","",MAX(0,(YEAR(E14)-YEAR(TODAY()))*12+MONTH(E14)-MONTH(TODAY()))) | K14: =IF(OR(C14="",E14=""),"",IF(H14=0,0,IF(J14=0,H14,IF(F14=0,H14/J14,MAX(0,-PMT(F14/12,J14,-D14,C14)))))) | L14: =IF(OR(C14="",E14=""),"",FV(F14/12,J14,-G14,-D14)) | M14: =IF(L14="","",L14-C14) | N14: =IF(C14="","",IF(D14>=C14,"Achieved",IF(J14=0,"Overdue",IF(L14>=C14,"On Track",IF(L14>=0.8*C14,"Slightly Behind","Behind")))))
H15: =IF(C15="","",MAX(0,C15-D15)) | I15: =IF(C15="","",IF(C15=0,0,MIN(1,D15/C15))) | J15: =IF(E15="","",MAX(0,(YEAR(E15)-YEAR(TODAY()))*12+MONTH(E15)-MONTH(TODAY()))) | K15: =IF(OR(C15="",E15=""),"",IF(H15=0,0,IF(J15=0,H15,IF(F15=0,H15/J15,MAX(0,-PMT(F15/12,J15,-D15,C15)))))) | L15: =IF(OR(C15="",E15=""),"",FV(F15/12,J15,-G15,-D15)) | M15: =IF(L15="","",L15-C15) | N15: =IF(C15="","",IF(D15>=C15,"Achieved",IF(J15=0,"Overdue",IF(L15>=C15,"On Track",IF(L15>=0.8*C15,"Slightly Behind","Behind")))))
H16: =IF(C16="","",MAX(0,C16-D16)) | I16: =IF(C16="","",IF(C16=0,0,MIN(1,D16/C16))) | J16: =IF(E16="","",MAX(0,(YEAR(E16)-YEAR(TODAY()))*12+MONTH(E16)-MONTH(TODAY()))) | K16: =IF(OR(C16="",E16=""),"",IF(H16=0,0,IF(J16=0,H16,IF(F16=0,H16/J16,MAX(0,-PMT(F16/12,J16,-D16,C16)))))) | L16: =IF(OR(C16="",E16=""),"",FV(F16/12,J16,-G16,-D16)) | M16: =IF(L16="","",L16-C16) | N16: =IF(C16="","",IF(D16>=C16,"Achieved",IF(J16=0,"Overdue",IF(L16>=C16,"On Track",IF(L16>=0.8*C16,"Slightly Behind","Behind")))))
H17: =IF(C17="","",MAX(0,C17-D17)) | I17: =IF(C17="","",IF(C17=0,0,MIN(1,D17/C17))) | J17: =IF(E17="","",MAX(0,(YEAR(E17)-YEAR(TODAY()))*12+MONTH(E17)-MONTH(TODAY()))) | K17: =IF(OR(C17="",E17=""),"",IF(H17=0,0,IF(J17=0,H17,IF(F17=0,H17/J17,MAX(0,-PMT(F17/12,J17,-D17,C17)))))) | L17: =IF(OR(C17="",E17=""),"",FV(F17/12,J17,-G17,-D17)) | M17: =IF(L17="","",L17-C17) | N17: =IF(C17="","",IF(D17>=C17,"Achieved",IF(J17=0,"Overdue",IF(L17>=C17,"On Track",IF(L17>=0.8*C17,"Slightly Behind","Behind")))))
A18: TOTAL / OVERALL | C18: =SUM(C6:C17) -> 7595000 | D18: =SUM(D6:D17) -> 1112000 | G18: =SUM(G6:G17) -> 57500 | H18: =SUM(H6:H17) -> 6483000 | I18: =IF(C18=0,0,MIN(1,D18/C18)) -> 0.14641211 | K18: =SUM(K6:K17) -> 114303.99 | L18: =SUM(L6:L17) -> 4945370.6 | M18: =SUM(M6:M17) -> -2649629.4
A20: Required monthly saving solves: Saved x (1+i)^n + Saving x [((1+i)^n - 1) / i] = Target, with i = annual return / 12 and n = months left. Use realistic returns (bank savings ~ 4-6%, DPS/FDR ~ 8-10% before tax; check current rates).

Sheet Debt & Loans
A1: DEBT & LOAN MANAGER | ঋণ
A2: Enter each loan (blue). EMI, balance, interest cost and payoff date are calculated. Rank 1 = highest interest rate (debt-avalanche: prepay this first). SAMPLE loans shown.
A5: Lender / Bank | B5: Loan Type | C5: Principal Borrowed (BDT) | D5: Annual Interest Rate | E5: Tenure (months) | F5: First EMI Month | G5: Monthly EMI (BDT) | H5: EMIs Paid | I5: Outstanding Balance (BDT) | J5: Total Interest Cost (BDT) | K5: Total Repayable (BDT) | L5: Final EMI Date | M5: EMIs Remaining | N5: Prepay Priority (avalanche)
A6: City Bank - Personal Loan | B6: Personal Loan | C6: 250000 | D6: 0.14 | E6: 36 | F6: 45996 | G6: =IF(OR(C6="",E6=""),"",IF(D6=0,C6/E6,-PMT(D6/12,E6,C6))) -> 8544.4074 | H6: =IF(OR(C6="",F6=""),"",MAX(0,MIN(E6,(YEAR(TODAY())-YEAR(F6))*12+MONTH(TODAY())-MONTH(F6)+1))) -> 11 | I6: =IF(OR(C6="",H6=""),"",IF(H6>=E6,0,IF(D6=0,C6-G6*H6,FV(D6/12,H6,G6,-C6)))) -> 184354.33 | J6: =IF(G6="","",G6*E6-C6) -> 57598.668 | K6: =IF(G6="","",G6*E6) -> 307598.67 | L6: =IF(OR(C6="",F6=""),"",EDATE(F6,E6-1)) -> 47062 | M6: =IF(H6="","",E6-H6) -> 25 | N6: =IF(OR(C6="",I6=""),"",IF(I6<=0,"Paid off",1+COUNTIFS($D$6:$D$15,">"&D6,$I$6:$I$15,">0"))) -> 2
A7: BRAC Bank - Motorcycle Loan | B7: Motorcycle Loan | C7: 200000 | D7: 0.13 | E7: 36 | F7: 46032 | G7: =IF(OR(C7="",E7=""),"",IF(D7=0,C7/E7,-PMT(D7/12,E7,C7))) -> 6738.7904 | H7: =IF(OR(C7="",F7=""),"",MAX(0,MIN(E7,(YEAR(TODAY())-YEAR(F7))*12+MONTH(TODAY())-MONTH(F7)+1))) -> 10 | I7: =IF(OR(C7="",H7=""),"",IF(H7>=E7,0,IF(D7=0,C7-G7*H7,FV(D7/12,H7,G7,-C7)))) -> 151984.22 | J7: =IF(G7="","",G7*E7-C7) -> 42596.454 | K7: =IF(G7="","",G7*E7) -> 242596.45 | L7: =IF(OR(C7="",F7=""),"",EDATE(F7,E7-1)) -> 47097 | M7: =IF(H7="","",E7-H7) -> 26 | N7: =IF(OR(C7="",I7=""),"",IF(I7<=0,"Paid off",1+COUNTIFS($D$6:$D$15,">"&D7,$I$6:$I$15,">0"))) -> 3
A8: City Bank Credit Card (instalment) | B8: Credit Card | C8: 30000 | D8: 0.2 | E8: 12 | F8: 46204 | G8: =IF(OR(C8="",E8=""),"",IF(D8=0,C8/E8,-PMT(D8/12,E8,C8))) -> 2779.0352 | H8: =IF(OR(C8="",F8=""),"",MAX(0,MIN(E8,(YEAR(TODAY())-YEAR(F8))*12+MONTH(TODAY())-MONTH(F8)+1))) -> 4 | I8: =IF(OR(C8="",H8=""),"",IF(H8>=E8,0,IF(D8=0,C8-G8*H8,FV(D8/12,H8,G8,-C8)))) -> 20653.413 | J8: =IF(G8="","",G8*E8-C8) -> 3348.4221 | K8: =IF(G8="","",G8*E8) -> 33348.422 | L8: =IF(OR(C8="",F8=""),"",EDATE(F8,E8-1)) -> 46539 | M8: =IF(H8="","",E8-H8) -> 8 | N8: =IF(OR(C8="",I8=""),"",IF(I8<=0,"Paid off",1+COUNTIFS($D$6:$D$15,">"&D8,$I$6:$I$15,">0"))) -> 1
G9: =IF(OR(C9="",E9=""),"",IF(D9=0,C9/E9,-PMT(D9/12,E9,C9))) | H9: =IF(OR(C9="",F9=""),"",MAX(0,MIN(E9,(YEAR(TODAY())-YEAR(F9))*12+MONTH(TODAY())-MONTH(F9)+1))) | I9: =IF(OR(C9="",H9=""),"",IF(H9>=E9,0,IF(D9=0,C9-G9*H9,FV(D9/12,H9,G9,-C9)))) | J9: =IF(G9="","",G9*E9-C9) | K9: =IF(G9="","",G9*E9) | L9: =IF(OR(C9="",F9=""),"",EDATE(F9,E9-1)) | M9: =IF(H9="","",E9-H9) | N9: =IF(OR(C9="",I9=""),"",IF(I9<=0,"Paid off",1+COUNTIFS($D$6:$D$15,">"&D9,$I$6:$I$15,">0")))
G10: =IF(OR(C10="",E10=""),"",IF(D10=0,C10/E10,-PMT(D10/12,E10,C10))) | H10: =IF(OR(C10="",F10=""),"",MAX(0,MIN(E10,(YEAR(TODAY())-YEAR(F10))*12+MONTH(TODAY())-MONTH(F10)+1))) | I10: =IF(OR(C10="",H10=""),"",IF(H10>=E10,0,IF(D10=0,C10-G10*H10,FV(D10/12,H10,G10,-C10)))) | J10: =IF(G10="","",G10*E10-C10) | K10: =IF(G10="","",G10*E10) | L10: =IF(OR(C10="",F10=""),"",EDATE(F10,E10-1)) | M10: =IF(H10="","",E10-H10) | N10: =IF(OR(C10="",I10=""),"",IF(I10<=0,"Paid off",1+COUNTIFS($D$6:$D$15,">"&D10,$I$6:$I$15,">0")))
G11: =IF(OR(C11="",E11=""),"",IF(D11=0,C11/E11,-PMT(D11/12,E11,C11))) | H11: =IF(OR(C11="",F11=""),"",MAX(0,MIN(E11,(YEAR(TODAY())-YEAR(F11))*12+MONTH(TODAY())-MONTH(F11)+1))) | I11: =IF(OR(C11="",H11=""),"",IF(H11>=E11,0,IF(D11=0,C11-G11*H11,FV(D11/12,H11,G11,-C11)))) | J11: =IF(G11="","",G11*E11-C11) | K11: =IF(G11="","",G11*E11) | L11: =IF(OR(C11="",F11=""),"",EDATE(F11,E11-1)) | M11: =IF(H11="","",E11-H11) | N11: =IF(OR(C11="",I11=""),"",IF(I11<=0,"Paid off",1+COUNTIFS($D$6:$D$15,">"&D11,$I$6:$I$15,">0")))
G12: =IF(OR(C12="",E12=""),"",IF(D12=0,C12/E12,-PMT(D12/12,E12,C12))) | H12: =IF(OR(C12="",F12=""),"",MAX(0,MIN(E12,(YEAR(TODAY())-YEAR(F12))*12+MONTH(TODAY())-MONTH(F12)+1))) | I12: =IF(OR(C12="",H12=""),"",IF(H12>=E12,0,IF(D12=0,C12-G12*H12,FV(D12/12,H12,G12,-C12)))) | J12: =IF(G12="","",G12*E12-C12) | K12: =IF(G12="","",G12*E12) | L12: =IF(OR(C12="",F12=""),"",EDATE(F12,E12-1)) | M12: =IF(H12="","",E12-H12) | N12: =IF(OR(C12="",I12=""),"",IF(I12<=0,"Paid off",1+COUNTIFS($D$6:$D$15,">"&D12,$I$6:$I$15,">0")))
G13: =IF(OR(C13="",E13=""),"",IF(D13=0,C13/E13,-PMT(D13/12,E13,C13))) | H13: =IF(OR(C13="",F13=""),"",MAX(0,MIN(E13,(YEAR(TODAY())-YEAR(F13))*12+MONTH(TODAY())-MONTH(F13)+1))) | I13: =IF(OR(C13="",H13=""),"",IF(H13>=E13,0,IF(D13=0,C13-G13*H13,FV(D13/12,H13,G13,-C13)))) | J13: =IF(G13="","",G13*E13-C13) | K13: =IF(G13="","",G13*E13) | L13: =IF(OR(C13="",F13=""),"",EDATE(F13,E13-1)) | M13: =IF(H13="","",E13-H13) | N13: =IF(OR(C13="",I13=""),"",IF(I13<=0,"Paid off",1+COUNTIFS($D$6:$D$15,">"&D13,$I$6:$I$15,">0")))
G14: =IF(OR(C14="",E14=""),"",IF(D14=0,C14/E14,-PMT(D14/12,E14,C14))) | H14: =IF(OR(C14="",F14=""),"",MAX(0,MIN(E14,(YEAR(TODAY())-YEAR(F14))*12+MONTH(TODAY())-MONTH(F14)+1))) | I14: =IF(OR(C14="",H14=""),"",IF(H14>=E14,0,IF(D14=0,C14-G14*H14,FV(D14/12,H14,G14,-C14)))) | J14: =IF(G14="","",G14*E14-C14) | K14: =IF(G14="","",G14*E14) | L14: =IF(OR(C14="",F14=""),"",EDATE(F14,E14-1)) | M14: =IF(H14="","",E14-H14) | N14: =IF(OR(C14="",I14=""),"",IF(I14<=0,"Paid off",1+COUNTIFS($D$6:$D$15,">"&D14,$I$6:$I$15,">0")))
G15: =IF(OR(C15="",E15=""),"",IF(D15=0,C15/E15,-PMT(D15/12,E15,C15))) | H15: =IF(OR(C15="",F15=""),"",MAX(0,MIN(E15,(YEAR(TODAY())-YEAR(F15))*12+MONTH(TODAY())-MONTH(F15)+1))) | I15: =IF(OR(C15="",H15=""),"",IF(H15>=E15,0,IF(D15=0,C15-G15*H15,FV(D15/12,H15,G15,-C15)))) | J15: =IF(G15="","",G15*E15-C15) | K15: =IF(G15="","",G15*E15) | L15: =IF(OR(C15="",F15=""),"",EDATE(F15,E15-1)) | M15: =IF(H15="","",E15-H15) | N15: =IF(OR(C15="",I15=""),"",IF(I15<=0,"Paid off",1+COUNTIFS($D$6:$D$15,">"&D15,$I$6:$I$15,">0")))
A16: TOTAL | C16: =SUM(C6:C15) -> 480000 | G16: =SUM(G6:G15) -> 18062.233 | I16: =SUM(I6:I15) -> 356991.97 | J16: =SUM(J6:J15) -> 103543.54 | K16: =SUM(K6:K15) -> 583543.54
A18: DEBT-TO-INCOME HEALTH CHECK
A19: Total monthly EMI (BDT) | C19: =G16 -> 18062.233
A20: Average monthly income, year to date (BDT) | C20: ='Monthly Summary'!$B$19 -> 140187.4
A21: Debt-to-Income ratio (EMI / income) | C21: =IF(C20=0,0,C19/C20) -> 0.12884348
A22: Maximum healthy ratio (Settings) | C22: =Settings!$B$9 -> 0.4
A23: Status | C23: =IF(C21<=C22,"HEALTHY","TOO HIGH") -> HEALTHY
A24: Debt-free date (last EMI) | C24: =IF(COUNT(L6:L15)=0,"-",MAX(L6:L15)) -> 47097
A26: EMI uses the standard reducing-balance formula: EMI = P x r x (1+r)^n / ((1+r)^n - 1), r = annual rate / 12. Banks may add processing fees or round differently - check your loan schedule. Credit-card rates in Bangladesh are capped by Bangladesh Bank (verify current cap).

Sheet Investments
A1: SAVINGS & INVESTMENT TRACKER | DPS, FDR, Sanchayapatra
A2: Maturity value, source tax and net return for typical Bangladeshi instruments. Rates shown are ILLUSTRATIVE - enter the rate on your certificate / bank offer letter. SAMPLE rows shown.
A5: Instrument | B5: Provider | C5: Type | D5: Method | E5: Amount (BDT) - lump sum, or monthly instalment for DPS | F5: Annual Rate | G5: Tenure (months) | H5: Start Date | I5: Compounding periods / year | J5: Source Tax Rate | K5: Total Invested (BDT) | L5: Gross Maturity Value | M5: Gross Interest / Profit | N5: Tax at Source | O5: Net Maturity Value | P5: Maturity Date | Q5: Net Return on Invested | R5: Real Annual Yield (after tax & inflation)
A6: DPS - Dutch-Bangla Bank | B6: Dutch-Bangla Bank | C6: Bank DPS | D6: Monthly Deposit (DPS) | E6: 5000 | F6: 0.085 | G6: 60 | H6: 45843 | J6: =Settings!$B$39 -> 0.1 | K6: =IF(E6="","",IF(LEFT(D6,7)="Monthly",E6*G6,E6)) -> 300000 | L6: =IF(OR(E6="",F6="",G6=""),"",IF(LEFT(D6,7)="Monthly",FV(F6/12,G6,-E6,0,1),IF(LEFT(D6,6)="Simple",E6*(1+F6*G6/12),E6*(1+F6/MAX(1,N(I6)))^(MAX(1,N(I6))*G6/12)))) -> 374848.69 | M6: =IF(L6="","",L6-K6) -> 74848.69 | N6: =IF(M6="","",M6*N(J6)) -> 7484.869 | O6: =IF(L6="","",L6-N6) -> 367363.82 | P6: =IF(OR(E6="",H6="",G6=""),"",EDATE(H6,G6)) -> 47669 | Q6: =IF(OR(K6="",K6=0),"",(O6-K6)/K6) -> 0.22454607 | R6: =IF(OR(E6="",F6=""),"",(1+F6*(1-N(J6)))/(1+Settings!$B$10)-1) -> -0.0078341014
A7: 1-Year FDR | B7: City Bank | C7: Bank FDR | D7: Compound (FDR / Term Deposit) | E7: 500000 | F7: 0.09 | G7: 12 | H7: 46106 | I7: 4 | J7: =Settings!$B$39 -> 0.1 | K7: =IF(E7="","",IF(LEFT(D7,7)="Monthly",E7*G7,E7)) -> 500000 | L7: =IF(OR(E7="",F7="",G7=""),"",IF(LEFT(D7,7)="Monthly",FV(F7/12,G7,-E7,0,1),IF(LEFT(D7,6)="Simple",E7*(1+F7*G7/12),E7*(1+F7/MAX(1,N(I7)))^(MAX(1,N(I7))*G7/12)))) -> 546541.66 | M7: =IF(L7="","",L7-K7) -> 46541.659 | N7: =IF(M7="","",M7*N(J7)) -> 4654.1659 | O7: =IF(L7="","",L7-N7) -> 541887.49 | P7: =IF(OR(E7="",H7="",G7=""),"",EDATE(H7,G7)) -> 46471 | Q7: =IF(OR(K7="",K7=0),"",(O7-K7)/K7) -> 0.083774987 | R7: =IF(OR(E7="",F7=""),"",(1+F7*(1-N(J7)))/(1+Settings!$B$10)-1) -> -0.0036866359
A8: Paribarik Sanchayapatra (5-year) | B8: National Savings Directorate | C8: Sanchayapatra | D8: Simple Interest (Sanchayapatra) | E8: 300000 | F8: 0.1152 | G8: 60 | H8: 45945 | J8: =Settings!$B$40 -> 0.1 | K8: =IF(E8="","",IF(LEFT(D8,7)="Monthly",E8*G8,E8)) -> 300000 | L8: =IF(OR(E8="",F8="",G8=""),"",IF(LEFT(D8,7)="Monthly",FV(F8/12,G8,-E8,0,1),IF(LEFT(D8,6)="Simple",E8*(1+F8*G8/12),E8*(1+F8/MAX(1,N(I8)))^(MAX(1,N(I8))*G8/12)))) -> 472800 | M8: =IF(L8="","",L8-K8) -> 172800 | N8: =IF(M8="","",M8*N(J8)) -> 17280 | O8: =IF(L8="","",L8-N8) -> 455520 | P8: =IF(OR(E8="",H8="",G8=""),"",EDATE(H8,G8)) -> 47771 | Q8: =IF(OR(K8="",K8=0),"",(O8-K8)/K8) -> 0.5184 | R8: =IF(OR(E8="",F8=""),"",(1+F8*(1-N(J8)))/(1+Settings!$B$10)-1) -> 0.01721659
K9: =IF(E9="","",IF(LEFT(D9,7)="Monthly",E9*G9,E9)) | L9: =IF(OR(E9="",F9="",G9=""),"",IF(LEFT(D9,7)="Monthly",FV(F9/12,G9,-E9,0,1),IF(LEFT(D9,6)="Simple",E9*(1+F9*G9/12),E9*(1+F9/MAX(1,N(I9)))^(MAX(1,N(I9))*G9/12)))) | M9: =IF(L9="","",L9-K9) | N9: =IF(M9="","",M9*N(J9)) | O9: =IF(L9="","",L9-N9) | P9: =IF(OR(E9="",H9="",G9=""),"",EDATE(H9,G9)) | Q9: =IF(OR(K9="",K9=0),"",(O9-K9)/K9) | R9: =IF(OR(E9="",F9=""),"",(1+F9*(1-N(J9)))/(1+Settings!$B$10)-1)
K10: =IF(E10="","",IF(LEFT(D10,7)="Monthly",E10*G10,E10)) | L10: =IF(OR(E10="",F10="",G10=""),"",IF(LEFT(D10,7)="Monthly",FV(F10/12,G10,-E10,0,1),IF(LEFT(D10,6)="Simple",E10*(1+F10*G10/12),E10*(1+F10/MAX(1,N(I10)))^(MAX(1,N(I10))*G10/12)))) | M10: =IF(L10="","",L10-K10) | N10: =IF(M10="","",M10*N(J10)) | O10: =IF(L10="","",L10-N10) | P10: =IF(OR(E10="",H10="",G10=""),"",EDATE(H10,G10)) | Q10: =IF(OR(K10="",K10=0),"",(O10-K10)/K10) | R10: =IF(OR(E10="",F10=""),"",(1+F10*(1-N(J10)))/(1+Settings!$B$10)-1)
K11: =IF(E11="","",IF(LEFT(D11,7)="Monthly",E11*G11,E11)) | L11: =IF(OR(E11="",F11="",G11=""),"",IF(LEFT(D11,7)="Monthly",FV(F11/12,G11,-E11,0,1),IF(LEFT(D11,6)="Simple",E11*(1+F11*G11/12),E11*(1+F11/MAX(1,N(I11)))^(MAX(1,N(I11))*G11/12)))) | M11: =IF(L11="","",L11-K11) | N11: =IF(M11="","",M11*N(J11)) | O11: =IF(L11="","",L11-N11) | P11: =IF(OR(E11="",H11="",G11=""),"",EDATE(H11,G11)) | Q11: =IF(OR(K11="",K11=0),"",(O11-K11)/K11) | R11: =IF(OR(E11="",F11=""),"",(1+F11*(1-N(J11)))/(1+Settings!$B$10)-1)
K12: =IF(E12="","",IF(LEFT(D12,7)="Monthly",E12*G12,E12)) | L12: =IF(OR(E12="",F12="",G12=""),"",IF(LEFT(D12,7)="Monthly",FV(F12/12,G12,-E12,0,1),IF(LEFT(D12,6)="Simple",E12*(1+F12*G12/12),E12*(1+F12/MAX(1,N(I12)))^(MAX(1,N(I12))*G12/12)))) | M12: =IF(L12="","",L12-K12) | N12: =IF(M12="","",M12*N(J12)) | O12: =IF(L12="","",L12-N12) | P12: =IF(OR(E12="",H12="",G12=""),"",EDATE(H12,G12)) | Q12: =IF(OR(K12="",K12=0),"",(O12-K12)/K12) | R12: =IF(OR(E12="",F12=""),"",(1+F12*(1-N(J12)))/(1+Settings!$B$10)-1)
K13: =IF(E13="","",IF(LEFT(D13,7)="Monthly",E13*G13,E13)) | L13: =IF(OR(E13="",F13="",G13=""),"",IF(LEFT(D13,7)="Monthly",FV(F13/12,G13,-E13,0,1),IF(LEFT(D13,6)="Simple",E13*(1+F13*G13/12),E13*(1+F13/MAX(1,N(I13)))^(MAX(1,N(I13))*G13/12)))) | M13: =IF(L13="","",L13-K13) | N13: =IF(M13="","",M13*N(J13)) | O13: =IF(L13="","",L13-N13) | P13: =IF(OR(E13="",H13="",G13=""),"",EDATE(H13,G13)) | Q13: =IF(OR(K13="",K13=0),"",(O13-K13)/K13) | R13: =IF(OR(E13="",F13=""),"",(1+F13*(1-N(J13)))/(1+Settings!$B$10)-1)
K14: =IF(E14="","",IF(LEFT(D14,7)="Monthly",E14*G14,E14)) | L14: =IF(OR(E14="",F14="",G14=""),"",IF(LEFT(D14,7)="Monthly",FV(F14/12,G14,-E14,0,1),IF(LEFT(D14,6)="Simple",E14*(1+F14*G14/12),E14*(1+F14/MAX(1,N(I14)))^(MAX(1,N(I14))*G14/12)))) | M14: =IF(L14="","",L14-K14) | N14: =IF(M14="","",M14*N(J14)) | O14: =IF(L14="","",L14-N14) | P14: =IF(OR(E14="",H14="",G14=""),"",EDATE(H14,G14)) | Q14: =IF(OR(K14="",K14=0),"",(O14-K14)/K14) | R14: =IF(OR(E14="",F14=""),"",(1+F14*(1-N(J14)))/(1+Settings!$B$10)-1)
K15: =IF(E15="","",IF(LEFT(D15,7)="Monthly",E15*G15,E15)) | L15: =IF(OR(E15="",F15="",G15=""),"",IF(LEFT(D15,7)="Monthly",FV(F15/12,G15,-E15,0,1),IF(LEFT(D15,6)="Simple",E15*(1+F15*G15/12),E15*(1+F15/MAX(1,N(I15)))^(MAX(1,N(I15))*G15/12)))) | M15: =IF(L15="","",L15-K15) | N15: =IF(M15="","",M15*N(J15)) | O15: =IF(L15="","",L15-N15) | P15: =IF(OR(E15="",H15="",G15=""),"",EDATE(H15,G15)) | Q15: =IF(OR(K15="",K15=0),"",(O15-K15)/K15) | R15: =IF(OR(E15="",F15=""),"",(1+F15*(1-N(J15)))/(1+Settings!$B$10)-1)
K16: =IF(E16="","",IF(LEFT(D16,7)="Monthly",E16*G16,E16)) | L16: =IF(OR(E16="",F16="",G16=""),"",IF(LEFT(D16,7)="Monthly",FV(F16/12,G16,-E16,0,1),IF(LEFT(D16,6)="Simple",E16*(1+F16*G16/12),E16*(1+F16/MAX(1,N(I16)))^(MAX(1,N(I16))*G16/12)))) | M16: =IF(L16="","",L16-K16) | N16: =IF(M16="","",M16*N(J16)) | O16: =IF(L16="","",L16-N16) | P16: =IF(OR(E16="",H16="",G16=""),"",EDATE(H16,G16)) | Q16: =IF(OR(K16="",K16=0),"",(O16-K16)/K16) | R16: =IF(OR(E16="",F16=""),"",(1+F16*(1-N(J16)))/(1+Settings!$B$10)-1)
K17: =IF(E17="","",IF(LEFT(D17,7)="Monthly",E17*G17,E17)) | L17: =IF(OR(E17="",F17="",G17=""),"",IF(LEFT(D17,7)="Monthly",FV(F17/12,G17,-E17,0,1),IF(LEFT(D17,6)="Simple",E17*(1+F17*G17/12),E17*(1+F17/MAX(1,N(I17)))^(MAX(1,N(I17))*G17/12)))) | M17: =IF(L17="","",L17-K17) | N17: =IF(M17="","",M17*N(J17)) | O17: =IF(L17="","",L17-N17) | P17: =IF(OR(E17="",H17="",G17=""),"",EDATE(H17,G17)) | Q17: =IF(OR(K17="",K17=0),"",(O17-K17)/K17) | R17: =IF(OR(E17="",F17=""),"",(1+F17*(1-N(J17)))/(1+Settings!$B$10)-1)
A18: TOTAL | K18: =SUM(K6:K17) -> 1100000 | L18: =SUM(L6:L17) -> 1394190.3 | M18: =SUM(M6:M17) -> 294190.35 | N18: =SUM(N6:N17) -> 29419.035 | O18: =SUM(O6:O17) -> 1364771.3
A20: Methods: Compound = FDR/term deposit with interest added every period; Monthly Deposit = DPS (instalment at start of month, monthly compounding approximation); Simple = Sanchayapatra-style profit on the face value. Banks may compound quarterly and round differently - your maturity certificate is the final authority.
A21: Source tax defaults come from Settings (10% with TIN; use 15% if you have no TIN). Real yield = (1 + rate x (1 - tax)) / (1 + inflation) - 1, using the inflation assumption in Settings.

Sheet Net Worth
A1: NET WORTH STATEMENT | সম্পদ ও দায়
A2: Assets minus liabilities. Update values monthly (blue cells). Gold uses quantity x rate per bhori (1 bhori = 11.664 g). SAMPLE values shown.
A5: Asset Class | B5: Item | C5: Value (BDT) | D5: Qty (bhori) | E5: Rate per bhori (BDT) | F5: Liquid? (for emergency fund)
A6: Liquid | B6: Cash in Hand | C6: 15000 | F6: Yes
A7: Liquid | B7: Bank Savings / Current Accounts | C7: 240000 | F7: Yes
A8: Liquid | B8: bKash / Nagad / Rocket Wallets | C8: 12000 | F8: Yes
A9: Investments | B9: DPS Balance | C9: 80000 | F9: No
A10: Investments | B10: FDR (Fixed Deposit) | C10: 500000 | F10: No
A11: Investments | B11: Sanchayapatra (National Savings) | C11: 300000 | F11: No
A12: Investments | B12: DSE Shares / Mutual Funds | C12: 120000 | F12: No
A13: Investments | B13: Provident / Pension Fund | C13: 450000 | F13: No
A14: Precious Metals | B14: Gold Jewellery / Bars (22K) | C14: =D14*E14 -> 600000 | D14: 3 | E14: 200000 | F14: No
A15: Property | B15: Land / Flat / Plot | C15: 0 | F15: No
A16: Vehicle | B16: Motorcycle / Car (market value) | C16: 140000 | F16: No
A17: Other | B17: Other Assets | C17: 0 | F17: No
A18: TOTAL ASSETS | C18: =SUM(C6:C17) -> 2457000
A20: LIABILITIES
A21: Loans | B21: Outstanding balance - Debt & Loans sheet | C21: ='Debt & Loans'!$I$16 -> 356991.97
A22: Other | B22: Other dues / informal borrowing | C22: 0
A23: TOTAL LIABILITIES | C23: =C21+C22 -> 356991.97
A25: NET WORTH | C25: =C18-C23 -> 2100008
A26: Liquid assets (cash, bank, wallets) | C26: =SUMIF(F6:F17,"Yes",C6:C17) -> 267000
A27: Emergency-fund coverage (months of spending) | C27: =IF('Monthly Summary'!$E$19=0,0,C26/'Monthly Summary'!$E$19) -> 2.8618897
A28: Debt-to-asset ratio | C28: =IF(C18=0,0,C23/C18) -> 0.14529588
A30: NET WORTH HISTORY (record month-end value)
A31: Month | B31: Net Worth (BDT) | C31: Change vs previous
A32: =Settings!$D$4 -> January | B32: 1700000 | C32: =""
A33: =Settings!$D$5 -> February | B33: 1735000 | C33: =IF(OR(B33="",B32=""),"",B33-B32) -> 35000
A34: =Settings!$D$6 -> March | B34: 1790000 | C34: =IF(OR(B34="",B33=""),"",B34-B33) -> 55000
A35: =Settings!$D$7 -> April | B35: 1812000 | C35: =IF(OR(B35="",B34=""),"",B35-B34) -> 22000
A36: =Settings!$D$8 -> May | B36: 1850000 | C36: =IF(OR(B36="",B35=""),"",B36-B35) -> 38000
A37: =Settings!$D$9 -> June | B37: 1880000 | C37: =IF(OR(B37="",B36=""),"",B37-B36) -> 30000
A38: =Settings!$D$10 -> July | B38: 1925000 | C38: =IF(OR(B38="",B37=""),"",B38-B37) -> 45000
A39: =Settings!$D$11 -> August | B39: 1960000 | C39: =IF(OR(B39="",B38=""),"",B39-B38) -> 35000
A40: =Settings!$D$12 -> September | B40: 2010000 | C40: =IF(OR(B40="",B39=""),"",B40-B39) -> 50000
A41: =Settings!$D$13 -> October | C41: =IF(OR(B41="",B40=""),"",B41-B40)
A42: =Settings!$D$14 -> November | C42: =IF(OR(B42="",B41=""),"",B42-B41)
A43: =Settings!$D$15 -> December | C43: =IF(OR(B43="",B42=""),"",B43-B42)
A44: Tip: type this month's closing Net Worth (cell C25) into the next blank blue cell each month-end to build the trend chart.

Sheet Income Tax
A1: INCOME TAX ESTIMATOR | আয়কর
A2: Individual taxpayer estimate using the slabs in Settings (budget FY2026-27 figures - VERIFY with NBR before filing). Planning aid only - not tax advice.
A4: TAXPAYER PROFILE
A5: Taxpayer category | B5: General
A6: Disabled children / dependents (count) | B6: 0
A9: ANNUAL INCOME (BDT)
A10: Basic salary (annual) | B10: 960000
A11: House rent allowance | B11: 480000
A12: Medical allowance | B12: 96000
A13: Conveyance allowance | B13: 36000
A14: Festival bonus (both Eids) | B14: 160000
A15: Other salary items (overtime, performance bonus) | B15: 0
A16: Total salary income | B16: =SUM(B10:B15) -> 1732000
A17: Other income - freelance / business / rental (net) | B17: 75000
A18: Other income - interest / dividend not taxed at source | B18: 0
A19: TOTAL INCOME | B19: =B16+B17+B18 -> 1807000
A20: Less: exempt portion of salary (lower of 1/3 of salary or cap) | B20: =MIN(B16*Settings!$B$33,Settings!$B$34) -> 450000
A21: TAXABLE INCOME | B21: =MAX(0,B19-B20) -> 1357000
A23: TAX CALCULATION
A24: Applicable tax-free threshold | B24: =INDEX(Settings!$B$19:$B$22,MATCH(B5,Settings!$A$19:$A$22,0))+B6*Settings!$B$23 -> 375000
A25: Slab | B25: From (BDT) | C25: Slab Width (BDT) | D25: Rate | E25: Income in Slab | F25: Tax (BDT)
A26: Tax-free slab | B26: 0 | C26: =B24 -> 375000 | D26: 0 | E26: =MIN($B$21,C26) -> 375000 | F26: =E26*D26 -> 0
A27: =Settings!$A$26 -> Slab 1 (next) | B27: =B26+C26 -> 375000 | C27: =Settings!$B$26 -> 300000 | D27: =Settings!$C$26 -> 0.1 | E27: =MAX(0,MIN($B$21-B27,C27)) -> 300000 | F27: =E27*D27 -> 30000
A28: =Settings!$A$27 -> Slab 2 (next) | B28: =B27+C27 -> 675000 | C28: =Settings!$B$27 -> 400000 | D28: =Settings!$C$27 -> 0.15 | E28: =MAX(0,MIN($B$21-B28,C28)) -> 400000 | F28: =E28*D28 -> 60000
A29: =Settings!$A$28 -> Slab 3 (next) | B29: =B28+C28 -> 1075000 | C29: =Settings!$B$28 -> 500000 | D29: =Settings!$C$28 -> 0.2 | E29: =MAX(0,MIN($B$21-B29,C29)) -> 282000 | F29: =E29*D29 -> 56400
A30: =Settings!$A$29 -> Slab 4 (next) | B30: =B29+C29 -> 1575000 | C30: =Settings!$B$29 -> 2000000 | D30: =Settings!$C$29 -> 0.25 | E30: =MAX(0,MIN($B$21-B30,C30)) -> 0 | F30: =E30*D30 -> 0
A31: =Settings!$A$30 -> Slab 5 (remainder) | B31: =B30+C30 -> 3575000 | C31: =Settings!$B$30 -> 1000000000 | D31: =Settings!$C$30 -> 0.3 | E31: =MAX(0,MIN($B$21-B31,C31)) -> 0 | F31: =E31*D31 -> 0
A32: TOTAL | E32: =SUM(E26:E31) -> 1357000 | F32: =SUM(F26:F31) -> 146400
A34: INVESTMENT TAX REBATE
A35: DPS deposits (YTD from Transactions) | B35: ='Annual Matrix'!$O$55 -> 50000
A36: FDR / Sanchayapatra purchases (YTD) | B36: ='Annual Matrix'!$O$56 -> 50000
A37: Stocks & mutual funds (YTD) | B37: ='Annual Matrix'!$O$57 -> 15000
A38: Life insurance premiums (YTD) | B38: ='Annual Matrix'!$O$52 -> 25000
A39: Other eligible investment / approved donation (enter) | B39: 0
A40: Total eligible investment | B40: =SUM(B35:B39) -> 140000
A41: Allowable investment (capped at % of taxable income) | B41: =MIN(B40,Settings!$B$37*B21) -> 140000
A42: Rebate limit A: % of taxable income | B42: =Settings!$B$35*B21 -> 40710
A43: Rebate limit B: rate x allowable investment | B43: =Settings!$B$36*B41 -> 21000
A44: Rebate limit C: absolute maximum | B44: =Settings!$B$38 -> 1000000
A45: TAX REBATE ALLOWED (lowest of A, B, C) | B45: =MIN(B42,B43,B44) -> 21000
A47: TAX PAYABLE
A48: Gross tax before rebate | B48: =F32 -> 146400
A49: Less: investment rebate | B49: =B45 -> 21000
A50: Tax after rebate | B50: =MAX(0,B48-B49) -> 125400
A51: Minimum tax applicable (if income exceeds threshold) | B51: =IF(B21>B24,Settings!$B$32,0) -> 5000
A52: TAX PAYABLE (higher of tax after rebate and minimum tax) | B52: =IF(B21<=B24,0,MAX(B50,B51)) -> 125400
A53: Less: tax already deducted / paid (employer TDS, advance tax) | B53: 60000
A54: NET TAX PAYABLE / (REFUND) | B54: =B52-B53 -> 65400
A55: Effective tax rate on total income | B55: =IF(B19=0,0,B52/B19) -> 0.06939679
A56: Suggested monthly tax set-aside | B56: =B52/12 -> 10450
A58: Notes: (1) Slabs, thresholds, minimum tax and rebate rules are editable in Settings - FY2026-27 budget coverage (June 2026) reported a Tk 3,75,000 general threshold; some sources differ, so confirm with the NBR / your tax lawyer. (2) Investment lines pull year-to-date amounts from your Transaction Log - overwrite with full-year estimates if needed. (3) Sanchayapatra/bank interest taxed at source may be treated differently on your return.

Sheet Zakat
A1: ZAKAT CALCULATOR | যাকাত
A2: Zakat is 2.5% of net zakatable wealth held above the nisab for one lunar year. Prices per bhori (tola) are blue inputs - use the current BAJUS gold / silver rate. Consult a qualified scholar for your situation.
A5: ZAKATABLE ASSETS
A6: Cash in hand, bank & MFS wallets | B6: =SUM('Net Worth'!C6:C8) -> 267000
A7: Gold owned (bhori) | B7: ='Net Worth'!D14 -> 3
A8: Gold price per bhori (BDT) | B8: ='Net Worth'!E14 -> 200000
A9: Gold value | B9: =B7*B8 -> 600000
A10: Silver owned (bhori) | B10: 0
A11: Silver price per bhori (BDT) - update from BAJUS | B11: 3500
A12: Silver value | B12: =B10*B11 -> 0
A13: Business inventory / trade goods | B13: 0
A14: Money lent (expected to be repaid) | B14: 0
A15: Shares / mutual funds held for trading | B15: ='Net Worth'!C12 -> 120000
A16: DPS, FDR & Sanchayapatra | B16: =SUM('Net Worth'!C9:C11) -> 880000
A17: Provident fund (include if accessible; scholars differ) | B17: ='Net Worth'!C13 -> 450000
A18: Other zakatable assets | B18: 0
A19: TOTAL ZAKATABLE ASSETS | B19: =B6+B9+B12+B13+B14+B15+B16+B17+B18 -> 2317000
A21: Less: debts due now (bills, current EMI, credit-card dues) | B21: 21000
A22: NET ZAKATABLE WEALTH | B22: =MAX(0,B19-B21) -> 2296000
A24: NISAB & ZAKAT DUE
A25: Nisab basis (choose) | B25: Silver (52.5 tola)
A26: Silver nisab value | B26: =Settings!$B$44*B11 -> 183750
A27: Gold nisab value | B27: =Settings!$B$45*B8 -> 1500000
A28: Applicable nisab | B28: =IF(LEFT(B25,6)="Silver",B26,B27) -> 183750
A29: Is Zakat due? | B29: =IF(B22>=B28,"YES - Zakat is due","NO - below nisab") -> YES - Zakat is due
A30: ZAKAT PAYABLE (2.5%) | B30: =IF(B22>=B28,B22*Settings!$B$43,0) -> 57400
A31: Monthly set-aside to be ready | B31: =B30/12 -> 4783.3333
A32: Zakat / Sadaqah paid this year (Transactions, category 'Zakat, Fitra & Sadaqah') | B32: ='Annual Matrix'!$O$47 -> 36650
A33: Remaining Zakat to pay | B33: =MAX(0,B30-B32) -> 20750
A35: Notes: silver nisab (52.5 tola) is the lower threshold and is widely used in Bangladesh; gold nisab (7.5 tola) is the other common basis - follow your scholar. Items counted (e.g. provident fund, personal-use jewellery) vary by school of thought. The paid line may include voluntary Sadaqah and Fitra - adjust as needed.

Sheet Festivals
A1: FESTIVAL & QURBANI PLANNER | উৎসব
A2: Plan Eid, Boishakh, Puja and social-event spending months ahead and see how much to set aside each month. Dates are approximate (Eid depends on moon sighting). SAMPLE budgets shown.
A5: Festival | B5: Approx. Date | C5: Total Budget (BDT) | D5: Total Actual (BDT) | E5: Variance (Budget - Actual) | F5: Months Left | G5: Monthly Saving Needed | H5: Funded So Far (BDT) | I5: Still Needed (BDT)
A6: Eid-ul-Fitr 2027 | B6: 46456 | C6: =SUMIF($A$28:$A$67,A6,$C$28:$C$67) -> 54480 | D6: =SUMIF($A$28:$A$67,A6,$D$28:$D$67) -> 0 | E6: =C6-D6 -> 54480 | F6: =IF(B6="","",MAX(0,(YEAR(B6)-YEAR(TODAY()))*12+MONTH(B6)-MONTH(TODAY()))) -> 5 | G6: =IF(F6="","",IF(F6=0,I6,I6/F6)) -> 7896 | H6: 15000 | I6: =MAX(0,C6-H6) -> 39480
A7: Eid-ul-Adha 2027 | B7: 46524 | C7: =SUMIF($A$28:$A$67,A7,$C$28:$C$67) -> 55000 | D7: =SUMIF($A$28:$A$67,A7,$D$28:$D$67) -> 0 | E7: =C7-D7 -> 55000 | F7: =IF(B7="","",MAX(0,(YEAR(B7)-YEAR(TODAY()))*12+MONTH(B7)-MONTH(TODAY()))) -> 7 | G7: =IF(F7="","",IF(F7=0,I7,I7/F7)) -> 7142.8571 | H7: 5000 | I7: =MAX(0,C7-H7) -> 50000
A8: Pohela Boishakh 1434 | B8: 46491 | C8: =SUMIF($A$28:$A$67,A8,$C$28:$C$67) -> 8500 | D8: =SUMIF($A$28:$A$67,A8,$D$28:$D$67) -> 0 | E8: =C8-D8 -> 8500 | F8: =IF(B8="","",MAX(0,(YEAR(B8)-YEAR(TODAY()))*12+MONTH(B8)-MONTH(TODAY()))) -> 6 | G8: =IF(F8="","",IF(F8=0,I8,I8/F8)) -> 1416.6667 | H8: 0 | I8: =MAX(0,C8-H8) -> 8500
A9: Durga Puja / Other Festival 2027 | B9: 46668 | C9: =SUMIF($A$28:$A$67,A9,$C$28:$C$67) -> 11000 | D9: =SUMIF($A$28:$A$67,A9,$D$28:$D$67) -> 0 | E9: =C9-D9 -> 11000 | F9: =IF(B9="","",MAX(0,(YEAR(B9)-YEAR(TODAY()))*12+MONTH(B9)-MONTH(TODAY()))) -> 12 | G9: =IF(F9="","",IF(F9=0,I9,I9/F9)) -> 916.66667 | H9: 0 | I9: =MAX(0,C9-H9) -> 11000
A10: Weddings & Social Events | B10: 46736 | C10: =SUMIF($A$28:$A$67,A10,$C$28:$C$67) -> 30000 | D10: =SUMIF($A$28:$A$67,A10,$D$28:$D$67) -> 0 | E10: =C10-D10 -> 30000 | F10: =IF(B10="","",MAX(0,(YEAR(B10)-YEAR(TODAY()))*12+MONTH(B10)-MONTH(TODAY()))) -> 14 | G10: =IF(F10="","",IF(F10=0,I10,I10/F10)) -> 2142.8571 | H10: 0 | I10: =MAX(0,C10-H10) -> 30000
A11: TOTAL | C11: =SUM(C6:C10) -> 158980 | D11: =SUM(D6:D10) -> 0 | E11: =SUM(E6:E10) -> 158980 | G11: =SUM(G6:G10) -> 19515.048 | H11: =SUM(H6:H10) -> 20000 | I11: =SUM(I6:I10) -> 138980
A13: CALCULATORS
A14: Sadaqatul Fitr (Fitra)
A15: Family members | B15: 4
A16: Fitra per person (BDT) - use the amount announced by Islamic Foundation each year | B16: 120
A17: Total Fitra | B17: =B15*B16 -> 480
A19: Qurbani (Eid-ul-Adha)
A20: Price of one share (1/7 of a cow, BDT) - or full goat price | B20: 20000
A21: Number of shares / animals | B21: 1
A22: Total animal cost | B22: =B20*B21 -> 20000
A23: Meat processing, butcher & transport (BDT) | B23: 3000
A25: BUDGET DETAIL (add your own lines in the blank rows)
A27: Festival | B27: Item | C27: Budget (BDT) | D27: Actual (BDT) | E27: Variance | F27: Notes
A28: Eid-ul-Fitr 2027 | B28: New clothes for family | C28: 25000 | E28: =IF(C28="","",C28-N(D28)) -> 25000
A29: Eid-ul-Fitr 2027 | B29: Food, sweets & guests | C29: 8000 | E29: =IF(C29="","",C29-N(D29)) -> 8000
A30: Eid-ul-Fitr 2027 | B30: Salami / Eidi | C30: 5000 | E30: =IF(C30="","",C30-N(D30)) -> 5000
A31: Eid-ul-Fitr 2027 | B31: Travel to village (bus / launch / train) | C31: 10000 | E31: =IF(C31="","",C31-N(D31)) -> 10000
A32: Eid-ul-Fitr 2027 | B32: Gifts for parents & relatives | C32: 6000 | E32: =IF(C32="","",C32-N(D32)) -> 6000
A33: Eid-ul-Fitr 2027 | B33: Sadaqatul Fitr (Fitra) | C33: =$B$17 -> 480 | E33: =IF(C33="","",C33-N(D33)) -> 480
A34: Eid-ul-Adha 2027 | B34: Qurbani animal / share | C34: =$B$22 -> 20000 | E34: =IF(C34="","",C34-N(D34)) -> 20000
A35: Eid-ul-Adha 2027 | B35: Meat processing, butcher & transport | C35: =$B$23 -> 3000 | E35: =IF(C35="","",C35-N(D35)) -> 3000
A36: Eid-ul-Adha 2027 | B36: New clothes | C36: 15000 | E36: =IF(C36="","",C36-N(D36)) -> 15000
A37: Eid-ul-Adha 2027 | B37: Travel to village | C37: 8000 | E37: =IF(C37="","",C37-N(D37)) -> 8000
A38: Eid-ul-Adha 2027 | B38: Salami / Eidi | C38: 3000 | E38: =IF(C38="","",C38-N(D38)) -> 3000
A39: Eid-ul-Adha 2027 | B39: Feast & guests | C39: 6000 | E39: =IF(C39="","",C39-N(D39)) -> 6000
A40: Pohela Boishakh 1434 | B40: Panta-ilish & outing | C40: 4000 | E40: =IF(C40="","",C40-N(D40)) -> 4000
A41: Pohela Boishakh 1434 | B41: New clothes (saree / panjabi) | C41: 3000 | E41: =IF(C41="","",C41-N(D41)) -> 3000
A42: Pohela Boishakh 1434 | B42: Fair & small gifts | C42: 1500 | E42: =IF(C42="","",C42-N(D42)) -> 1500
A43: Durga Puja / Other Festival 2027 | B43: Clothes | C43: 6000 | E43: =IF(C43="","",C43-N(D43)) -> 6000
A44: Durga Puja / Other Festival 2027 | B44: Food & pandal visits | C44: 3000 | E44: =IF(C44="","",C44-N(D44)) -> 3000
A45: Durga Puja / Other Festival 2027 | B45: Gifts | C45: 2000 | E45: =IF(C45="","",C45-N(D45)) -> 2000
A46: Weddings & Social Events | B46: Gaye holud / wedding gift (cash envelope) | C46: 10000 | E46: =IF(C46="","",C46-N(D46)) -> 10000
A47: Weddings & Social Events | B47: Outfit | C47: 8000 | E47: =IF(C47="","",C47-N(D47)) -> 8000
... A49: Weddings & Social Events | B49: Aqiqah / Milad / other | C49: 5000 | E49: =IF(C49="","",C49-N(D49)) -> 5000
E50: =IF(C50="","",C50-N(D50))
E51: =IF(C51="","",C51-N(D51))
E52: =IF(C52="","",C52-N(D52))
E53: =IF(C53="","",C53-N(D53))
E54: =IF(C54="","",C54-N(D54))
E55: =IF(C55="","",C55-N(D55))
E56: =IF(C56="","",C56-N(D56))
E57: =IF(C57="","",C57-N(D57))
E58: =IF(C58="","",C58-N(D58))
E59: =IF(C59="","",C59-N(D59))
E60: =IF(C60="","",C60-N(D60))
E61: =IF(C61="","",C61-N(D61))
... E67: =IF(C67="","",C67-N(D67))

Sheet Bills
A1: BILLS & SUBSCRIPTIONS TRACKER | বিল
A2: Never miss a due date. Monthly equivalent and annual cost are calculated, and status flags overdue / due-soon bills. Update 'Next Due Date' after each payment. SAMPLE bills shown.
A5: Bill / Subscription | B5: Provider | C5: Expense Category | D5: Frequency | E5: Amount (BDT) | F5: Next Due Date | G5: Pay Via | H5: Monthly Equivalent | I5: Annual Cost | J5: Days to Due | K5: Status | L5: Notes
A6: House rent | B6: Landlord | C6: House Rent | D6: Monthly | E6: 22000 | F6: 46329 | G6: Bank Transfer / BEFTN | H6: =IF(OR(E6="",D6=""),"",E6/INDEX(Settings!$R$4:$R$7,MATCH(D6,Settings!$Q$4:$Q$7,0))) -> 22000 | I6: =IF(H6="","",H6*12) -> 264000 | J6: =IF(F6="","",F6-TODAY()) -> 14 | K6: =IF(J6="","",IF(J6<0,"Overdue",IF(J6<=7,"Due Soon",IF(J6<=30,"This Month","Upcoming")))) -> This Month | L6: Pay by 5th
A7: Electricity (prepaid) | B7: DESCO | C7: Electricity (DESCO / DPDC / REB) | D7: Monthly | E7: 3000 | F7: 46323 | G7: bKash | H7: =IF(OR(E7="",D7=""),"",E7/INDEX(Settings!$R$4:$R$7,MATCH(D7,Settings!$Q$4:$Q$7,0))) -> 3000 | I7: =IF(H7="","",H7*12) -> 36000 | J7: =IF(F7="","",F7-TODAY()) -> 8 | K7: =IF(J7="","",IF(J7<0,"Overdue",IF(J7<=7,"Due Soon",IF(J7<=30,"This Month","Upcoming")))) -> This Month | L7: Recharge when balance low
A8: Gas bill | B8: Titas Gas | C8: Gas (Titas / Bakhrabad / Jalalabad) | D8: Monthly | E8: 1080 | F8: 46336 | G8: bKash | H8: =IF(OR(E8="",D8=""),"",E8/INDEX(Settings!$R$4:$R$7,MATCH(D8,Settings!$Q$4:$Q$7,0))) -> 1080 | I8: =IF(H8="","",H8*12) -> 12960 | J8: =IF(F8="","",F8-TODAY()) -> 21 | K8: =IF(J8="","",IF(J8<0,"Overdue",IF(J8<=7,"Due Soon",IF(J8<=30,"This Month","Upcoming")))) -> This Month | L8: Double-burner tariff - verify
A9: Water & sewerage | B9: Dhaka WASA | C9: Water & Sewerage (WASA) | D9: Monthly | E9: 900 | F9: 46338 | G9: bKash | H9: =IF(OR(E9="",D9=""),"",E9/INDEX(Settings!$R$4:$R$7,MATCH(D9,Settings!$Q$4:$Q$7,0))) -> 900 | I9: =IF(H9="","",H9*12) -> 10800 | J9: =IF(F9="","",F9-TODAY()) -> 23 | K9: =IF(J9="","",IF(J9<0,"Overdue",IF(J9<=7,"Due Soon",IF(J9<=30,"This Month","Upcoming")))) -> This Month
A10: Broadband | B10: Link3 | C10: Internet / Broadband | D10: Monthly | E10: 1000 | F10: 46332 | G10: bKash | H10: =IF(OR(E10="",D10=""),"",E10/INDEX(Settings!$R$4:$R$7,MATCH(D10,Settings!$Q$4:$Q$7,0))) -> 1000 | I10: =IF(H10="","",H10*12) -> 12000 | J10: =IF(F10="","",F10-TODAY()) -> 17 | K10: =IF(J10="","",IF(J10<0,"Overdue",IF(J10<=7,"Due Soon",IF(J10<=30,"This Month","Upcoming")))) -> This Month
A11: Mobile postpaid / recharge | B11: Grameenphone | C11: Mobile Recharge & Data | D11: Monthly | E11: 700 | F11: 46335 | G11: bKash | H11: =IF(OR(E11="",D11=""),"",E11/INDEX(Settings!$R$4:$R$7,MATCH(D11,Settings!$Q$4:$Q$7,0))) -> 700 | I11: =IF(H11="","",H11*12) -> 8400 | J11: =IF(F11="","",F11-TODAY()) -> 20 | K11: =IF(J11="","",IF(J11<0,"Overdue",IF(J11<=7,"Due Soon",IF(J11<=30,"This Month","Upcoming")))) -> This Month
A12: Netflix + Chorki | B12: Streaming | C12: Entertainment & Subscriptions | D12: Monthly | E12: 1100 | F12: 46328 | G12: Credit Card | H12: =IF(OR(E12="",D12=""),"",E12/INDEX(Settings!$R$4:$R$7,MATCH(D12,Settings!$Q$4:$Q$7,0))) -> 1100 | I12: =IF(H12="","",H12*12) -> 13200 | J12: =IF(F12="","",F12-TODAY()) -> 13 | K12: =IF(J12="","",IF(J12<0,"Overdue",IF(J12<=7,"Due Soon",IF(J12<=30,"This Month","Upcoming")))) -> This Month | L12: Cancel if unused
A13: School tuition | B13: Child's school | C13: School / College / University Fees | D13: Monthly | E13: 3500 | F13: 46331 | G13: Bank Transfer / BEFTN | H13: =IF(OR(E13="",D13=""),"",E13/INDEX(Settings!$R$4:$R$7,MATCH(D13,Settings!$Q$4:$Q$7,0))) -> 3500 | I13: =IF(H13="","",H13*12) -> 42000 | J13: =IF(F13="","",F13-TODAY()) -> 16 | K13: =IF(J13="","",IF(J13<0,"Overdue",IF(J13<=7,"Due Soon",IF(J13<=30,"This Month","Upcoming")))) -> This Month
A14: Maid salary | B14: Domestic help | C14: Maid / Domestic Help | D14: Monthly | E14: 3000 | F14: 46331 | G14: Cash | H14: =IF(OR(E14="",D14=""),"",E14/INDEX(Settings!$R$4:$R$7,MATCH(D14,Settings!$Q$4:$Q$7,0))) -> 3000 | I14: =IF(H14="","",H14*12) -> 36000 | J14: =IF(F14="","",F14-TODAY()) -> 16 | K14: =IF(J14="","",IF(J14<0,"Overdue",IF(J14<=7,"Due Soon",IF(J14<=30,"This Month","Upcoming")))) -> This Month
A15: Life insurance premium | B15: Delta Life | C15: Insurance Premium | D15: Quarterly | E15: 7500 | F15: 46371 | G15: Auto-debit / Standing Order | H15: =IF(OR(E15="",D15=""),"",E15/INDEX(Settings!$R$4:$R$7,MATCH(D15,Settings!$Q$4:$Q$7,0))) -> 2500 | I15: =IF(H15="","",H15*12) -> 30000 | J15: =IF(F15="","",F15-TODAY()) -> 56 | K15: =IF(J15="","",IF(J15<0,"Overdue",IF(J15<=7,"Due Soon",IF(J15<=30,"This Month","Upcoming")))) -> Upcoming | L15: Tax-rebate eligible
A16: City Corporation holding tax | B16: Dhaka North City Corp. | C16: Service Charge & Holding Tax | D16: Yearly | E16: 9000 | F16: 46568 | G16: Bank Transfer / BEFTN | H16: =IF(OR(E16="",D16=""),"",E16/INDEX(Settings!$R$4:$R$7,MATCH(D16,Settings!$Q$4:$Q$7,0))) -> 750 | I16: =IF(H16="","",H16*12) -> 9000 | J16: =IF(F16="","",F16-TODAY()) -> 253 | K16: =IF(J16="","",IF(J16<0,"Overdue",IF(J16<=7,"Due Soon",IF(J16<=30,"This Month","Upcoming")))) -> Upcoming | L16: Due before fiscal year-end
A17: Motorcycle tax token & fitness | B17: BRTA | C17: Vehicle Maintenance & Parking | D17: Yearly | E17: 3500 | F17: 46418 | G17: Cash | H17: =IF(OR(E17="",D17=""),"",E17/INDEX(Settings!$R$4:$R$7,MATCH(D17,Settings!$Q$4:$Q$7,0))) -> 291.66667 | I17: =IF(H17="","",H17*12) -> 3500 | J17: =IF(F17="","",F17-TODAY()) -> 103 | K17: =IF(J17="","",IF(J17<0,"Overdue",IF(J17<=7,"Due Soon",IF(J17<=30,"This Month","Upcoming")))) -> Upcoming | L17: Renew on time
